Workbook

Sheet EmployeeLoan
A1: Employee Code | B1: Loan Amount | C1: LoanReleasedOn | D1: DeductFrom | E1: MonthlyAmount | F1: Status
A2: A1 | B2: 50000 | C2: march | D2: 44652 | E2: 8333
A3: A5 | B3: 20000 | C3: Sept | D3: 44835 | E3: 3333

Sheet SalaryMonth
B1: Month Start Date | C1: 26
B2: Salary Year | C2: 2022
A4: S.No | B4: Month | C4: Start Date | D4: End Date | E4: Work Days
A5: 1 | B5: 44652 | C5: 44646 | D5: 44676 | E5: =D5-C5+1 -> 31
A6: 2 | B6: 44682 | C6: 44677 | D6: 44706 | E6: =D6-C6+1 -> 30
A7: 3 | B7: 44713 | C7: 44707 | D7: 44737 | E7: =D7-C7+1 -> 31
A8: 4 | B8: 44743 | C8: 44738 | D8: 44767 | E8: =D8-C8+1 -> 30
A9: 5 | B9: 44774 | C9: 44768 | D9: 44798 | E9: =D9-C9+1 -> 31
A10: 6 | B10: 44805 | C10: 44799 | D10: 44829 | E10: =D10-C10+1 -> 31
A11: 7 | B11: 44835 | C11: 44830 | D11: 44859 | E11: =D11-C11+1 -> 30
A12: 8 | B12: 44866 | C12: 44860 | D12: 44890 | E12: =D12-C12+1 -> 31
A13: 9 | B13: 44896 | C13: 44891 | D13: 44920 | E13: =D13-C13+1 -> 30
A14: 10 | B14: 44927 | C14: 44921 | D14: 44951 | E14: =D14-C14+1 -> 31
A15: 11 | B15: 44958 | C15: 44952 | D15: 44982 | E15: =D15-C15+1 -> 31
A16: 12 | B16: 44986 | C16: 44983 | D16: 45010 | E16: =D16-C16+1 -> 28

Sheet Salary
A1: 1 | B1: =A1+1 -> 2 | C1: =B1+1 -> 3 | D1: =C1+1 -> 4 | E1: =D1+1 -> 5 | F1: =E1+1 -> 6 | G1: =F1+1 -> 7 | H1: =G1+1 -> 8 | I1: =H1+1 -> 9 | ... BB1: =BA1+1 -> 54
F2: Salary Actual | V2: Salary for pay | AB2: Salary Earned
A3: S.No | B3: Employee Code | C3: DOJ | D3: DOR | E3: Salary | F3: Basic | G3: HRA | H3: Medical & Transport Allowance | I3: Food Coupons | J3: Special Allowance | K3: Month | L3: Month Start | M3: Month End | N3: Month Days | O3: Is New Employee | P3: Is Left Employee | Q3: Employee Working days | R3: Days present | S3: LOP Days | T3: Late Coming days | U3: Unauthorized leaves | V3: Basic | W3: HRA | X3: Medical & Transport Allowance | Y3: Food Coupons | Z3: Special Allowance | AB3: Basic | AC3: HRA | AD3: Medical & Transport Allowance | AE3: Food Coupons | AF3: Special Allowance | AG3: Salary Earned (For ESI) | AH3: Arrears | AI3: Incentives | AJ3: Gross Earnings Total | AK3: LOP Amount | AL3: UA Amount | AM3: LC Amount | AN3: Staff Salary Advances | AO3: Food Coupons | AP3: Paycut | AQ3: Net Salary Earned | AR3: PT | AS3: Income Tax | AT3: PF Employee Contribution | AU3: ESI Employee Contribution | AV3: ESI Final | AW3: Gross Earnings | AX3: Gross Earnings For Tax | AY3: Gross Deduction | AZ3: Net Take Home | BA3: Comments | BB3: Income Tax Calculated This Month
A4: 1 | B4: A1 | C4: 40180 | E4: 62000 | F4: =E4*50% -> 31000 | G4: =F4*40% -> 12400 | H4: =IF(E4<11750,0,3500) -> 3500 | I4: 0 | J4: =E4-SUM(F4:I4) -> 15100 | K4: 44652 | L4: =VLOOKUP(K4,SalaryMonth!$B$5:$E$16,2,FALSE) -> 44646 | M4: =VLOOKUP(K4,SalaryMonth!$B$5:$E$16,3,FALSE) -> 44676 | N4: =VLOOKUP(K4,SalaryMonth!$B$5:$E$16,4,FALSE) -> 31 | O4: =IF(L4<=C4,"Y","N") -> N | P4: =IF(OR(D4<>"",M4<D4),"Y","N") -> N | Q4: 31 | R4: 28 | S4: 1 | T4: 1 | U4: 1 | V4: =ROUND((F4/N4)*Q4,0) -> 31000 | W4: =ROUND((G4/N4)*Q4,0) -> 12400 | X4: =ROUND((H4/N4)*Q4,0) -> 3500 | Y4: =(I4/N4)*Q4 -> 0 | Z4: =ROUND((J4/N4)*Q4,0) -> 15100 | AB4: =ROUND((V4/Q4)*Q4-(V4/Q4)*S4,0) -> 30000 | AC4: =ROUND((W4/Q4)*Q4-(W4/Q4)*S4,0) -> 12000 | AD4: =ROUND((X4/Q4)*Q4-(X4/Q4)*S4,0) -> 3387 | AE4: =Y4 -> 0 | AF4: =ROUND((Z4/Q4)*Q4-(Z4/Q4)*S4,0) -> 14613 | AG4: =SUM(AB4:AF4) -> 60000 | AH4: 1000 | AI4: 1000 | AJ4: =SUM(AB4:AI4) -> 122000 | AK4: =SUM(V4:Z4)-AG4 -> 2000 | AL4: =ROUND(E4*(U4/Q4),0) -> 2000 | AM4: =ROUND(E4*(T4/Q4),0) -> 2000 | AN4: 8333 | AO4: =AE4 -> 0 | AP4: 200 | AQ4: =SUM(F4:J4)-SUM(AK4:AP4) -> 47467 | AR4: =IF( AX4<15001,0,IF(AX4<20001,150,200)) -> 200 | AS4: 500 | AT4: =MIN( ROUND(AB4*12%,0),1800) -> 1800 | AU4: =ROUNDUP(IF(E4<=21000,AG4*1.75%,0),0) -> 0 | AV4: =AU4 -> 0 | AW4: =SUM(V4:Z4)+SUM(AH4:AI4) -> 64000 | AX4: =AW4-AP4-SUM(AK4:AM4) -> 57800 | AY4: =SUM(AK4:AP4)+SUM(AR4:AT4)+AV4 -> 17033 | AZ4: =AW4-AY4-BB4 -> 46967 | BA4: Arrears Incentives Added /Advance Deducted 8333/LATE Coming /UnAuthorized/incometax | BB4: 0
A5: =A4+1 -> 2 | B5: A2 | C5: 40180 | E5: 22000 | F5: =E5*50% -> 11000 | G5: =F5*40% -> 4400 | H5: =IF(E5<11750,0,3500) -> 3500 | I5: 0 | J5: =E5-SUM(F5:I5) -> 3100 | K5: 44652 | L5: =VLOOKUP(K5,SalaryMonth!$B$5:$E$16,2,FALSE) -> 44646 | M5: =VLOOKUP(K5,SalaryMonth!$B$5:$E$16,3,FALSE) -> 44676 | N5: =VLOOKUP(K5,SalaryMonth!$B$5:$E$16,4,FALSE) -> 31 | O5: =IF(L5<C5,"Y","N") -> N | P5: =IF(OR(D5<>"",M5<D5),"Y","N") -> N | Q5: 31 | R5: 29 | S5: 0 | T5: 0 | U5: 0 | V5: =ROUND((F5/N5)*Q5,0) -> 11000 | W5: =ROUND((G5/N5)*Q5,0) -> 4400 | X5: =ROUND((H5/N5)*Q5,0) -> 3500 | Y5: =(I5/N5)*Q5 -> 0 | Z5: =ROUND((J5/N5)*Q5,0) -> 3100 | AB5: =ROUND((V5/Q5)*Q5-(V5/Q5)*S5,0) -> 11000 | AC5: =ROUND((W5/Q5)*Q5-(W5/Q5)*S5,0) -> 4400 | AD5: =ROUND((X5/Q5)*Q5-(X5/Q5)*S5,0) -> 3500 | AE5: =I5 -> 0 | AF5: =ROUND((Z5/Q5)*Q5-(Z5/Q5)*S5,0) -> 3100 | AG5: =SUM(AB5:AF5) -> 22000 | AH5: 0 | AI5: 0 | AJ5: =SUM(AB5:AI5) -> 44000 | AK5: =SUM(V5:Z5)-AG5 -> 0 | AL5: =ROUND(E5*(U5/Q5),0) -> 0 | AM5: =ROUND(E5*(T5/Q5),0) -> 0 | AN5: 0 | AO5: =AE5 -> 0 | AP5: 0 | AQ5: =SUM(F5:J5)-SUM(AK5:AP5) -> 22000 | AR5: =IF( AX5<15001,0,IF(AX5<20001,150,200)) -> 200 | AS5: 0 | AT5: =MIN( ROUND(AB5*12%,0),1800) -> 1320 | AU5: =ROUNDUP(IF(E5<=21000,AG5*1.75%,0),0) -> 0 | AV5: =AU5 -> 0 | AW5: =SUM(V5:Z5)+SUM(AH5:AI5) -> 22000 | AX5: =AW5-AP5-SUM(AK5:AM5) -> 22000 | AY5: =SUM(AK5:AP5)+SUM(AR5:AT5)+AV5 -> 1520 | AZ5: =AW5-AY5-BB5 -> 20480 | BA5: ESI is not deducted because Employee salary is Not under ESI slab | BB5: 0
A6: =A5+1 -> 3 | B6: A3 | C6: 40181 | E6: 11000 | F6: =E6*50% -> 5500 | G6: =F6*40% -> 2200 | H6: =IF(E6<11750,0,3500) -> 0 | I6: 0 | J6: =E6-SUM(F6:I6) -> 3300 | K6: 44652 | L6: =VLOOKUP(K6,SalaryMonth!$B$5:$E$16,2,FALSE) -> 44646 | M6: =VLOOKUP(K6,SalaryMonth!$B$5:$E$16,3,FALSE) -> 44676 | N6: =VLOOKUP(K6,SalaryMonth!$B$5:$E$16,4,FALSE) -> 31 | O6: =IF(L6<C6,"Y","N") -> N | P6: =IF(OR(D6<>"",M6<D6),"Y","N") -> N | Q6: 31 | R6: 29 | S6: 0 | T6: 0 | U6: 0 | V6: =ROUND((F6/N6)*Q6,0) -> 5500 | W6: =ROUND((G6/N6)*Q6,0) -> 2200 | X6: =ROUND((H6/N6)*Q6,0) -> 0 | Y6: =(I6/N6)*Q6 -> 0 | Z6: =ROUND((J6/N6)*Q6,0) -> 3300 | AB6: =ROUND((V6/Q6)*Q6-(V6/Q6)*S6,0) -> 5500 | AC6: =ROUND((W6/Q6)*Q6-(W6/Q6)*S6,0) -> 2200 | AD6: =ROUND((X6/Q6)*Q6-(X6/Q6)*S6,0) -> 0 | AE6: =I6 -> 0 | AF6: =ROUND((Z6/Q6)*Q6-(Z6/Q6)*S6,0) -> 3300 | AG6: =SUM(AB6:AF6) -> 11000 | AH6: 0 | AI6: 0 | AJ6: =SUM(AB6:AI6) -> 22000 | AK6: =SUM(V6:Z6)-AG6 -> 0 | AL6: =ROUND(E6*(U6/Q6),0) -> 0 | AM6: =ROUND(E6*(T6/Q6),0) -> 0 | AN6: 0 | AO6: =AE6 -> 0 | AP6: 0 | AQ6: =SUM(F6:J6)-SUM(AK6:AP6) -> 11000 | AR6: =IF( AX6<15001,0,IF(AX6<20001,150,200)) -> 0 | AS6: 0 | AT6: =MIN( ROUND(AB6*12%,0),1800) -> 660 | AU6: =ROUNDUP(IF(E6<=21000,AG6*1.75%,0),0) -> 193 | AV6: =AU6 -> 193 | AW6: =SUM(V6:Z6)+SUM(AH6:AI6) -> 11000 | AX6: =AW6-AP6-SUM(AK6:AM6) -> 11000 | AY6: =SUM(AK6:AP6)+SUM(AR6:AT6)+AV6 -> 853 | AZ6: =AW6-AY6-BB6 -> 10147 | BA6: ESI is deducted because employee salary is under ESI slab
A7: =A6+1 -> 4 | B7: A4 | C7: 40182 | E7: 25000 | F7: =E7*50% -> 12500 | G7: =F7*40% -> 5000 | H7: =IF(E7<11750,0,3500) -> 3500 | I7: 0 | J7: =E7-SUM(F7:I7) -> 4000 | K7: 44652 | L7: =VLOOKUP(K7,SalaryMonth!$B$5:$E$16,2,FALSE) -> 44646 | M7: =VLOOKUP(K7,SalaryMonth!$B$5:$E$16,3,FALSE) -> 44676 | N7: =VLOOKUP(K7,SalaryMonth!$B$5:$E$16,4,FALSE) -> 31 | O7: =IF(L7<C7,"Y","N") -> N | P7: =IF(OR(D7<>"",M7<D7),"Y","N") -> N | Q7: 31 | R7: 29 | S7: 0 | T7: 0 | U7: 0 | V7: =ROUND((F7/N7)*Q7,0) -> 12500 | W7: =ROUND((G7/N7)*Q7,0) -> 5000 | X7: =ROUND((H7/N7)*Q7,0) -> 3500 | Y7: =(I7/N7)*Q7 -> 0 | Z7: =ROUND((J7/N7)*Q7,0) -> 4000 | AB7: =ROUND((V7/Q7)*Q7-(V7/Q7)*S7,0) -> 12500 | AC7: =ROUND((W7/Q7)*Q7-(W7/Q7)*S7,0) -> 5000 | AD7: =ROUND((X7/Q7)*Q7-(X7/Q7)*S7,0) -> 3500 | AE7: =I7 -> 0 | AF7: =ROUND((Z7/Q7)*Q7-(Z7/Q7)*S7,0) -> 4000 | AG7: =SUM(AB7:AF7) -> 25000 | AH7: 0 | AI7: 0 | AJ7: =SUM(AB7:AI7) -> 50000 | AK7: =SUM(V7:Z7)-AG7 -> 0 | AL7: =ROUND(E7*(U7/Q7),0) -> 0 | AM7: =ROUND(E7*(T7/Q7),0) -> 0 | AN7: 0 | AO7: =AE7 -> 0 | AP7: 0 | AQ7: =SUM(F7:J7)-SUM(AK7:AP7) -> 25000 | AR7: =IF( AX7<15001,0,IF(AX7<20001,150,200)) -> 200 | AS7: 0 | AT7: =MIN( ROUND(AB7*12%,0),1800) -> 1500 | AU7: =ROUNDUP(IF(E7<=21000,AG7*1.75%,0),0) -> 0 | AV7: =AU7 -> 0 | AW7: =SUM(V7:Z7)+SUM(AH7:AI7) -> 25000 | AX7: =AW7-AP7-SUM(AK7:AM7) -> 25000 | AY7: =SUM(AK7:AP7)+SUM(AR7:AT7)+AV7 -> 1700 | AZ7: =AW7-AY7-BB7 -> 23300
A8: =A7+1 -> 5 | B8: A5 | C8: 40183 | E8: 45000 | F8: =E8*50% -> 22500 | G8: =F8*40% -> 9000 | H8: =IF(E8<11750,0,3500) -> 3500 | I8: 2400 | J8: =E8-SUM(F8:I8) -> 7600 | K8: 44652 | L8: =VLOOKUP(K8,SalaryMonth!$B$5:$E$16,2,FALSE) -> 44646 | M8: =VLOOKUP(K8,SalaryMonth!$B$5:$E$16,3,FALSE) -> 44676 | N8: =VLOOKUP(K8,SalaryMonth!$B$5:$E$16,4,FALSE) -> 31 | O8: =IF(L8<C8,"Y","N") -> N | P8: =IF(OR(D8<>"",M8<D8),"Y","N") -> N | Q8: 31 | R8: 29 | S8: 0 | T8: 0 | U8: 0 | V8: =ROUND((F8/N8)*Q8,0) -> 22500 | W8: =ROUND((G8/N8)*Q8,0) -> 9000 | X8: =ROUND((H8/N8)*Q8,0) -> 3500 | Y8: =(I8/N8)*Q8 -> 2400 | Z8: =ROUND((J8/N8)*Q8,0) -> 7600 | AB8: =ROUND((V8/Q8)*Q8-(V8/Q8)*S8,0) -> 22500 | AC8: =ROUND((W8/Q8)*Q8-(W8/Q8)*S8,0) -> 9000 | AD8: =ROUND((X8/Q8)*Q8-(X8/Q8)*S8,0) -> 3500 | AE8: =I8 -> 2400 | AF8: =ROUND((Z8/Q8)*Q8-(Z8/Q8)*S8,0) -> 7600 | AG8: =SUM(AB8:AF8) -> 45000 | AH8: 0 | AI8: 0 | AJ8: =SUM(AB8:AI8) -> 90000 | AK8: =SUM(V8:Z8)-AG8 -> 0 | AL8: =ROUND(E8*(U8/Q8),0) -> 0 | AM8: =ROUND(E8*(T8/Q8),0) -> 0 | AN8: 0 | AO8: =AE8 -> 2400 | AP8: 0 | AQ8: =SUM(F8:J8)-SUM(AK8:AP8) -> 42600 | AR8: =IF( AX8<15001,0,IF(AX8<20001,150,200)) -> 200 | AS8: 2000 | AT8: =MIN( ROUND(AB8*12%,0),1800) -> 1800 | AU8: =ROUNDUP(IF(E8<=21000,AG8*1.75%,0),0) -> 0 | AV8: =AU8 -> 0 | AW8: =SUM(V8:Z8)+SUM(AH8:AI8) -> 45000 | AX8: =AW8-AP8-SUM(AK8:AM8) -> 45000 | AY8: =SUM(AK8:AP8)+SUM(AR8:AT8)+AV8 -> 6400 | AZ8: =AW8-AY8-BB8 -> 38600 | BA8: Income tax Added
A9: =A8+1 -> 6 | B9: B1 | C9: 40183 | E9: 120000 | F9: =E9*50% -> 60000 | G9: =F9*40% -> 24000 | H9: =IF(E9<11750,0,3500) -> 3500 | I9: 2400 | J9: =E9-SUM(F9:I9) -> 30100 | K9: 44652 | L9: =VLOOKUP(K9,SalaryMonth!$B$5:$E$16,2,FALSE) -> 44646 | M9: =VLOOKUP(K9,SalaryMonth!$B$5:$E$16,3,FALSE) -> 44676 | N9: =VLOOKUP(K9,SalaryMonth!$B$5:$E$16,4,FALSE) -> 31 | O9: =IF(L9<C9,"Y","N") -> N | P9: =IF(OR(D9<>"",M9<D9),"Y","N") -> N | Q9: 31 | R9: 31 | S9: 0 | T9: 0 | U9: 0 | V9: =ROUND((F9/N9)*Q9,0) -> 60000 | W9: =ROUND((G9/N9)*Q9,0) -> 24000 | X9: =ROUND((H9/N9)*Q9,0) -> 3500 | Y9: =(I9/N9)*Q9 -> 2400 | Z9: =ROUND((J9/N9)*Q9,0) -> 30100 | AB9: =ROUND((V9/Q9)*Q9-(V9/Q9)*S9,0) -> 60000 | AC9: =ROUND((W9/Q9)*Q9-(W9/Q9)*S9,0) -> 24000 | AD9: =ROUND((X9/Q9)*Q9-(X9/Q9)*S9,0) -> 3500 | AE9: =I9 -> 2400 | AF9: =ROUND((Z9/Q9)*Q9-(Z9/Q9)*S9,0) -> 30100 | AG9: =SUM(AB9:AF9) -> 120000 | AH9: 0 | AI9: 0 | AJ9: =SUM(AB9:AI9) -> 240000 | AK9: =SUM(V9:Z9)-AG9 -> 0 | AL9: =ROUND(E9*(U9/Q9),0) -> 0 | AM9: =ROUND(E9*(T9/Q9),0) -> 0 | AN9: 0 | AO9: =AE9 -> 2400 | AP9: 0 | AQ9: =SUM(F9:J9)-SUM(AK9:AP9) -> 117600 | AR9: =IF( AX9<15001,0,IF(AX9<20001,150,200)) -> 200 | AS9: 0 | AT9: =MIN( ROUND(AB9*12%,0),1800) -> 1800 | AU9: =ROUNDUP(IF(E9<=21000,AG9*1.75%,0),0) -> 0 | AV9: =AU9 -> 0 | AW9: =SUM(V9:Z9)+SUM(AH9:AI9) -> 120000 | AX9: =AW9-AP9-SUM(AK9:AM9) -> 120000 | AY9: =SUM(AK9:AP9)+SUM(AR9:AT9)+AV9 -> 4400 | AZ9: =AW9-AY9-BB9 -> 105280 | BA9: Income tax Added | BB9: 10320
A10: =A9+1 -> 7 | AK10: =SUM(V10:Z10)-AG10 -> 0 | AZ10: =AW10-AY10-BB10 -> 0
A11: =A10+1 -> 8 | B11: A1 | C11: 40180 | E11: 62000 | F11: =E11*50% -> 31000 | G11: =F11*40% -> 12400 | H11: =IF(E11<11750,0,3500) -> 3500 | I11: 0 | J11: =E11-SUM(F11:I11) -> 15100 | K11: 44682 | L11: =VLOOKUP(K11,SalaryMonth!$B$5:$E$16,2,FALSE) -> 44677 | M11: =VLOOKUP(K11,SalaryMonth!$B$5:$E$16,3,FALSE) -> 44706 | N11: =VLOOKUP(K11,SalaryMonth!$B$5:$E$16,4,FALSE) -> 30 | O11: =IF(L11<=C11,"Y","N") -> N | P11: =IF(OR(D11<>"",M11<D11),"Y","N") -> N | Q11: 30 | R11: 29 | S11: 1 | T11: 0 | U11: 0 | V11: =ROUND((F11/N11)*Q11,0) -> 31000 | W11: =ROUND((G11/N11)*Q11,0) -> 12400 | X11: =ROUND((H11/N11)*Q11,0) -> 3500 | Y11: =(I11/N11)*Q11 -> 0 | Z11: =ROUND((J11/N11)*Q11,0) -> 15100 | AB11: =ROUND((V11/Q11)*Q11-(V11/Q11)*S11,0) -> 29967 | AC11: =ROUND((W11/Q11)*Q11-(W11/Q11)*S11,0) -> 11987 | AD11: =ROUND((X11/Q11)*Q11-(X11/Q11)*S11,0) -> 3383 | AE11: =I11 -> 0 | AF11: =ROUND((Z11/Q11)*Q11-(Z11/Q11)*S11,0) -> 14597 | AG11: =SUM(AB11:AF11) -> 59934 | AH11: 0 | AI11: 1000 | AJ11: =SUM(AB11:AI11) -> 120868 | AK11: =SUM(V11:Z11)-AG11 -> 2066 | AL11: =ROUND(E11*(U11/Q11),0) -> 0 | AM11: =ROUND(E11*(T11/Q11),0) -> 0 | AN11: 8333 | AO11: =AE11 -> 0 | AP11: 0 | AQ11: =SUM(F11:J11)-SUM(AK11:AP11) -> 51601 | AR11: =IF( AX11<15001,0,IF(AX11<20001,150,200)) -> 200 | AS11: 0 | AT11: =MIN( ROUND(AB11*12%,0),1800) -> 1800 | AU11: =ROUNDUP(IF(E11<=21000,AG11*1.75%,0),0) -> 0 | AV11: =AU11 -> 0 | AW11: =SUM(V11:Z11)+SUM(AH11:AI11) -> 63000 | AX11: =AW11-AP11-SUM(AK11:AM11) -> 60934 | AY11: =SUM(AK11:AP11)+SUM(AR11:AT11)+AV11 -> 12399 | AZ11: =AW11-AY11-BB11 -> 47161 | BA11: incentives Added 1000rs/Advance Deducted 8333 | BB11: 3440
A12: =A11+1 -> 9 | B12: A2 | C12: 40180 | E12: 21000 | F12: =E12*50% -> 10500 | G12: =F12*40% -> 4200 | H12: =IF(E12<11750,0,3500) -> 3500 | I12: 0 | J12: =E12-SUM(F12:I12) -> 2800 | K12: 44682 | L12: =VLOOKUP(K12,SalaryMonth!$B$5:$E$16,2,FALSE) -> 44677 | M12: =VLOOKUP(K12,SalaryMonth!$B$5:$E$16,3,FALSE) -> 44706 | N12: =VLOOKUP(K12,SalaryMonth!$B$5:$E$16,4,FALSE) -> 30 | O12: =IF(L12<C12,"Y","N") -> N | P12: =IF(OR(D12<>"",M12<D12),"Y","N") -> N | Q12: 30 | R12: 29 | S12: 0 | T12: 0 | U12: 0 | V12: =ROUND((F12/N12)*Q12,0) -> 10500 | W12: =ROUND((G12/N12)*Q12,0) -> 4200 | X12: =ROUND((H12/N12)*Q12,0) -> 3500 | Y12: =(I12/N12)*Q12 -> 0 | Z12: =ROUND((J12/N12)*Q12,0) -> 2800 | AB12: =ROUND((V12/Q12)*Q12-(V12/Q12)*S12,0) -> 10500 | AC12: =ROUND((W12/Q12)*Q12-(W12/Q12)*S12,0) -> 4200 | AD12: =ROUND((X12/Q12)*Q12-(X12/Q12)*S12,0) -> 3500 | AE12: =Y12 -> 0 | AF12: =ROUND((Z12/Q12)*Q12-(Z12/Q12)*S12,0) -> 2800 | AG12: =SUM(AB12:AF12) -> 21000 | AH12: 0 | AI12: 0 | AJ12: =SUM(AB12:AI12) -> 42000 | AK12: =SUM(V12:Z12)-AG12 -> 0 | AL12: =ROUND(E12*(U12/Q12),0) -> 0 | AM12: =ROUND(E12*(T12/Q12),0) -> 0 | AN12: 0 | AO12: =AE12 -> 0 | AP12: 0 | AQ12: =SUM(F12:J12)-SUM(AK12:AP12) -> 21000 | AR12: =IF( AX12<15001,0,IF(AX12<20001,150,200)) -> 200 | AS12: 0 | AT12: =MIN( ROUND(AB12*12%,0),1800) -> 1260 | AU12: =ROUNDUP(IF(E12<=21000,AG12*1.75%,0),0) -> 368 | AV12: =AU12 -> 368 | AW12: =SUM(V12:Z12)+SUM(AH12:AI12) -> 21000 | AX12: =AW12-AP12-SUM(AK12:AM12) -> 21000 | AY12: =SUM(AK12:AP12)+SUM(AR12:AT12)+AV12 -> 1828 | AZ12: =AW12-AY12-BB12 -> 19172 | BA12: ESI is deducted because employee salary is under ESI slab
A13: =A12+1 -> 10 | B13: A3 | C13: 40181 | E13: 11000 | F13: =E13*50% -> 5500 | G13: =F13*40% -> 2200 | H13: =IF(E13<11750,0,3500) -> 0 | I13: 0 | J13: =E13-SUM(F13:I13) -> 3300 | K13: 44682 | L13: =VLOOKUP(K13,SalaryMonth!$B$5:$E$16,2,FALSE) -> 44677 | M13: =VLOOKUP(K13,SalaryMonth!$B$5:$E$16,3,FALSE) -> 44706 | N13: =VLOOKUP(K13,SalaryMonth!$B$5:$E$16,4,FALSE) -> 30 | O13: =IF(L13<C13,"Y","N") -> N | P13: =IF(OR(D13<>"",M13<D13),"Y","N") -> N | Q13: 30 | R13: 29 | S13: 0 | T13: 0 | U13: 0 | V13: =ROUND((F13/N13)*Q13,0) -> 5500 | W13: =ROUND((G13/N13)*Q13,0) -> 2200 | X13: =ROUND((H13/N13)*Q13,0) -> 0 | Y13: =(I13/N13)*Q13 -> 0 | Z13: =ROUND((J13/N13)*Q13,0) -> 3300 | AB13: =ROUND((V13/Q13)*Q13-(V13/Q13)*S13,0) -> 5500 | AC13: =ROUND((W13/Q13)*Q13-(W13/Q13)*S13,0) -> 2200 | AD13: =ROUND((X13/Q13)*Q13-(X13/Q13)*S13,0) -> 0 | AE13: =Y13 -> 0 | AF13: =ROUND((Z13/Q13)*Q13-(Z13/Q13)*S13,0) -> 3300 | AG13: =SUM(AB13:AF13) -> 11000 | AH13: 0 | AI13: 0 | AJ13: =SUM(AB13:AI13) -> 22000 | AK13: =SUM(V13:Z13)-AG13 -> 0 | AL13: =ROUND(E13*(U13/Q13),0) -> 0 | AM13: =ROUND(E13*(T13/Q13),0) -> 0 | AN13: 0 | AO13: =AE13 -> 0 | AP13: 0 | AQ13: =SUM(F13:J13)-SUM(AK13:AP13) -> 11000 | AR13: =IF( AX13<15001,0,IF(AX13<20001,150,200)) -> 0 | AS13: 0 | AT13: =MIN( ROUND(AB13*12%,0),1800) -> 660 | AU13: =ROUNDUP(IF(E13<=21000,AG13*1.75%,0),0) -> 193 | AV13: =AU13 -> 193 | AW13: =SUM(V13:Z13)+SUM(AH13:AI13) -> 11000 | AX13: =AW13-AP13-SUM(AK13:AM13) -> 11000 | AY13: =SUM(AK13:AP13)+SUM(AR13:AT13)+AV13 -> 853 | AZ13: =AW13-AY13-BB13 -> 10147 | BA13: ESI is deducted because employee salary is under ESI slab
A14: =A13+1 -> 11 | B14: A4 | C14: 40182 | E14: 25000 | F14: =E14*50% -> 12500 | G14: =F14*40% -> 5000 | H14: =IF(E14<11750,0,3500) -> 3500 | I14: 0 | J14: =E14-SUM(F14:I14) -> 4000 | K14: 44682 | L14: =VLOOKUP(K14,SalaryMonth!$B$5:$E$16,2,FALSE) -> 44677 | M14: =VLOOKUP(K14,SalaryMonth!$B$5:$E$16,3,FALSE) -> 44706 | N14: =VLOOKUP(K14,SalaryMonth!$B$5:$E$16,4,FALSE) -> 30 | O14: =IF(L14<C14,"Y","N") -> N | P14: =IF(OR(D14<>"",M14<D14),"Y","N") -> N | Q14: 30 | R14: 29 | S14: 0 | T14: 0 | U14: 0 | V14: =ROUND((F14/N14)*Q14,0) -> 12500 | W14: =ROUND((G14/N14)*Q14,0) -> 5000 | X14: =ROUND((H14/N14)*Q14,0) -> 3500 | Y14: =(I14/N14)*Q14 -> 0 | Z14: =ROUND((J14/N14)*Q14,0) -> 4000 | AB14: =ROUND((V14/Q14)*Q14-(V14/Q14)*S14,0) -> 12500 | AC14: =ROUND((W14/Q14)*Q14-(W14/Q14)*S14,0) -> 5000 | AD14: =ROUND((X14/Q14)*Q14-(X14/Q14)*S14,0) -> 3500 | AE14: =Y14 -> 0 | AF14: =ROUND((Z14/Q14)*Q14-(Z14/Q14)*S14,0) -> 4000 | AG14: =SUM(AB14:AF14) -> 25000 | AH14: 0 | AI14: 0 | AJ14: =SUM(AB14:AI14) -> 50000 | AK14: =SUM(V14:Z14)-AG14 -> 0 | AL14: =ROUND(E14*(U14/Q14),0) -> 0 | AM14: =ROUND(E14*(T14/Q14),0) -> 0 | AN14: 0 | AO14: =AE14 -> 0 | AP14: 0 | AQ14: =SUM(F14:J14)-SUM(AK14:AP14) -> 25000 | AR14: =IF( AX14<15001,0,IF(AX14<20001,150,200)) -> 200 | AS14: 0 | AT14: =MIN( ROUND(AB14*12%,0),1800) -> 1500 | AU14: =ROUNDUP(IF(E14<=21000,AG14*1.75%,0),0) -> 0 | AV14: =AU14 -> 0 | AW14: =SUM(V14:Z14)+SUM(AH14:AI14) -> 25000 | AX14: =AW14-AP14-SUM(AK14:AM14) -> 25000 | AY14: =SUM(AK14:AP14)+SUM(AR14:AT14)+AV14 -> 1700 | AZ14: =AW14-AY14-BB14 -> 23300
A15: =A14+1 -> 12 | B15: A5 | C15: 40183 | E15: 50000 | F15: =E15*50% -> 25000 | G15: =F15*40% -> 10000 | H15: =IF(E15<11750,0,3500) -> 3500 | I15: 2400 | J15: =E15-SUM(F15:I15) -> 9100 | K15: 44682 | L15: =VLOOKUP(K15,SalaryMonth!$B$5:$E$16,2,FALSE) -> 44677 | M15: =VLOOKUP(K15,SalaryMonth!$B$5:$E$16,3,FALSE) -> 44706 | N15: =VLOOKUP(K15,SalaryMonth!$B$5:$E$16,4,FALSE) -> 30 | O15: =IF(L15<C15,"Y","N") -> N | P15: =IF(OR(D15<>"",M15<D15),"Y","N") -> N | Q15: 30 | R15: 29 | S15: 0 | T15: 0 | U15: 0 | V15: =ROUND((F15/N15)*Q15,0) -> 25000 | W15: =ROUND((G15/N15)*Q15,0) -> 10000 | X15: =ROUND((H15/N15)*Q15,0) -> 3500 | Y15: =(I15/N15)*Q15 -> 2400 | Z15: =ROUND((J15/N15)*Q15,0) -> 9100 | AB15: =ROUND((V15/Q15)*Q15-(V15/Q15)*S15,0) -> 25000 | AC15: =ROUND((W15/Q15)*Q15-(W15/Q15)*S15,0) -> 10000 | AD15: =ROUND((X15/Q15)*Q15-(X15/Q15)*S15,0) -> 3500 | AE15: =Y15 -> 2400 | AF15: =ROUND((Z15/Q15)*Q15-(Z15/Q15)*S15,0) -> 9100 | AG15: =SUM(AB15:AF15) -> 50000 | AH15: 2000 | AI15: 0 | AJ15: =SUM(AB15:AI15) -> 102000 | AK15: =SUM(V15:Z15)-AG15 -> 0 | AL15: =ROUND(E15*(U15/Q15),0) -> 0 | AM15: =ROUND(E15*(T15/Q15),0) -> 0 | AN15: 0 | AO15: =AE15 -> 2400 | AP15: 0 | AQ15: =SUM(F15:J15)-SUM(AK15:AP15) -> 47600 | AR15: =IF( AX15<15001,0,IF(AX15<20001,150,200)) -> 200 | AS15: 2000 | AT15: =MIN( ROUND(AB15*12%,0),1800) -> 1800 | AU15: =ROUNDUP(IF(E15<=21000,AG15*1.75%,0),0) -> 0 | AV15: =AU15 -> 0 | AW15: =SUM(V15:Z15)+SUM(AH15:AI15) -> 52000 | AX15: =AW15-AP15-SUM(AK15:AM15) -> 52000 | AY15: =SUM(AK15:AP15)+SUM(AR15:AT15)+AV15 -> 6400 | AZ15: =AW15-AY15-BB15 -> 45600 | BA15: Income tax Added/Arrears Added
A16: =A15+1 -> 13 | B16: B1 | C16: 40183 | E16: 120000 | F16: =E16*50% -> 60000 | G16: =F16*40% -> 24000 | H16: =IF(E16<11750,0,3500) -> 3500 | I16: 2400 | J16: =E16-SUM(F16:I16) -> 30100 | K16: 44682 | L16: =VLOOKUP(K16,SalaryMonth!$B$5:$E$16,2,FALSE) -> 44677 | M16: =VLOOKUP(K16,SalaryMonth!$B$5:$E$16,3,FALSE) -> 44706 | N16: =VLOOKUP(K16,SalaryMonth!$B$5:$E$16,4,FALSE) -> 30 | O16: =IF(L16<C16,"Y","N") -> N | P16: =IF(OR(D16<>"",M16<D16),"Y","N") -> N | Q16: 30 | R16: 30 | S16: 0 | T16: 0 | U16: 0 | V16: =ROUND((F16/N16)*Q16,0) -> 60000 | W16: =ROUND((G16/N16)*Q16,0) -> 24000 | X16: =ROUND((H16/N16)*Q16,0) -> 3500 | Y16: =(I16/N16)*Q16 -> 2400 | Z16: =ROUND((J16/N16)*Q16,0) -> 30100 | AB16: =ROUND((V16/Q16)*Q16-(V16/Q16)*S16,0) -> 60000 | AC16: =ROUND((W16/Q16)*Q16-(W16/Q16)*S16,0) -> 24000 | AD16: =ROUND((X16/Q16)*Q16-(X16/Q16)*S16,0) -> 3500 | AE16: =I16 -> 2400 | AF16: =ROUND((Z16/Q16)*Q16-(Z16/Q16)*S16,0) -> 30100 | AG16: =SUM(AB16:AF16) -> 120000 | AH16: 0 | AI16: 0 | AJ16: =SUM(AB16:AI16) -> 240000 | AK16: =SUM(V16:Z16)-AG16 -> 0 | AL16: =ROUND(E16*(U16/Q16),0) -> 0 | AM16: =ROUND(E16*(T16/Q16),0) -> 0 | AN16: 0 | AO16: =AE16 -> 2400 | AP16: 0 | AQ16: =SUM(F16:J16)-SUM(AK16:AP16) -> 117600 | AR16: =IF( AX16<15001,0,IF(AX16<20001,150,200)) -> 200 | AS16: 0 | AT16: =MIN( ROUND(AB16*12%,0),1800) -> 1800 | AU16: =ROUNDUP(IF(E16<=21000,AG16*1.75%,0),0) -> 0 | AV16: =AU16 -> 0 | AW16: =SUM(V16:Z16)+SUM(AH16:AI16) -> 120000 | AX16: =AW16-AP16-SUM(AK16:AM16) -> 120000 | AY16: =SUM(AK16:AP16)+SUM(AR16:AT16)+AV16 -> 4400 | AZ16: =AW16-AY16-BB16 -> 105280 | BA16: Income tax Added | BB16: 10320
A17: =A16+1 -> 14 | AK17: =SUM(V17:Z17)-AG17 -> 0 | AZ17: =AW17-AY17-BB17 -> 0
A18: =A17+1 -> 15 | B18: A1 | C18: 40180 | E18: 62000 | F18: =E18*50% -> 31000 | G18: =F18*40% -> 12400 | H18: =IF(E18<11750,0,3500) -> 3500 | I18: 0 | J18: =E18-SUM(F18:I18) -> 15100 | K18: 44713 | L18: =VLOOKUP(K18,SalaryMonth!$B$5:$E$16,2,FALSE) -> 44707 | M18: =VLOOKUP(K18,SalaryMonth!$B$5:$E$16,3,FALSE) -> 44737 | N18: =VLOOKUP(K18,SalaryMonth!$B$5:$E$16,4,FALSE) -> 31 | O18: =IF(L18<=C18,"Y","N") -> N | P18: =IF(OR(D18<>"",M18<D18),"Y","N") -> N | Q18: 31 | R18: 29 | S18: 1 | T18: 0 | U18: 0 | V18: =ROUND((F18/N18)*Q18,0) -> 31000 | W18: =ROUND((G18/N18)*Q18,0) -> 12400 | X18: =ROUND((H18/N18)*Q18,0) -> 3500 | Y18: =(I18/N18)*Q18 -> 0 | Z18: =ROUND((J18/N18)*Q18,0) -> 15100 | AB18: =ROUND((V18/Q18)*Q18-(V18/Q18)*S18,0) -> 30000 | AC18: =ROUND((W18/Q18)*Q18-(W18/Q18)*S18,0) -> 12000 | AD18: =ROUND((X18/Q18)*Q18-(X18/Q18)*S18,0) -> 3387 | AE18: =Y18 -> 0 | AF18: =ROUND((Z18/Q18)*Q18-(Z18/Q18)*S18,0) -> 14613 | AG18: =SUM(AB18:AF18) -> 60000 | AH18: 0 | AI18: 0 | AJ18: =SUM(AB18:AI18) -> 120000 | AK18: =SUM(V18:Z18)-AG18 -> 2000 | AL18: =ROUND(E18*(U18/Q18),0) -> 0 | AM18: =ROUND(E18*(T18/Q18),0) -> 0 | AN18: 8333 | AO18: =AE18 -> 0 | AP18: 0 | AQ18: =SUM(F18:J18)-SUM(AK18:AP18) -> 51667 | AR18: =IF( AX18<15001,0,IF(AX18<20001,150,200)) -> 200 | AS18: 0 | AT18: =MIN( ROUND(AB18*12%,0),1800) -> 1800 | AU18: =ROUNDUP(IF(E18<=21000,AG18*1.75%,0),0) -> 0 | AV18: =AU18 -> 0 | AW18: =SUM(V18:Z18)+SUM(AH18:AI18) -> 62000 | AX18: =AW18-AP18-SUM(AK18:AM18) -> 60000 | AY18: =SUM(AK18:AP18)+SUM(AR18:AT18)+AV18 -> 12333 | AZ18: =AW18-AY18-BB18 -> 46297 | BA18: /Advance Deducted 8333 | BB18: 3370
A19: =A18+1 -> 16 | B19: A2 | C19: 40180 | E19: 24000 | F19: =E19*50% -> 12000 | G19: =F19*40% -> 4800 | H19: =IF(E19<11750,0,3500) -> 3500 | I19: 0 | J19: =E19-SUM(F19:I19) -> 3700 | K19: 44713 | L19: =VLOOKUP(K19,SalaryMonth!$B$5:$E$16,2,FALSE) -> 44707 | M19: =VLOOKUP(K19,SalaryMonth!$B$5:$E$16,3,FALSE) -> 44737 | N19: =VLOOKUP(K19,SalaryMonth!$B$5:$E$16,4,FALSE) -> 31 | O19: =IF(L19<C19,"Y","N") -> N | P19: =IF(OR(D19<>"",M19<D19),"Y","N") -> N | Q19: 31 | R19: 29 | S19: 0 | T19: 0 | U19: 0 | V19: =ROUND((F19/N19)*Q19,0) -> 12000 | W19: =ROUND((G19/N19)*Q19,0) -> 4800 | X19: =ROUND((H19/N19)*Q19,0) -> 3500 | Y19: =(I19/N19)*Q19 -> 0 | Z19: =ROUND((J19/N19)*Q19,0) -> 3700 | AB19: =ROUND((V19/Q19)*Q19-(V19/Q19)*S19,0) -> 12000 | AC19: =ROUND((W19/Q19)*Q19-(W19/Q19)*S19,0) -> 4800 | AD19: =ROUND((X19/Q19)*Q19-(X19/Q19)*S19,0) -> 3500 | AE19: =Y19 -> 0 | AF19: =ROUND((Z19/Q19)*Q19-(Z19/Q19)*S19,0) -> 3700 | AG19: =SUM(AB19:AF19) -> 24000 | AH19: 0 | AI19: 0 | AJ19: =SUM(AB19:AI19) -> 48000 | AK19: =SUM(V19:Z19)-AG19 -> 0 | AL19: =ROUND(E19*(U19/Q19),0) -> 0 | AM19: =ROUND(E19*(T19/Q19),0) -> 0 | AN19: 0 | AO19: =AE19 -> 0 | AP19: 0 | AQ19: =SUM(F19:J19)-SUM(AK19:AP19) -> 24000 | AR19: =IF( AX19<15001,0,IF(AX19<20001,150,200)) -> 200 | AS19: 0 | AT19: =MIN( ROUND(AB19*12%,0),1800) -> 1440 | AU19: =ROUNDUP(IF(E19<=21000,AG19*1.75%,0),0) -> 0 | AV19: =ROUNDUP(AG19 *1.75%,0) -> 420 | AW19: =SUM(V19:Z19)+SUM(AH19:AI19) -> 24000 | AX19: =AW19-AP19-SUM(AK19:AM19) -> 24000 | AY19: =SUM(AK19:AP19)+SUM(AR19:AT19)+AV19 -> 2060 | AZ19: =AW19-AY19-BB19 -> 21940 | BA19: ESI should be deducted because ESI is deducted in May month it will continue up to sep irrespective of salary
A20: =A19+1 -> 17 | B20: A3 | C20: 40181 | E20: 11000 | F20: =E20*50% -> 5500 | G20: =F20*40% -> 2200 | H20: =IF(E20<11750,0,3500) -> 0 | I20: 0 | J20: =E20-SUM(F20:I20) -> 3300 | K20: 44713 | L20: =VLOOKUP(K20,SalaryMonth!$B$5:$E$16,2,FALSE) -> 44707 | M20: =VLOOKUP(K20,SalaryMonth!$B$5:$E$16,3,FALSE) -> 44737 | N20: =VLOOKUP(K20,SalaryMonth!$B$5:$E$16,4,FALSE) -> 31 | O20: =IF(L20<C20,"Y","N") -> N | P20: =IF(OR(D20<>"",M20<D20),"Y","N") -> N | Q20: 31 | R20: 29 | S20: 0 | T20: 0 | U20: 0 | V20: =ROUND((F20/N20)*Q20,0) -> 5500 | W20: =ROUND((G20/N20)*Q20,0) -> 2200 | X20: =ROUND((H20/N20)*Q20,0) -> 0 | Y20: =(I20/N20)*Q20 -> 0 | Z20: =ROUND((J20/N20)*Q20,0) -> 3300 | AB20: =ROUND((V20/Q20)*Q20-(V20/Q20)*S20,0) -> 5500 | AC20: =ROUND((W20/Q20)*Q20-(W20/Q20)*S20,0) -> 2200 | AD20: =ROUND((X20/Q20)*Q20-(X20/Q20)*S20,0) -> 0 | AE20: =Y20 -> 0 | AF20: =ROUND((Z20/Q20)*Q20-(Z20/Q20)*S20,0) -> 3300 | AG20: =SUM(AB20:AF20) -> 11000 | AH20: 0 | AI20: 0 | AJ20: =SUM(AB20:AI20) -> 22000 | AK20: =SUM(V20:Z20)-AG20 -> 0 | AL20: =ROUND(E20*(U20/Q20),0) -> 0 | AM20: =ROUND(E20*(T20/Q20),0) -> 0 | AN20: 0 | AO20: =AE20 -> 0 | AP20: 0 | AQ20: =SUM(F20:J20)-SUM(AK20:AP20) -> 11000 | AR20: =IF( AX20<15001,0,IF(AX20<20001,150,200)) -> 0 | AS20: 0 | AT20: =MIN( ROUND(AB20*12%,0),1800) -> 660 | AU20: =ROUNDUP(IF(E20<=21000,AG20*1.75%,0),0) -> 193 | AV20: =AU20 -> 193 | AW20: =SUM(V20:Z20)+SUM(AH20:AI20) -> 11000 | AX20: =AW20-AP20-SUM(AK20:AM20) -> 11000 | AY20: =SUM(AK20:AP20)+SUM(AR20:AT20)+AV20 -> 853 | AZ20: =AW20-AY20-BB20 -> 10147 | BA20: ESI is deducted because employee salary is under ESI slab
A21: =A20+1 -> 18 | B21: A4 | C21: 40182 | E21: 25000 | F21: =E21*50% -> 12500 | G21: =F21*40% -> 5000 | H21: =IF(E21<11750,0,3500) -> 3500 | I21: 0 | J21: =E21-SUM(F21:I21) -> 4000 | K21: 44713 | L21: =VLOOKUP(K21,SalaryMonth!$B$5:$E$16,2,FALSE) -> 44707 | M21: =VLOOKUP(K21,SalaryMonth!$B$5:$E$16,3,FALSE) -> 44737 | N21: =VLOOKUP(K21,SalaryMonth!$B$5:$E$16,4,FALSE) -> 31 | O21: =IF(L21<C21,"Y","N") -> N | P21: =IF(OR(D21<>"",M21<D21),"Y","N") -> N | Q21: 31 | R21: 29 | S21: 0 | T21: 0 | U21: 0 | V21: =ROUND((F21/N21)*Q21,0) -> 12500 | W21: =ROUND((G21/N21)*Q21,0) -> 5000 | X21: =ROUND((H21/N21)*Q21,0) -> 3500 | Y21: =(I21/N21)*Q21 -> 0 | Z21: =ROUND((J21/N21)*Q21,0) -> 4000 | AB21: =ROUND((V21/Q21)*Q21-(V21/Q21)*S21,0) -> 12500 | AC21: =ROUND((W21/Q21)*Q21-(W21/Q21)*S21,0) -> 5000 | AD21: =ROUND((X21/Q21)*Q21-(X21/Q21)*S21,0) -> 3500 | AE21: =Y21 -> 0 | AF21: =ROUND((Z21/Q21)*Q21-(Z21/Q21)*S21,0) -> 4000 | AG21: =SUM(AB21:AF21) -> 25000 | AH21: 0 | AI21: 0 | AJ21: =SUM(AB21:AI21) -> 50000 | AK21: =SUM(V21:Z21)-AG21 -> 0 | AL21: =ROUND(E21*(U21/Q21),0) -> 0 | AM21: =ROUND(E21*(T21/Q21),0) -> 0 | AN21: 0 | AO21: =AE21 -> 0 | AP21: 0 | AQ21: =SUM(F21:J21)-SUM(AK21:AP21) -> 25000 | AR21: =IF( AX21<15001,0,IF(AX21<20001,150,200)) -> 200 | AS21: 0 | AT21: =MIN( ROUND(AB21*12%,0),1800) -> 1500 | AU21: =ROUNDUP(IF(E21<=21000,AG21*1.75%,0),0) -> 0 | AV21: =AU21 -> 0 | AW21: =SUM(V21:Z21)+SUM(AH21:AI21) -> 25000 | AX21: =AW21-AP21-SUM(AK21:AM21) -> 25000 | AY21: =SUM(AK21:AP21)+SUM(AR21:AT21)+AV21 -> 1700 | AZ21: =AW21-AY21-BB21 -> 23300
A22: =A21+1 -> 19 | B22: A5 | C22: 40183 | E22: 32000 | F22: =E22*50% -> 16000 | G22: =F22*40% -> 6400 | H22: =IF(E22<11750,0,3500) -> 3500 | I22: 0 | J22: =E22-SUM(F22:I22) -> 6100 | K22: 44713 | L22: =VLOOKUP(K22,SalaryMonth!$B$5:$E$16,2,FALSE) -> 44707 | M22: =VLOOKUP(K22,SalaryMonth!$B$5:$E$16,3,FALSE) -> 44737 | N22: =VLOOKUP(K22,SalaryMonth!$B$5:$E$16,4,FALSE) -> 31 | O22: =IF(L22<C22,"Y","N") -> N | P22: =IF(OR(D22<>"",M22<D22),"Y","N") -> N | Q22: 31 | R22: 29 | S22: 0 | T22: 0 | U22: 0 | V22: =ROUND((F22/N22)*Q22,0) -> 16000 | W22: =ROUND((G22/N22)*Q22,0) -> 6400 | X22: =ROUND((H22/N22)*Q22,0) -> 3500 | Y22: =(I22/N22)*Q22 -> 0 | Z22: =ROUND((J22/N22)*Q22,0) -> 6100 | AB22: =ROUND((V22/Q22)*Q22-(V22/Q22)*S22,0) -> 16000 | AC22: =ROUND((W22/Q22)*Q22-(W22/Q22)*S22,0) -> 6400 | AD22: =ROUND((X22/Q22)*Q22-(X22/Q22)*S22,0) -> 3500 | AE22: =Y22 -> 0 | AF22: =ROUND((Z22/Q22)*Q22-(Z22/Q22)*S22,0) -> 6100 | AG22: =SUM(AB22:AF22) -> 32000 | AH22: 0 | AI22: 0 | AJ22: =SUM(AB22:AI22) -> 64000 | AK22: =SUM(V22:Z22)-AG22 -> 0 | AL22: =ROUND(E22*(U22/Q22),0) -> 0 | AM22: =ROUND(E22*(T22/Q22),0) -> 0 | AN22: 0 | AO22: =AE22 -> 0 | AP22: 0 | AQ22: =SUM(F22:J22)-SUM(AK22:AP22) -> 32000 | AR22: =IF( AX22<15001,0,IF(AX22<20001,150,200)) -> 200 | AS22: 0 | AT22: =MIN( ROUND(AB22*12%,0),1800) -> 1800 | AU22: =ROUNDUP(IF(E22<=21000,AG22*1.75%,0),0) -> 0 | AV22: =AU22 -> 0 | AW22: =SUM(V22:Z22)+SUM(AH22:AI22) -> 32000 | AX22: =AW22-AP22-SUM(AK22:AM22) -> 32000 | AY22: =SUM(AK22:AP22)+SUM(AR22:AT22)+AV22 -> 2000 | AZ22: =AW22-AY22-BB22 -> 30000
A23: =A22+1 -> 20 | B23: B1 | C23: 40183 | E23: 120000 | F23: =E23*50% -> 60000 | G23: =F23*40% -> 24000 | H23: =IF(E23<11750,0,3500) -> 3500 | I23: 2400 | J23: =E23-SUM(F23:I23) -> 30100 | K23: 44713 | L23: =VLOOKUP(K23,SalaryMonth!$B$5:$E$16,2,FALSE) -> 44707 | M23: =VLOOKUP(K23,SalaryMonth!$B$5:$E$16,3,FALSE) -> 44737 | N23: =VLOOKUP(K23,SalaryMonth!$B$5:$E$16,4,FALSE) -> 31 | O23: =IF(L23<C23,"Y","N") -> N | P23: =IF(OR(D23<>"",M23<D23),"Y","N") -> N | Q23: 31 | R23: 31 | S23: 0 | T23: 0 | U23: 0 | V23: =ROUND((F23/N23)*Q23,0) -> 60000 | W23: =ROUND((G23/N23)*Q23,0) -> 24000 | X23: =ROUND((H23/N23)*Q23,0) -> 3500 | Y23: =(I23/N23)*Q23 -> 2400 | Z23: =ROUND((J23/N23)*Q23,0) -> 30100 | AB23: =ROUND((V23/Q23)*Q23-(V23/Q23)*S23,0) -> 60000 | AC23: =ROUND((W23/Q23)*Q23-(W23/Q23)*S23,0) -> 24000 | AD23: =ROUND((X23/Q23)*Q23-(X23/Q23)*S23,0) -> 3500 | AE23: =I23 -> 2400 | AF23: =ROUND((Z23/Q23)*Q23-(Z23/Q23)*S23,0) -> 30100 | AG23: =SUM(AB23:AF23) -> 120000 | AH23: 0 | AI23: 0 | AJ23: =SUM(AB23:AI23) -> 240000 | AK23: =SUM(V23:Z23)-AG23 -> 0 | AL23: =ROUND(E23*(U23/Q23),0) -> 0 | AM23: =ROUND(E23*(T23/Q23),0) -> 0 | AN23: 0 | AO23: =AE23 -> 2400 | AP23: 0 | AQ23: =SUM(F23:J23)-SUM(AK23:AP23) -> 117600 | AR23: =IF( AX23<15001,0,IF(AX23<20001,150,200)) -> 200 | AS23: 0 | AT23: =MIN( ROUND(AB23*12%,0),1800) -> 1800 | AU23: =ROUNDUP(IF(E23<=21000,AG23*1.75%,0),0) -> 0 | AV23: =AU23 -> 0 | AW23: =SUM(V23:Z23)+SUM(AH23:AI23) -> 120000 | AX23: =AW23-AP23-SUM(AK23:AM23) -> 120000 | AY23: =SUM(AK23:AP23)+SUM(AR23:AT23)+AV23 -> 4400 | AZ23: =AW23-AY23-BB23 -> 105280 | BA23: Income tax Added | BB23: 10320
A24: =A23+1 -> 21 | AK24: =SUM(V24:Z24)-AG24 -> 0 | AZ24: =AW24-AY24-BB24 -> 0
A25: =A24+1 -> 22 | B25: A1 | C25: 40180 | E25: 62000 | F25: =E25*50% -> 31000 | G25: =F25*40% -> 12400 | H25: =IF(E25<11750,0,3500) -> 3500 | I25: 0 | J25: =E25-SUM(F25:I25) -> 15100 | K25: 44743 | L25: =VLOOKUP(K25,SalaryMonth!$B$5:$E$16,2,FALSE) -> 44738 | M25: =VLOOKUP(K25,SalaryMonth!$B$5:$E$16,3,FALSE) -> 44767 | N25: =VLOOKUP(K25,SalaryMonth!$B$5:$E$16,4,FALSE) -> 30 | O25: =IF(L25<=C25,"Y","N") -> N | P25: =IF(OR(D25<>"",M25<D25),"Y","N") -> N | Q25: 30 | R25: 29 | S25: 1 | T25: 0 | U25: 0 | V25: =ROUND((F25/N25)*Q25,0) -> 31000 | W25: =ROUND((G25/N25)*Q25,0) -> 12400 | X25: =ROUND((H25/N25)*Q25,0) -> 3500 | Y25: =(I25/N25)*Q25 -> 0 | Z25: =ROUND((J25/N25)*Q25,0) -> 15100 | AB25: =ROUND((V25/Q25)*Q25-(V25/Q25)*S25,0) -> 29967 | AC25: =ROUND((W25/Q25)*Q25-(W25/Q25)*S25,0) -> 11987 | AD25: =ROUND((X25/Q25)*Q25-(X25/Q25)*S25,0) -> 3383 | AE25: =Y25 -> 0 | AF25: =ROUND((Z25/Q25)*Q25-(Z25/Q25)*S25,0) -> 14597 | AG25: =SUM(AB25:AF25) -> 59934 | AH25: 0 | AI25: 0 | AJ25: =SUM(AB25:AI25) -> 119868 | AK25: =SUM(V25:Z25)-AG25 -> 2066 | AL25: =ROUND(E25*(U25/Q25),0) -> 0 | AM25: =ROUND(E25*(T25/Q25),0) -> 0 | AN25: 8333 | AO25: =AE25 -> 0 | AP25: 0 | AQ25: =SUM(F25:J25)-SUM(AK25:AP25) -> 51601 | AR25: =IF( AX25<15001,0,IF(AX25<20001,150,200)) -> 200 | AS25: 2000 | AT25: =MIN( ROUND(AB25*12%,0),1800) -> 1800 | AU25: =ROUNDUP(IF(E25<=21000,AG25*1.75%,0),0) -> 0 | AV25: =AU25 -> 0 | AW25: =SUM(V25:Z25)+SUM(AH25:AI25) -> 62000 | AX25: =AW25-AP25-SUM(AK25:AM25) -> 59934 | AY25: =SUM(AK25:AP25)+SUM(AR25:AT25)+AV25 -> 14399 | AZ25: =AW25-AY25-BB25 -> 47601 | BA25: Advance Deducted 8333/income Tax
A26: =A25+1 -> 23 | B26: A2 | C26: 40180 | E26: 25000 | F26: =E26*50% -> 12500 | G26: =F26*40% -> 5000 | H26: =IF(E26<11750,0,3500) -> 3500 | I26: 0 | J26: =E26-SUM(F26:I26) -> 4000 | K26: 44743 | L26: =VLOOKUP(K26,SalaryMonth!$B$5:$E$16,2,FALSE) -> 44738 | M26: =VLOOKUP(K26,SalaryMonth!$B$5:$E$16,3,FALSE) -> 44767 | N26: =VLOOKUP(K26,SalaryMonth!$B$5:$E$16,4,FALSE) -> 30 | O26: =IF(L26<C26,"Y","N") -> N | P26: =IF(OR(D26<>"",M26<D26),"Y","N") -> N | Q26: 30 | R26: 29 | S26: 0 | T26: 0 | U26: 0 | V26: =ROUND((F26/N26)*Q26,0) -> 12500 | W26: =ROUND((G26/N26)*Q26,0) -> 5000 | X26: =ROUND((H26/N26)*Q26,0) -> 3500 | Y26: =(I26/N26)*Q26 -> 0 | Z26: =ROUND((J26/N26)*Q26,0) -> 4000 | AB26: =ROUND((V26/Q26)*Q26-(V26/Q26)*S26,0) -> 12500 | AC26: =ROUND((W26/Q26)*Q26-(W26/Q26)*S26,0) -> 5000 | AD26: =ROUND((X26/Q26)*Q26-(X26/Q26)*S26,0) -> 3500 | AE26: =Y26 -> 0 | AF26: =ROUND((Z26/Q26)*Q26-(Z26/Q26)*S26,0) -> 4000 | AG26: =SUM(AB26:AF26) -> 25000 | AH26: 0 | AI26: 0 | AJ26: =SUM(AB26:AI26) -> 50000 | AK26: =SUM(V26:Z26)-AG26 -> 0 | AL26: =ROUND(E26*(U26/Q26),0) -> 0 | AM26: =ROUND(E26*(T26/Q26),0) -> 0 | AN26: 0 | AO26: =AE26 -> 0 | AP26: 0 | AQ26: =SUM(F26:J26)-SUM(AK26:AP26) -> 25000 | AR26: =IF( AX26<15001,0,IF(AX26<20001,150,200)) -> 200 | AS26: 0 | AT26: =MIN( ROUND(AB26*12%,0),1800) -> 1500 | AU26: =ROUNDUP(IF(E26<=21000,AG26*1.75%,0),0) -> 0 | AV26: =ROUNDUP(AG26 *1.75%,0) -> 438 | AW26: =SUM(V26:Z26)+SUM(AH26:AI26) -> 25000 | AX26: =AW26-AP26-SUM(AK26:AM26) -> 25000 | AY26: =SUM(AK26:AP26)+SUM(AR26:AT26)+AV26 -> 2138 | AZ26: =AW26-AY26-BB26 -> 22862 | BA26: ESI should be deducted because ESI is deducted in May month it will continue up to sep irrespective of salary
A27: =A26+1 -> 24 | B27: A3 | C27: 40181 | E27: 11000 | F27: =E27*50% -> 5500 | G27: =F27*40% -> 2200 | H27: =IF(E27<11750,0,3500) -> 0 | I27: 0 | J27: =E27-SUM(F27:I27) -> 3300 | K27: 44743 | L27: =VLOOKUP(K27,SalaryMonth!$B$5:$E$16,2,FALSE) -> 44738 | M27: =VLOOKUP(K27,SalaryMonth!$B$5:$E$16,3,FALSE) -> 44767 | N27: =VLOOKUP(K27,SalaryMonth!$B$5:$E$16,4,FALSE) -> 30 | O27: =IF(L27<C27,"Y","N") -> N | P27: =IF(OR(D27<>"",M27<D27),"Y","N") -> N | Q27: 30 | R27: 29 | S27: 0 | T27: 0 | U27: 0 | V27: =ROUND((F27/N27)*Q27,0) -> 5500 | W27: =ROUND((G27/N27)*Q27,0) -> 2200 | X27: =ROUND((H27/N27)*Q27,0) -> 0 | Y27: =(I27/N27)*Q27 -> 0 | Z27: =ROUND((J27/N27)*Q27,0) -> 3300 | AB27: =ROUND((V27/Q27)*Q27-(V27/Q27)*S27,0) -> 5500 | AC27: =ROUND((W27/Q27)*Q27-(W27/Q27)*S27,0) -> 2200 | AD27: =ROUND((X27/Q27)*Q27-(X27/Q27)*S27,0) -> 0 | AE27: =Y27 -> 0 | AF27: =ROUND((Z27/Q27)*Q27-(Z27/Q27)*S27,0) -> 3300 | AG27: =SUM(AB27:AF27) -> 11000 | AH27: 0 | AI27: 0 | AJ27: =SUM(AB27:AI27) -> 22000 | AK27: =SUM(V27:Z27)-AG27 -> 0 | AL27: =ROUND(E27*(U27/Q27),0) -> 0 | AM27: =ROUND(E27*(T27/Q27),0) -> 0 | AN27: 0 | AO27: =AE27 -> 0 | AP27: 0 | AQ27: =SUM(F27:J27)-SUM(AK27:AP27) -> 11000 | AR27: =IF( AX27<15001,0,IF(AX27<20001,150,200)) -> 0 | AS27: 0 | AT27: =MIN( ROUND(AB27*12%,0),1800) -> 660 | AU27: =ROUNDUP(IF(E27<=21000,AG27*1.75%,0),0) -> 193 | AV27: =AU27 -> 193 | AW27: =SUM(V27:Z27)+SUM(AH27:AI27) -> 11000 | AX27: =AW27-AP27-SUM(AK27:AM27) -> 11000 | AY27: =SUM(AK27:AP27)+SUM(AR27:AT27)+AV27 -> 853 | AZ27: =AW27-AY27-BB27 -> 10147 | BA27: ESI is deducted because employee salary is under ESI slab
A28: =A27+1 -> 25 | B28: A4 | C28: 40182 | E28: 25000 | F28: =E28*50% -> 12500 | G28: =F28*40% -> 5000 | H28: =IF(E28<11750,0,3500) -> 3500 | I28: 0 | J28: =E28-SUM(F28:I28) -> 4000 | K28: 44743 | L28: =VLOOKUP(K28,SalaryMonth!$B$5:$E$16,2,FALSE) -> 44738 | M28: =VLOOKUP(K28,SalaryMonth!$B$5:$E$16,3,FALSE) -> 44767 | N28: =VLOOKUP(K28,SalaryMonth!$B$5:$E$16,4,FALSE) -> 30 | O28: =IF(L28<C28,"Y","N") -> N | P28: =IF(OR(D28<>"",M28<D28),"Y","N") -> N | Q28: 30 | R28: 29 | S28: 0 | T28: 0 | U28: 0 | V28: =ROUND((F28/N28)*Q28,0) -> 12500 | W28: =ROUND((G28/N28)*Q28,0) -> 5000 | X28: =ROUND((H28/N28)*Q28,0) -> 3500 | Y28: =(I28/N28)*Q28 -> 0 | Z28: =ROUND((J28/N28)*Q28,0) -> 4000 | AB28: =ROUND((V28/Q28)*Q28-(V28/Q28)*S28,0) -> 12500 | AC28: =ROUND((W28/Q28)*Q28-(W28/Q28)*S28,0) -> 5000 | AD28: =ROUND((X28/Q28)*Q28-(X28/Q28)*S28,0) -> 3500 | AE28: =Y28 -> 0 | AF28: =ROUND((Z28/Q28)*Q28-(Z28/Q28)*S28,0) -> 4000 | AG28: =SUM(AB28:AF28) -> 25000 | AH28: 0 | AI28: 0 | AJ28: =SUM(AB28:AI28) -> 50000 | AK28: =SUM(V28:Z28)-AG28 -> 0 | AL28: =ROUND(E28*(U28/Q28),0) -> 0 | AM28: =ROUND(E28*(T28/Q28),0) -> 0 | AN28: 0 | AO28: =AE28 -> 0 | AP28: 2000 | AQ28: =SUM(F28:J28)-SUM(AK28:AP28) -> 23000 | AR28: =IF( AX28<15001,0,IF(AX28<20001,150,200)) -> 200 | AS28: 0 | AT28: =MIN( ROUND(AB28*12%,0),1800) -> 1500 | AU28: =ROUNDUP(IF(E28<=21000,AG28*1.75%,0),0) -> 0 | AV28: =AU28 -> 0 | AW28: =SUM(V28:Z28)+SUM(AH28:AI28) -> 25000 | AX28: =AW28-AP28-SUM(AK28:AM28) -> 23000 | AY28: =SUM(AK28:AP28)+SUM(AR28:AT28)+AV28 -> 3700 | AZ28: =AW28-AY28-BB28 -> 21300 | BA28: Paycut added 2000
A29: =A28+1 -> 26 | B29: A5 | C29: 40183 | E29: 32000 | F29: =E29*50% -> 16000 | G29: =F29*40% -> 6400 | H29: =IF(E29<11750,0,3500) -> 3500 | I29: 0 | J29: =E29-SUM(F29:I29) -> 6100 | K29: 44743 | L29: =VLOOKUP(K29,SalaryMonth!$B$5:$E$16,2,FALSE) -> 44738 | M29: =VLOOKUP(K29,SalaryMonth!$B$5:$E$16,3,FALSE) -> 44767 | N29: =VLOOKUP(K29,SalaryMonth!$B$5:$E$16,4,FALSE) -> 30 | O29: =IF(L29<C29,"Y","N") -> N | P29: =IF(OR(D29<>"",M29<D29),"Y","N") -> N | Q29: 30 | R29: 29 | S29: 0 | T29: 0 | U29: 0 | V29: =ROUND((F29/N29)*Q29,0) -> 16000 | W29: =ROUND((G29/N29)*Q29,0) -> 6400 | X29: =ROUND((H29/N29)*Q29,0) -> 3500 | Y29: =(I29/N29)*Q29 -> 0 | Z29: =ROUND((J29/N29)*Q29,0) -> 6100 | AB29: =ROUND((V29/Q29)*Q29-(V29/Q29)*S29,0) -> 16000 | AC29: =ROUND((W29/Q29)*Q29-(W29/Q29)*S29,0) -> 6400 | AD29: =ROUND((X29/Q29)*Q29-(X29/Q29)*S29,0) -> 3500 | AE29: =Y29 -> 0 | AF29: =ROUND((Z29/Q29)*Q29-(Z29/Q29)*S29,0) -> 6100 | AG29: =SUM(AB29:AF29) -> 32000 | AH29: 0 | AI29: 0 | AJ29: =SUM(AB29:AI29) -> 64000 | AK29: =SUM(V29:Z29)-AG29 -> 0 | AL29: =ROUND(E29*(U29/Q29),0) -> 0 | AM29: =ROUND(E29*(T29/Q29),0) -> 0 | AN29: 0 | AO29: =AE29 -> 0 | AP29: 0 | AQ29: =SUM(F29:J29)-SUM(AK29:AP29) -> 32000 | AR29: =IF( AX29<15001,0,IF(AX29<20001,150,200)) -> 200 | AS29: 0 | AT29: =MIN( ROUND(AB29*12%,0),1800) -> 1800 | AU29: =ROUNDUP(IF(E29<=21000,AG29*1.75%,0),0) -> 0 | AV29: =AU29 -> 0 | AW29: =SUM(V29:Z29)+SUM(AH29:AI29) -> 32000 | AX29: =AW29-AP29-SUM(AK29:AM29) -> 32000 | AY29: =SUM(AK29:AP29)+SUM(AR29:AT29)+AV29 -> 2000 | AZ29: =AW29-AY29-BB29 -> 30000
A30: =A29+1 -> 27 | B30: B1 | C30: 40183 | E30: 120000 | F30: =E30*50% -> 60000 | G30: =F30*40% -> 24000 | H30: =IF(E30<11750,0,3500) -> 3500 | I30: 2400 | J30: =E30-SUM(F30:I30) -> 30100 | K30: 44743 | L30: =VLOOKUP(K30,SalaryMonth!$B$5:$E$16,2,FALSE) -> 44738 | M30: =VLOOKUP(K30,SalaryMonth!$B$5:$E$16,3,FALSE) -> 44767 | N30: =VLOOKUP(K30,SalaryMonth!$B$5:$E$16,4,FALSE) -> 30 | O30: =IF(L30<C30,"Y","N") -> N | P30: =IF(OR(D30<>"",M30<D30),"Y","N") -> N | Q30: 30 | R30: 30 | S30: 0 | T30: 0 | U30: 0 | V30: =ROUND((F30/N30)*Q30,0) -> 60000 | W30: =ROUND((G30/N30)*Q30,0) -> 24000 | X30: =ROUND((H30/N30)*Q30,0) -> 3500 | Y30: =(I30/N30)*Q30 -> 2400 | Z30: =ROUND((J30/N30)*Q30,0) -> 30100 | AB30: =ROUND((V30/Q30)*Q30-(V30/Q30)*S30,0) -> 60000 | AC30: =ROUND((W30/Q30)*Q30-(W30/Q30)*S30,0) -> 24000 | AD30: =ROUND((X30/Q30)*Q30-(X30/Q30)*S30,0) -> 3500 | AE30: =I30 -> 2400 | AF30: =ROUND((Z30/Q30)*Q30-(Z30/Q30)*S30,0) -> 30100 | AG30: =SUM(AB30:AF30) -> 120000 | AH30: 0 | AI30: 0 | AJ30: =SUM(AB30:AI30) -> 240000 | AK30: =SUM(V30:Z30)-AG30 -> 0 | AL30: =ROUND(E30*(U30/Q30),0) -> 0 | AM30: =ROUND(E30*(T30/Q30),0) -> 0 | AN30: 0 | AO30: =AE30 -> 2400 | AP30: 0 | AQ30: =SUM(F30:J30)-SUM(AK30:AP30) -> 117600 | AR30: =IF( AX30<15001,0,IF(AX30<20001,150,200)) -> 200 | AS30: 0 | AT30: =MIN( ROUND(AB30*12%,0),1800) -> 1800 | AU30: =ROUNDUP(IF(E30<=21000,AG30*1.75%,0),0) -> 0 | AV30: =AU30 -> 0 | AW30: =SUM(V30:Z30)+SUM(AH30:AI30) -> 120000 | AX30: =AW30-AP30-SUM(AK30:AM30) -> 120000 | AY30: =SUM(AK30:AP30)+SUM(AR30:AT30)+AV30 -> 4400 | AZ30: =AW30-AY30-BB30 -> 105280 | BA30: Income tax Added | BB30: 10320
A31: =A30+1 -> 28 | AK31: =SUM(V31:Z31)-AG31 -> 0 | AZ31: =AW31-AY31-BB31 -> 0
A32: =A31+1 -> 29 | B32: A1 | C32: 40180 | E32: 62000 | F32: =E32*50% -> 31000 | G32: =F32*40% -> 12400 | H32: =IF(E32<11750,0,3500) -> 3500 | I32: 0 | J32: =E32-SUM(F32:I32) -> 15100 | K32: 44774 | L32: =VLOOKUP(K32,SalaryMonth!$B$5:$E$16,2,FALSE) -> 44768 | M32: =VLOOKUP(K32,SalaryMonth!$B$5:$E$16,3,FALSE) -> 44798 | N32: =VLOOKUP(K32,SalaryMonth!$B$5:$E$16,4,FALSE) -> 31 | O32: =IF(L32<=C32,"Y","N") -> N | P32: =IF(OR(D32<>"",M32<D32),"Y","N") -> N | Q32: 31 | R32: 29 | S32: 1 | T32: 0 | U32: 0 | V32: =ROUND((F32/N32)*Q32,0) -> 31000 | W32: =ROUND((G32/N32)*Q32,0) -> 12400 | X32: =ROUND((H32/N32)*Q32,0) -> 3500 | Y32: =(I32/N32)*Q32 -> 0 | Z32: =ROUND((J32/N32)*Q32,0) -> 15100 | AB32: =ROUND((V32/Q32)*Q32-(V32/Q32)*S32,0) -> 30000 | AC32: =ROUND((W32/Q32)*Q32-(W32/Q32)*S32,0) -> 12000 | AD32: =ROUND((X32/Q32)*Q32-(X32/Q32)*S32,0) -> 3387 | AE32: =Y32 -> 0 | AF32: =ROUND((Z32/Q32)*Q32-(Z32/Q32)*S32,0) -> 14613 | AG32: =SUM(AB32:AF32) -> 60000 | AH32: 0 | AI32: 0 | AJ32: =SUM(AB32:AI32) -> 120000 | AK32: =SUM(V32:Z32)-AG32 -> 2000 | AL32: =ROUND(E32*(U32/Q32),0) -> 0 | AM32: =ROUND(E32*(T32/Q32),0) -> 0 | AN32: 8333 | AO32: =AE32 -> 0 | AP32: 0 | AQ32: =SUM(F32:J32)-SUM(AK32:AP32) -> 51667 | AR32: =IF( AX32<15001,0,IF(AX32<20001,150,200)) -> 200 | AS32: 200 | AT32: =MIN( ROUND(AB32*12%,0),1800) -> 1800 | AU32: =ROUNDUP(IF(E32<=21000,AG32*1.75%,0),0) -> 0 | AV32: =AU32 -> 0 | AW32: =SUM(V32:Z32)+SUM(AH32:AI32) -> 62000 | AX32: =AW32-AP32-SUM(AK32:AM32) -> 60000 | AY32: =SUM(AK32:AP32)+SUM(AR32:AT32)+AV32 -> 12533 | AZ32: =AW32-AY32-BB32 -> 49467 | BA32: Advance Deducted 8333/income tax
A33: =A32+1 -> 30 | B33: A2 | C33: 40180 | E33: 17000 | F33: =E33*50% -> 8500 | G33: =F33*40% -> 3400 | H33: =IF(E33<11750,0,3500) -> 3500 | I33: 0 | J33: =E33-SUM(F33:I33) -> 1600 | K33: 44774 | L33: =VLOOKUP(K33,SalaryMonth!$B$5:$E$16,2,FALSE) -> 44768 | M33: =VLOOKUP(K33,SalaryMonth!$B$5:$E$16,3,FALSE) -> 44798 | N33: =VLOOKUP(K33,SalaryMonth!$B$5:$E$16,4,FALSE) -> 31 | O33: =IF(L33<C33,"Y","N") -> N | P33: =IF(OR(D33<>"",M33<D33),"Y","N") -> N | Q33: 31 | R33: 29 | S33: 0 | T33: 0 | U33: 0 | V33: =ROUND((F33/N33)*Q33,0) -> 8500 | W33: =ROUND((G33/N33)*Q33,0) -> 3400 | X33: =ROUND((H33/N33)*Q33,0) -> 3500 | Y33: =(I33/N33)*Q33 -> 0 | Z33: =ROUND((J33/N33)*Q33,0) -> 1600 | AB33: =ROUND((V33/Q33)*Q33-(V33/Q33)*S33,0) -> 8500 | AC33: =ROUND((W33/Q33)*Q33-(W33/Q33)*S33,0) -> 3400 | AD33: =ROUND((X33/Q33)*Q33-(X33/Q33)*S33,0) -> 3500 | AE33: =Y33 -> 0 | AF33: =ROUND((Z33/Q33)*Q33-(Z33/Q33)*S33,0) -> 1600 | AG33: =SUM(AB33:AF33) -> 17000 | AH33: 0 | AI33: 0 | AJ33: =SUM(AB33:AI33) -> 34000 | AK33: =SUM(V33:Z33)-AG33 -> 0 | AL33: =ROUND(E33*(U33/Q33),0) -> 0 | AM33: =ROUND(E33*(T33/Q33),0) -> 0 | AN33: 0 | AO33: =AE33 -> 0 | AP33: 0 | AQ33: =SUM(F33:J33)-SUM(AK33:AP33) -> 17000 | AR33: =IF( AX33<15001,0,IF(AX33<20001,150,200)) -> 150 | AS33: 0 | AT33: =MIN( ROUND(AB33*12%,0),1800) -> 1020 | AU33: =ROUNDUP(IF(E33<=21000,AG33*1.75%,0),0) -> 298 | AV33: =AU33 -> 298 | AW33: =SUM(V33:Z33)+SUM(AH33:AI33) -> 17000 | AX33: =AW33-AP33-SUM(AK33:AM33) -> 17000 | AY33: =SUM(AK33:AP33)+SUM(AR33:AT33)+AV33 -> 1468 | AZ33: =AW33-AY33-BB33 -> 15532 | BA33: ESI should be deducted because ESI is deducted in May month it will continue up to sep irrespective of salary
A34: =A33+1 -> 31 | B34: A3 | C34: 40181 | E34: 11000 | F34: =E34*50% -> 5500 | G34: =F34*40% -> 2200 | H34: =IF(E34<11750,0,3500) -> 0 | I34: 0 | J34: =E34-SUM(F34:I34) -> 3300 | K34: 44774 | L34: =VLOOKUP(K34,SalaryMonth!$B$5:$E$16,2,FALSE) -> 44768 | M34: =VLOOKUP(K34,SalaryMonth!$B$5:$E$16,3,FALSE) -> 44798 | N34: =VLOOKUP(K34,SalaryMonth!$B$5:$E$16,4,FALSE) -> 31 | O34: =IF(L34<C34,"Y","N") -> N | P34: =IF(OR(D34<>"",M34<D34),"Y","N") -> N | Q34: 31 | R34: 29 | S34: 0 | T34: 0 | U34: 0 | V34: =ROUND((F34/N34)*Q34,0) -> 5500 | W34: =ROUND((G34/N34)*Q34,0) -> 2200 | X34: =ROUND((H34/N34)*Q34,0) -> 0 | Y34: =(I34/N34)*Q34 -> 0 | Z34: =ROUND((J34/N34)*Q34,0) -> 3300 | AB34: =ROUND((V34/Q34)*Q34-(V34/Q34)*S34,0) -> 5500 | AC34: =ROUND((W34/Q34)*Q34-(W34/Q34)*S34,0) -> 2200 | AD34: =ROUND((X34/Q34)*Q34-(X34/Q34)*S34,0) -> 0 | AE34: =Y34 -> 0 | AF34: =ROUND((Z34/Q34)*Q34-(Z34/Q34)*S34,0) -> 3300 | AG34: =SUM(AB34:AF34) -> 11000 | AH34: 0 | AI34: 0 | AJ34: =SUM(AB34:AI34) -> 22000 | AK34: =SUM(V34:Z34)-AG34 -> 0 | AL34: =ROUND(E34*(U34/Q34),0) -> 0 | AM34: =ROUND(E34*(T34/Q34),0) -> 0 | AN34: 0 | AO34: =AE34 -> 0 | AP34: 0 | AQ34: =SUM(F34:J34)-SUM(AK34:AP34) -> 11000 | AR34: =IF( AX34<15001,0,IF(AX34<20001,150,200)) -> 0 | AS34: 0 | AT34: =MIN( ROUND(AB34*12%,0),1800) -> 660 | AU34: =ROUNDUP(IF(E34<=21000,AG34*1.75%,0),0) -> 193 | AV34: =AU34 -> 193 | AW34: =SUM(V34:Z34)+SUM(AH34:AI34) -> 11000 | AX34: =AW34-AP34-SUM(AK34:AM34) -> 11000 | AY34: =SUM(AK34:AP34)+SUM(AR34:AT34)+AV34 -> 853 | AZ34: =AW34-AY34-BB34 -> 10147 | BA34: ESI is deducted because employee salary is under ESI slab
A35: =A34+1 -> 32 | B35: A4 | C35: 40182 | E35: 25000 | F35: =E35*50% -> 12500 | G35: =F35*40% -> 5000 | H35: =IF(E35<11750,0,3500) -> 3500 | I35: 0 | J35: =E35-SUM(F35:I35) -> 4000 | K35: 44774 | L35: =VLOOKUP(K35,SalaryMonth!$B$5:$E$16,2,FALSE) -> 44768 | M35: =VLOOKUP(K35,SalaryMonth!$B$5:$E$16,3,FALSE) -> 44798 | N35: =VLOOKUP(K35,SalaryMonth!$B$5:$E$16,4,FALSE) -> 31 | O35: =IF(L35<C35,"Y","N") -> N | P35: =IF(OR(D35<>"",M35<D35),"Y","N") -> N | Q35: 31 | R35: 29 | S35: 0 | T35: 0 | U35: 0 | V35: =ROUND((F35/N35)*Q35,0) -> 12500 | W35: =ROUND((G35/N35)*Q35,0) -> 5000 | X35: =ROUND((H35/N35)*Q35,0) -> 3500 | Y35: =(I35/N35)*Q35 -> 0 | Z35: =ROUND((J35/N35)*Q35,0) -> 4000 | AB35: =ROUND((V35/Q35)*Q35-(V35/Q35)*S35,0) -> 12500 | AC35: =ROUND((W35/Q35)*Q35-(W35/Q35)*S35,0) -> 5000 | AD35: =ROUND((X35/Q35)*Q35-(X35/Q35)*S35,0) -> 3500 | AE35: =Y35 -> 0 | AF35: =ROUND((Z35/Q35)*Q35-(Z35/Q35)*S35,0) -> 4000 | AG35: =SUM(AB35:AF35) -> 25000 | AH35: 0 | AI35: 0 | AJ35: =SUM(AB35:AI35) -> 50000 | AK35: =SUM(V35:Z35)-AG35 -> 0 | AL35: =ROUND(E35*(U35/Q35),0) -> 0 | AM35: =ROUND(E35*(T35/Q35),0) -> 0 | AN35: 0 | AO35: =AE35 -> 0 | AP35: 2000 | AQ35: =SUM(F35:J35)-SUM(AK35:AP35) -> 23000 | AR35: =IF( AX35<15001,0,IF(AX35<20001,150,200)) -> 200 | AS35: 0 | AT35: =MIN( ROUND(AB35*12%,0),1800) -> 1500 | AU35: =ROUNDUP(IF(E35<=21000,AG35*1.75%,0),0) -> 0 | AV35: =AU35 -> 0 | AW35: =SUM(V35:Z35)+SUM(AH35:AI35) -> 25000 | AX35: =AW35-AP35-SUM(AK35:AM35) -> 23000 | AY35: =SUM(AK35:AP35)+SUM(AR35:AT35)+AV35 -> 3700 | AZ35: =AW35-AY35-BB35 -> 21300 | BA35: paycut added 2000
A36: =A35+1 -> 33 | B36: A5 | C36: 40183 | E36: 32000 | F36: =E36*50% -> 16000 | G36: =F36*40% -> 6400 | H36: =IF(E36<11750,0,3500) -> 3500 | I36: 0 | J36: =E36-SUM(F36:I36) -> 6100 | K36: 44774 | L36: =VLOOKUP(K36,SalaryMonth!$B$5:$E$16,2,FALSE) -> 44768 | M36: =VLOOKUP(K36,SalaryMonth!$B$5:$E$16,3,FALSE) -> 44798 | N36: =VLOOKUP(K36,SalaryMonth!$B$5:$E$16,4,FALSE) -> 31 | O36: =IF(L36<C36,"Y","N") -> N | P36: =IF(OR(D36<>"",M36<D36),"Y","N") -> N | Q36: 31 | R36: 29 | S36: 0 | T36: 0 | U36: 0 | V36: =ROUND((F36/N36)*Q36,0) -> 16000 | W36: =ROUND((G36/N36)*Q36,0) -> 6400 | X36: =ROUND((H36/N36)*Q36,0) -> 3500 | Y36: =(I36/N36)*Q36 -> 0 | Z36: =ROUND((J36/N36)*Q36,0) -> 6100 | AB36: =ROUND((V36/Q36)*Q36-(V36/Q36)*S36,0) -> 16000 | AC36: =ROUND((W36/Q36)*Q36-(W36/Q36)*S36,0) -> 6400 | AD36: =ROUND((X36/Q36)*Q36-(X36/Q36)*S36,0) -> 3500 | AE36: =Y36 -> 0 | AF36: =ROUND((Z36/Q36)*Q36-(Z36/Q36)*S36,0) -> 6100 | AG36: =SUM(AB36:AF36) -> 32000 | AH36: 0 | AI36: 0 | AJ36: =SUM(AB36:AI36) -> 64000 | AK36: =SUM(V36:Z36)-AG36 -> 0 | AL36: =ROUND(E36*(U36/Q36),0) -> 0 | AM36: =ROUND(E36*(T36/Q36),0) -> 0 | AN36: 0 | AO36: =AE36 -> 0 | AP36: 0 | AQ36: =SUM(F36:J36)-SUM(AK36:AP36) -> 32000 | AR36: =IF( AX36<15001,0,IF(AX36<20001,150,200)) -> 200 | AS36: 0 | AT36: =MIN( ROUND(AB36*12%,0),1800) -> 1800 | AU36: =ROUNDUP(IF(E36<=21000,AG36*1.75%,0),0) -> 0 | AV36: =AU36 -> 0 | AW36: =SUM(V36:Z36)+SUM(AH36:AI36) -> 32000 | AX36: =AW36-AP36-SUM(AK36:AM36) -> 32000 | AY36: =SUM(AK36:AP36)+SUM(AR36:AT36)+AV36 -> 2000 | AZ36: =AW36-AY36-BB36 -> 30000
A37: =A36+1 -> 34 | B37: B1 | C37: 40183 | E37: 120000 | F37: =E37*50% -> 60000 | G37: =F37*40% -> 24000 | H37: =IF(E37<11750,0,3500) -> 3500 | I37: 2400 | J37: =E37-SUM(F37:I37) -> 30100 | K37: 44774 | L37: =VLOOKUP(K37,SalaryMonth!$B$5:$E$16,2,FALSE) -> 44768 | M37: =VLOOKUP(K37,SalaryMonth!$B$5:$E$16,3,FALSE) -> 44798 | N37: =VLOOKUP(K37,SalaryMonth!$B$5:$E$16,4,FALSE) -> 31 | O37: =IF(L37<C37,"Y","N") -> N | P37: =IF(OR(D37<>"",M37<D37),"Y","N") -> N | Q37: 31 | R37: 31 | S37: 0 | T37: 0 | U37: 0 | V37: =ROUND((F37/N37)*Q37,0) -> 60000 | W37: =ROUND((G37/N37)*Q37,0) -> 24000 | X37: =ROUND((H37/N37)*Q37,0) -> 3500 | Y37: =(I37/N37)*Q37 -> 2400 | Z37: =ROUND((J37/N37)*Q37,0) -> 30100 | AB37: =ROUND((V37/Q37)*Q37-(V37/Q37)*S37,0) -> 60000 | AC37: =ROUND((W37/Q37)*Q37-(W37/Q37)*S37,0) -> 24000 | AD37: =ROUND((X37/Q37)*Q37-(X37/Q37)*S37,0) -> 3500 | AE37: =I37 -> 2400 | AF37: =ROUND((Z37/Q37)*Q37-(Z37/Q37)*S37,0) -> 30100 | AG37: =SUM(AB37:AF37) -> 120000 | AH37: 0 | AI37: 0 | AJ37: =SUM(AB37:AI37) -> 240000 | AK37: =SUM(V37:Z37)-AG37 -> 0 | AL37: =ROUND(E37*(U37/Q37),0) -> 0 | AM37: =ROUND(E37*(T37/Q37),0) -> 0 | AN37: 0 | AO37: =AE37 -> 2400 | AP37: 0 | AQ37: =SUM(F37:J37)-SUM(AK37:AP37) -> 117600 | AR37: =IF( AX37<15001,0,IF(AX37<20001,150,200)) -> 200 | AS37: 0 | AT37: =MIN( ROUND(AB37*12%,0),1800) -> 1800 | AU37: =ROUNDUP(IF(E37<=21000,AG37*1.75%,0),0) -> 0 | AV37: =AU37 -> 0 | AW37: =SUM(V37:Z37)+SUM(AH37:AI37) -> 120000 | AX37: =AW37-AP37-SUM(AK37:AM37) -> 120000 | AY37: =SUM(AK37:AP37)+SUM(AR37:AT37)+AV37 -> 4400 | AZ37: =AW37-AY37-BB37 -> 105290 | BA37: Income tax Added | BB37: 10310
A38: =A37+1 -> 35 | AK38: =SUM(V38:Z38)-AG38 -> 0 | AZ38: =AW38-AY38-BB38 -> 0
A39: =A38+1 -> 36 | B39: A1 | C39: 40180 | E39: 62000 | F39: =E39*50% -> 31000 | G39: =F39*40% -> 12400 | H39: =IF(E39<11750,0,3500) -> 3500 | I39: 0 | J39: =E39-SUM(F39:I39) -> 15100 | K39: 44805 | L39: =VLOOKUP(K39,SalaryMonth!$B$5:$E$16,2,FALSE) -> 44799 | M39: =VLOOKUP(K39,SalaryMonth!$B$5:$E$16,3,FALSE) -> 44829 | N39: =VLOOKUP(K39,SalaryMonth!$B$5:$E$16,4,FALSE) -> 31 | O39: =IF(L39<=C39,"Y","N") -> N | P39: =IF(OR(D39<>"",M39<D39),"Y","N") -> N | Q39: 31 | R39: 29 | S39: 1 | T39: 0 | U39: 0 | V39: =ROUND((F39/N39)*Q39,0) -> 31000 | W39: =ROUND((G39/N39)*Q39,0) -> 12400 | X39: =ROUND((H39/N39)*Q39,0) -> 3500 | Y39: =(I39/N39)*Q39 -> 0 | Z39: =ROUND((J39/N39)*Q39,0) -> 15100 | AB39: =ROUND((V39/Q39)*Q39-(V39/Q39)*S39,0) -> 30000 | AC39: =ROUND((W39/Q39)*Q39-(W39/Q39)*S39,0) -> 12000 | AD39: =ROUND((X39/Q39)*Q39-(X39/Q39)*S39,0) -> 3387 | AE39: =Y39 -> 0 | AF39: =ROUND((Z39/Q39)*Q39-(Z39/Q39)*S39,0) -> 14613 | AG39: =SUM(AB39:AF39) -> 60000 | AH39: 0 | AI39: 0 | AJ39: =SUM(AB39:AI39) -> 120000 | AK39: =SUM(V39:Z39)-AG39 -> 2000 | AL39: =ROUND(E39*(U39/Q39),0) -> 0 | AM39: =ROUND(E39*(T39/Q39),0) -> 0 | AN39: 8333 | AO39: =AE39 -> 0 | AP39: 2000 | AQ39: =SUM(F39:J39)-SUM(AK39:AP39) -> 49667 | AR39: =IF( AX39<15001,0,IF(AX39<20001,150,200)) -> 200 | AS39: 0 | AT39: =MIN( ROUND(AB39*12%,0),1800) -> 1800 | AU39: =ROUNDUP(IF(E39<=21000,AG39*1.75%,0),0) -> 0 | AV39: =AU39 -> 0 | AW39: =SUM(V39:Z39)+SUM(AH39:AI39) -> 62000 | AX39: =AW39-AP39-SUM(AK39:AM39) -> 58000 | AY39: =SUM(AK39:AP39)+SUM(AR39:AT39)+AV39 -> 14333 | AZ39: =AW39-AY39-BB39 -> 43597 | BA39: Paycut added 2000/Advance Deducted 8333 | BB39: 4070
A40: =A39+1 -> 37 | B40: A2 | C40: 40180 | E40: 24000 | F40: =E40*50% -> 12000 | G40: =F40*40% -> 4800 | H40: =IF(E40<11750,0,3500) -> 3500 | I40: 0 | J40: =E40-SUM(F40:I40) -> 3700 | K40: 44805 | L40: =VLOOKUP(K40,SalaryMonth!$B$5:$E$16,2,FALSE) -> 44799 | M40: =VLOOKUP(K40,SalaryMonth!$B$5:$E$16,3,FALSE) -> 44829 | N40: =VLOOKUP(K40,SalaryMonth!$B$5:$E$16,4,FALSE) -> 31 | O40: =IF(L40<C40,"Y","N") -> N | P40: =IF(OR(D40<>"",M40<D40),"Y","N") -> N | Q40: 31 | R40: 29 | S40: 0 | T40: 0 | U40: 0 | V40: =ROUND((F40/N40)*Q40,0) -> 12000 | W40: =ROUND((G40/N40)*Q40,0) -> 4800 | X40: =ROUND((H40/N40)*Q40,0) -> 3500 | Y40: =(I40/N40)*Q40 -> 0 | Z40: =ROUND((J40/N40)*Q40,0) -> 3700 | AB40: =ROUND((V40/Q40)*Q40-(V40/Q40)*S40,0) -> 12000 | AC40: =ROUND((W40/Q40)*Q40-(W40/Q40)*S40,0) -> 4800 | AD40: =ROUND((X40/Q40)*Q40-(X40/Q40)*S40,0) -> 3500 | AE40: =Y40 -> 0 | AF40: =ROUND((Z40/Q40)*Q40-(Z40/Q40)*S40,0) -> 3700 | AG40: =SUM(AB40:AF40) -> 24000 | AH40: 0 | AI40: 0 | AJ40: =SUM(AB40:AI40) -> 48000 | AK40: =SUM(V40:Z40)-AG40 -> 0 | AL40: =ROUND(E40*(U40/Q40),0) -> 0 | AM40: =ROUND(E40*(T40/Q40),0) -> 0 | AN40: 0 | AO40: =AE40 -> 0 | AP40: 0 | AQ40: =SUM(F40:J40)-SUM(AK40:AP40) -> 24000 | AR40: =IF( AX40<15001,0,IF(AX40<20001,150,200)) -> 200 | AS40: 0 | AT40: =MIN( ROUND(AB40*12%,0),1800) -> 1440 | AU40: =ROUNDUP(IF(E40<=21000,AG40*1.75%,0),0) -> 0 | AV40: =ROUNDUP(AG40 *1.75%,0) -> 420 | AW40: =SUM(V40:Z40)+SUM(AH40:AI40) -> 24000 | AX40: =AW40-AP40-SUM(AK40:AM40) -> 24000 | AY40: =SUM(AK40:AP40)+SUM(AR40:AT40)+AV40 -> 2060 | AZ40: =AW40-AY40-BB40 -> 21940 | BA40: ESI should be deducted because ESI is deducted in May month it will continue up to sep irrespective of salary
A41: =A40+1 -> 38 | B41: A3 | C41: 40181 | E41: 11000 | F41: =E41*50% -> 5500 | G41: =F41*40% -> 2200 | H41: =IF(E41<11750,0,3500) -> 0 | I41: 0 | J41: =E41-SUM(F41:I41) -> 3300 | K41: 44805 | L41: =VLOOKUP(K41,SalaryMonth!$B$5:$E$16,2,FALSE) -> 44799 | M41: =VLOOKUP(K41,SalaryMonth!$B$5:$E$16,3,FALSE) -> 44829 | N41: =VLOOKUP(K41,SalaryMonth!$B$5:$E$16,4,FALSE) -> 31 | O41: =IF(L41<C41,"Y","N") -> N | P41: =IF(OR(D41<>"",M41<D41),"Y","N") -> N | Q41: 31 | R41: 29 | S41: 0 | T41: 0 | U41: 0 | V41: =ROUND((F41/N41)*Q41,0) -> 5500 | W41: =ROUND((G41/N41)*Q41,0) -> 2200 | X41: =ROUND((H41/N41)*Q41,0) -> 0 | Y41: =(I41/N41)*Q41 -> 0 | Z41: =ROUND((J41/N41)*Q41,0) -> 3300 | AB41: =ROUND((V41/Q41)*Q41-(V41/Q41)*S41,0) -> 5500 | AC41: =ROUND((W41/Q41)*Q41-(W41/Q41)*S41,0) -> 2200 | AD41: =ROUND((X41/Q41)*Q41-(X41/Q41)*S41,0) -> 0 | AE41: =Y41 -> 0 | AF41: =ROUND((Z41/Q41)*Q41-(Z41/Q41)*S41,0) -> 3300 | AG41: =SUM(AB41:AF41) -> 11000 | AH41: 0 | AI41: 0 | AJ41: =SUM(AB41:AI41) -> 22000 | AK41: =SUM(V41:Z41)-AG41 -> 0 | AL41: =ROUND(E41*(U41/Q41),0) -> 0 | AM41: =ROUND(E41*(T41/Q41),0) -> 0 | AN41: 0 | AO41: =AE41 -> 0 | AP41: 0 | AQ41: =SUM(F41:J41)-SUM(AK41:AP41) -> 11000 | AR41: =IF( AX41<15001,0,IF(AX41<20001,150,200)) -> 0 | AS41: 0 | AT41: =MIN( ROUND(AB41*12%,0),1800) -> 660 | AU41: =ROUNDUP(IF(E41<=21000,AG41*1.75%,0),0) -> 193 | AV41: =AU41 -> 193 | AW41: =SUM(V41:Z41)+SUM(AH41:AI41) -> 11000 | AX41: =AW41-AP41-SUM(AK41:AM41) -> 11000 | AY41: =SUM(AK41:AP41)+SUM(AR41:AT41)+AV41 -> 853 | AZ41: =AW41-AY41-BB41 -> 10147 | BA41: ESI is deducted because employee salary is under ESI slab
A42: =A41+1 -> 39 | B42: A4 | C42: 40182 | E42: 25000 | F42: =E42*50% -> 12500 | G42: =F42*40% -> 5000 | H42: =IF(E42<11750,0,3500) -> 3500 | I42: 0 | J42: =E42-SUM(F42:I42) -> 4000 | K42: 44805 | L42: =VLOOKUP(K42,SalaryMonth!$B$5:$E$16,2,FALSE) -> 44799 | M42: =VLOOKUP(K42,SalaryMonth!$B$5:$E$16,3,FALSE) -> 44829 | N42: =VLOOKUP(K42,SalaryMonth!$B$5:$E$16,4,FALSE) -> 31 | O42: =IF(L42<C42,"Y","N") -> N | P42: =IF(OR(D42<>"",M42<D42),"Y","N") -> N | Q42: 31 | R42: 29 | S42: 0 | T42: 0 | U42: 0 | V42: =ROUND((F42/N42)*Q42,0) -> 12500 | W42: =ROUND((G42/N42)*Q42,0) -> 5000 | X42: =ROUND((H42/N42)*Q42,0) -> 3500 | Y42: =(I42/N42)*Q42 -> 0 | Z42: =ROUND((J42/N42)*Q42,0) -> 4000 | AB42: =ROUND((V42/Q42)*Q42-(V42/Q42)*S42,0) -> 12500 | AC42: =ROUND((W42/Q42)*Q42-(W42/Q42)*S42,0) -> 5000 | AD42: =ROUND((X42/Q42)*Q42-(X42/Q42)*S42,0) -> 3500 | AE42: =Y42 -> 0 | AF42: =ROUND((Z42/Q42)*Q42-(Z42/Q42)*S42,0) -> 4000 | AG42: =SUM(AB42:AF42) -> 25000 | AH42: 0 | AI42: 0 | AJ42: =SUM(AB42:AI42) -> 50000 | AK42: =SUM(V42:Z42)-AG42 -> 0 | AL42: =ROUND(E42*(U42/Q42),0) -> 0 | AM42: =ROUND(E42*(T42/Q42),0) -> 0 | AN42: 0 | AO42: =AE42 -> 0 | AP42: 0 | AQ42: =SUM(F42:J42)-SUM(AK42:AP42) -> 25000 | AR42: =IF( AX42<15001,0,IF(AX42<20001,150,200)) -> 200 | AS42: 0 | AT42: =MIN( ROUND(AB42*12%,0),1800) -> 1500 | AU42: =ROUNDUP(IF(E42<=21000,AG42*1.75%,0),0) -> 0 | AV42: =AU42 -> 0 | AW42: =SUM(V42:Z42)+SUM(AH42:AI42) -> 25000 | AX42: =AW42-AP42-SUM(AK42:AM42) -> 25000 | AY42: =SUM(AK42:AP42)+SUM(AR42:AT42)+AV42 -> 1700 | AZ42: =AW42-AY42-BB42 -> 23300
A43: =A42+1 -> 40 | B43: A5 | C43: 40183 | E43: 32000 | F43: =E43*50% -> 16000 | G43: =F43*40% -> 6400 | H43: =IF(E43<11750,0,3500) -> 3500 | I43: 0 | J43: =E43-SUM(F43:I43) -> 6100 | K43: 44805 | L43: =VLOOKUP(K43,SalaryMonth!$B$5:$E$16,2,FALSE) -> 44799 | M43: =VLOOKUP(K43,SalaryMonth!$B$5:$E$16,3,FALSE) -> 44829 | N43: =VLOOKUP(K43,SalaryMonth!$B$5:$E$16,4,FALSE) -> 31 | O43: =IF(L43<C43,"Y","N") -> N | P43: =IF(OR(D43<>"",M43<D43),"Y","N") -> N | Q43: 31 | R43: 29 | S43: 0 | T43: 0 | U43: 0 | V43: =ROUND((F43/N43)*Q43,0) -> 16000 | W43: =ROUND((G43/N43)*Q43,0) -> 6400 | X43: =ROUND((H43/N43)*Q43,0) -> 3500 | Y43: =(I43/N43)*Q43 -> 0 | Z43: =ROUND((J43/N43)*Q43,0) -> 6100 | AB43: =ROUND((V43/Q43)*Q43-(V43/Q43)*S43,0) -> 16000 | AC43: =ROUND((W43/Q43)*Q43-(W43/Q43)*S43,0) -> 6400 | AD43: =ROUND((X43/Q43)*Q43-(X43/Q43)*S43,0) -> 3500 | AE43: =Y43 -> 0 | AF43: =ROUND((Z43/Q43)*Q43-(Z43/Q43)*S43,0) -> 6100 | AG43: =SUM(AB43:AF43) -> 32000 | AH43: 0 | AI43: 0 | AJ43: =SUM(AB43:AI43) -> 64000 | AK43: =SUM(V43:Z43)-AG43 -> 0 | AL43: =ROUND(E43*(U43/Q43),0) -> 0 | AM43: =ROUND(E43*(T43/Q43),0) -> 0 | AN43: 0 | AO43: =AE43 -> 0 | AP43: 0 | AQ43: =SUM(F43:J43)-SUM(AK43:AP43) -> 32000 | AR43: =IF( AX43<15001,0,IF(AX43<20001,150,200)) -> 200 | AS43: 0 | AT43: =MIN( ROUND(AB43*12%,0),1800) -> 1800 | AU43: =ROUNDUP(IF(E43<=21000,AG43*1.75%,0),0) -> 0 | AV43: =AU43 -> 0 | AW43: =SUM(V43:Z43)+SUM(AH43:AI43) -> 32000 | AX43: =AW43-AP43-SUM(AK43:AM43) -> 32000 | AY43: =SUM(AK43:AP43)+SUM(AR43:AT43)+AV43 -> 2000 | AZ43: =AW43-AY43-BB43 -> 30000
A44: =A43+1 -> 41 | B44: B1 | C44: 40183 | E44: 120000 | F44: =E44*50% -> 60000 | G44: =F44*40% -> 24000 | H44: =IF(E44<11750,0,3500) -> 3500 | I44: 2400 | J44: =E44-SUM(F44:I44) -> 30100 | K44: 44805 | L44: =VLOOKUP(K44,SalaryMonth!$B$5:$E$16,2,FALSE) -> 44799 | M44: =VLOOKUP(K44,SalaryMonth!$B$5:$E$16,3,FALSE) -> 44829 | N44: =VLOOKUP(K44,SalaryMonth!$B$5:$E$16,4,FALSE) -> 31 | O44: =IF(L44<C44,"Y","N") -> N | P44: =IF(OR(D44<>"",M44<D44),"Y","N") -> N | Q44: 31 | R44: 31 | S44: 0 | T44: 0 | U44: 0 | V44: =ROUND((F44/N44)*Q44,0) -> 60000 | W44: =ROUND((G44/N44)*Q44,0) -> 24000 | X44: =ROUND((H44/N44)*Q44,0) -> 3500 | Y44: =(I44/N44)*Q44 -> 2400 | Z44: =ROUND((J44/N44)*Q44,0) -> 30100 | AB44: =ROUND((V44/Q44)*Q44-(V44/Q44)*S44,0) -> 60000 | AC44: =ROUND((W44/Q44)*Q44-(W44/Q44)*S44,0) -> 24000 | AD44: =ROUND((X44/Q44)*Q44-(X44/Q44)*S44,0) -> 3500 | AE44: =I44 -> 2400 | AF44: =ROUND((Z44/Q44)*Q44-(Z44/Q44)*S44,0) -> 30100 | AG44: =SUM(AB44:AF44) -> 120000 | AH44: 0 | AI44: 0 | AJ44: =SUM(AB44:AI44) -> 240000 | AK44: =SUM(V44:Z44)-AG44 -> 0 | AL44: =ROUND(E44*(U44/Q44),0) -> 0 | AM44: =ROUND(E44*(T44/Q44),0) -> 0 | AN44: 0 | AO44: =AE44 -> 2400 | AP44: 0 | AQ44: =SUM(F44:J44)-SUM(AK44:AP44) -> 117600 | AR44: =IF( AX44<15001,0,IF(AX44<20001,150,200)) -> 200 | AS44: 0 | AT44: =MIN( ROUND(AB44*12%,0),1800) -> 1800 | AU44: =ROUNDUP(IF(E44<=21000,AG44*1.75%,0),0) -> 0 | AV44: =AU44 -> 0 | AW44: =SUM(V44:Z44)+SUM(AH44:AI44) -> 120000 | AX44: =AW44-AP44-SUM(AK44:AM44) -> 120000 | AY44: =SUM(AK44:AP44)+SUM(AR44:AT44)+AV44 -> 4400 | AZ44: =AW44-AY44-BB44 -> 105290 | BA44: Income tax Added | BB44: 10310
A45: =A44+1 -> 42 | AK45: =SUM(V45:Z45)-AG45 -> 0 | AZ45: =AW45-AY45-BB45 -> 0
A46: =A45+1 -> 43 | B46: A1 | C46: 40180 | E46: 62000 | F46: =E46*50% -> 31000 | G46: =F46*40% -> 12400 | H46: =IF(E46<11750,0,3500) -> 3500 | I46: 0 | J46: =E46-SUM(F46:I46) -> 15100 | K46: 44835 | L46: =VLOOKUP(K46,SalaryMonth!$B$5:$E$16,2,FALSE) -> 44830 | M46: =VLOOKUP(K46,SalaryMonth!$B$5:$E$16,3,FALSE) -> 44859 | N46: =VLOOKUP(K46,SalaryMonth!$B$5:$E$16,4,FALSE) -> 30 | O46: =IF(L46<=C46,"Y","N") -> N | P46: =IF(OR(D46<>"",M46<D46),"Y","N") -> N | Q46: 30 | R46: 1 | S46: 29 | T46: 0 | U46: 0 | V46: =ROUND((F46/N46)*Q46,0) -> 31000 | W46: =ROUND((G46/N46)*Q46,0) -> 12400 | X46: =ROUND((H46/N46)*Q46,0) -> 3500 | Y46: =(I46/N46)*Q46 -> 0 | Z46: =ROUND((J46/N46)*Q46,0) -> 15100 | AB46: =ROUND((V46/Q46)*Q46-(V46/Q46)*S46,0) -> 1033 | AC46: =ROUND((W46/Q46)*Q46-(W46/Q46)*S46,0) -> 413 | AD46: =ROUND((X46/Q46)*Q46-(X46/Q46)*S46,0) -> 117 | AE46: =Y46 -> 0 | AF46: =ROUND((Z46/Q46)*Q46-(Z46/Q46)*S46,0) -> 503 | AG46: =SUM(AB46:AF46) -> 2066 | AH46: 0 | AI46: 0 | AJ46: =SUM(AB46:AI46) -> 4132 | AK46: =SUM(V46:Z46)-AG46 -> 59934 | AL46: =ROUND(E46*(U46/Q46),0) -> 0 | AM46: =ROUND(E46*(T46/Q46),0) -> 0 | AN46: 2 | AO46: =AE46 -> 0 | AP46: 0 | AQ46: =SUM(F46:J46)-SUM(AK46:AP46) -> 2064 | AR46: =IF( AX46<15001,0,IF(AX46<20001,150,200)) -> 0 | AS46: 0 | AT46: =MIN( ROUND(AB46*12%,0),1800) -> 124 | AU46: =ROUNDUP(IF(E46<=21000,AG46*1.75%,0),0) -> 0 | AV46: =AU46 -> 0 | AW46: =SUM(V46:Z46)+SUM(AH46:AI46) -> 62000 | AX46: =AW46-AP46-SUM(AK46:AM46) -> 2066 | AY46: =SUM(AK46:AP46)+SUM(AR46:AT46)+AV46 -> 60060 | AZ46: =AW46-AY46-BB46 -> 1940 | BA46: Lop Added 29days as Employee Present days are 29 | BB46: 0
A47: =A46+1 -> 44 | B47: A2 | C47: 44690 | E47: 24000 | F47: =E47*50% -> 12000 | G47: =F47*40% -> 4800 | H47: =IF(E47<11750,0,3500) -> 3500 | I47: 0 | J47: =E47-SUM(F47:I47) -> 3700 | K47: 44835 | L47: =VLOOKUP(K47,SalaryMonth!$B$5:$E$16,2,FALSE) -> 44830 | M47: =VLOOKUP(K47,SalaryMonth!$B$5:$E$16,3,FALSE) -> 44859 | N47: =VLOOKUP(K47,SalaryMonth!$B$5:$E$16,4,FALSE) -> 30 | O47: =IF(L47<C47,"Y","N") -> N | P47: =IF(OR(D47<>"",M47<D47),"Y","N") -> N | Q47: 30 | R47: 25 | S47: 5 | T47: 0 | U47: 0 | V47: =ROUND((F47/N47)*Q47,0) -> 12000 | W47: =ROUND((G47/N47)*Q47,0) -> 4800 | X47: =ROUND((H47/N47)*Q47,0) -> 3500 | Y47: =(I47/N47)*Q47 -> 0 | Z47: =ROUND((J47/N47)*Q47,0) -> 3700 | AB47: =ROUND((V47/Q47)*Q47-(V47/Q47)*S47,0) -> 10000 | AC47: =ROUND((W47/Q47)*Q47-(W47/Q47)*S47,0) -> 4000 | AD47: =ROUND((X47/Q47)*Q47-(X47/Q47)*S47,0) -> 2917 | AE47: =Y47 -> 0 | AF47: =ROUND((Z47/Q47)*Q47-(Z47/Q47)*S47,0) -> 3083 | AG47: =SUM(AB47:AF47) -> 20000 | AH47: 0 | AI47: 0 | AJ47: =SUM(AB47:AI47) -> 40000 | AK47: =SUM(V47:Z47)-AG47 -> 4000 | AL47: =ROUND(E47*(U47/Q47),0) -> 0 | AM47: =ROUND(E47*(T47/Q47),0) -> 0 | AN47: 0 | AO47: =AE47 -> 0 | AP47: 1000 | AQ47: =SUM(F47:J47)-SUM(AK47:AP47) -> 19000 | AR47: =IF( AX47<15001,0,IF(AX47<20001,150,200)) -> 150 | AS47: 0 | AT47: =MIN( ROUND(AB47*12%,0),1800) -> 1200 | AU47: =ROUNDUP(IF(E47<=21000,AG47*1.75%,0),0) -> 0 | AV47: =AU47 -> 0 | AW47: =SUM(V47:Z47)+SUM(AH47:AI47) -> 24000 | AX47: =AW47-AP47-SUM(AK47:AM47) -> 19000 | AY47: =SUM(AK47:AP47)+SUM(AR47:AT47)+AV47 -> 6350 | AZ47: =AW47-AY47-BB47 -> 17650 | BA47: ESI is not deducted because Employee salary is Not under ESI slab
A48: =A47+1 -> 45 | B48: A3 | C48: 40181 | E48: 11000 | F48: =E48*50% -> 5500 | G48: =F48*40% -> 2200 | H48: =IF(E48<11750,0,3500) -> 0 | I48: 0 | J48: =E48-SUM(F48:I48) -> 3300 | K48: 44835 | L48: =VLOOKUP(K48,SalaryMonth!$B$5:$E$16,2,FALSE) -> 44830 | M48: =VLOOKUP(K48,SalaryMonth!$B$5:$E$16,3,FALSE) -> 44859 | N48: =VLOOKUP(K48,SalaryMonth!$B$5:$E$16,4,FALSE) -> 30 | O48: =IF(L48<C48,"Y","N") -> N | P48: =IF(OR(D48<>"",M48<D48),"Y","N") -> N | Q48: 30 | R48: 29 | S48: 0 | T48: 0 | U48: 0 | V48: =ROUND((F48/N48)*Q48,0) -> 5500 | W48: =ROUND((G48/N48)*Q48,0) -> 2200 | X48: =ROUND((H48/N48)*Q48,0) -> 0 | Y48: =(I48/N48)*Q48 -> 0 | Z48: =ROUND((J48/N48)*Q48,0) -> 3300 | AB48: =ROUND((V48/Q48)*Q48-(V48/Q48)*S48,0) -> 5500 | AC48: =ROUND((W48/Q48)*Q48-(W48/Q48)*S48,0) -> 2200 | AD48: =ROUND((X48/Q48)*Q48-(X48/Q48)*S48,0) -> 0 | AE48: =Y48 -> 0 | AF48: =ROUND((Z48/Q48)*Q48-(Z48/Q48)*S48,0) -> 3300 | AG48: =SUM(AB48:AF48) -> 11000 | AH48: 0 | AI48: 0 | AJ48: =SUM(AB48:AI48) -> 22000 | AK48: =SUM(V48:Z48)-AG48 -> 0 | AL48: =ROUND(E48*(U48/Q48),0) -> 0 | AM48: =ROUND(E48*(T48/Q48),0) -> 0 | AN48: 0 | AO48: =AE48 -> 0 | AP48: 0 | AQ48: =SUM(F48:J48)-SUM(AK48:AP48) -> 11000 | AR48: =IF( AX48<15001,0,IF(AX48<20001,150,200)) -> 0 | AS48: 0 | AT48: =MIN( ROUND(AB48*12%,0),1800) -> 660 | AU48: =ROUNDUP(IF(E48<=21000,AG48*1.75%,0),0) -> 193 | AV48: =AU48 -> 193 | AW48: =SUM(V48:Z48)+SUM(AH48:AI48) -> 11000 | AX48: =AW48-AP48-SUM(AK48:AM48) -> 11000 | AY48: =SUM(AK48:AP48)+SUM(AR48:AT48)+AV48 -> 853 | AZ48: =AW48-AY48-BB48 -> 10147 | BA48: ESI is deducted because employee salary is under ESI slab
A49: =A48+1 -> 46 | B49: A4 | C49: 40182 | E49: 25000 | F49: =E49*50% -> 12500 | G49: =F49*40% -> 5000 | H49: =IF(E49<11750,0,3500) -> 3500 | I49: 0 | J49: =E49-SUM(F49:I49) -> 4000 | K49: 44835 | L49: =VLOOKUP(K49,SalaryMonth!$B$5:$E$16,2,FALSE) -> 44830 | M49: =VLOOKUP(K49,SalaryMonth!$B$5:$E$16,3,FALSE) -> 44859 | N49: =VLOOKUP(K49,SalaryMonth!$B$5:$E$16,4,FALSE) -> 30 | O49: =IF(L49<C49,"Y","N") -> N | P49: =IF(OR(D49<>"",M49<D49),"Y","N") -> N | Q49: 30 | R49: 29 | S49: 0 | T49: 0 | U49: 0 | V49: =ROUND((F49/N49)*Q49,0) -> 12500 | W49: =ROUND((G49/N49)*Q49,0) -> 5000 | X49: =ROUND((H49/N49)*Q49,0) -> 3500 | Y49: =(I49/N49)*Q49 -> 0 | Z49: =ROUND((J49/N49)*Q49,0) -> 4000 | AB49: =ROUND((V49/Q49)*Q49-(V49/Q49)*S49,0) -> 12500 | AC49: =ROUND((W49/Q49)*Q49-(W49/Q49)*S49,0) -> 5000 | AD49: =ROUND((X49/Q49)*Q49-(X49/Q49)*S49,0) -> 3500 | AE49: =Y49 -> 0 | AF49: =ROUND((Z49/Q49)*Q49-(Z49/Q49)*S49,0) -> 4000 | AG49: =SUM(AB49:AF49) -> 25000 | AH49: 0 | AI49: 0 | AJ49: =SUM(AB49:AI49) -> 50000 | AK49: =SUM(V49:Z49)-AG49 -> 0 | AL49: =ROUND(E49*(U49/Q49),0) -> 0 | AM49: =ROUND(E49*(T49/Q49),0) -> 0 | AN49: 0 | AO49: =AE49 -> 0 | AP49: 0 | AQ49: =SUM(F49:J49)-SUM(AK49:AP49) -> 25000 | AR49: =IF( AX49<15001,0,IF(AX49<20001,150,200)) -> 200 | AS49: 0 | AT49: =MIN( ROUND(AB49*12%,0),1800) -> 1500 | AU49: =ROUNDUP(IF(E49<=21000,AG49*1.75%,0),0) -> 0 | AV49: =AU49 -> 0 | AW49: =SUM(V49:Z49)+SUM(AH49:AI49) -> 25000 | AX49: =AW49-AP49-SUM(AK49:AM49) -> 25000 | AY49: =SUM(AK49:AP49)+SUM(AR49:AT49)+AV49 -> 1700 | AZ49: =AW49-AY49-BB49 -> 23300
A50: =A49+1 -> 47 | B50: A5 | C50: 40183 | E50: 45000 | F50: =E50*50% -> 22500 | G50: =F50*40% -> 9000 | H50: =IF(E50<11750,0,3500) -> 3500 | I50: 2400 | J50: =E50-SUM(F50:I50) -> 7600 | K50: 44835 | L50: =VLOOKUP(K50,SalaryMonth!$B$5:$E$16,2,FALSE) -> 44830 | M50: =VLOOKUP(K50,SalaryMonth!$B$5:$E$16,3,FALSE) -> 44859 | N50: =VLOOKUP(K50,SalaryMonth!$B$5:$E$16,4,FALSE) -> 30 | O50: =IF(L50<C50,"Y","N") -> N | P50: =IF(OR(D50<>"",M50<D50),"Y","N") -> N | Q50: 30 | R50: 29 | S50: 0 | T50: 0 | U50: 0 | V50: =ROUND((F50/N50)*Q50,0) -> 22500 | W50: =ROUND((G50/N50)*Q50,0) -> 9000 | X50: =ROUND((H50/N50)*Q50,0) -> 3500 | Y50: =(I50/N50)*Q50 -> 2400 | Z50: =ROUND((J50/N50)*Q50,0) -> 7600 | AB50: =ROUND((V50/Q50)*Q50-(V50/Q50)*S50,0) -> 22500 | AC50: =ROUND((W50/Q50)*Q50-(W50/Q50)*S50,0) -> 9000 | AD50: =ROUND((X50/Q50)*Q50-(X50/Q50)*S50,0) -> 3500 | AE50: =Y50 -> 2400 | AF50: =ROUND((Z50/Q50)*Q50-(Z50/Q50)*S50,0) -> 7600 | AG50: =SUM(AB50:AF50) -> 45000 | AH50: 0 | AI50: 0 | AJ50: =SUM(AB50:AI50) -> 90000 | AK50: =SUM(V50:Z50)-AG50 -> 0 | AL50: =ROUND(E50*(U50/Q50),0) -> 0 | AM50: =ROUND(E50*(T50/Q50),0) -> 0 | AN50: 3333 | AO50: =AE50 -> 2400 | AP50: 0 | AQ50: =SUM(F50:J50)-SUM(AK50:AP50) -> 39267 | AR50: =IF( AX50<15001,0,IF(AX50<20001,150,200)) -> 200 | AS50: 2000 | AT50: =MIN( ROUND(AB50*12%,0),1800) -> 1800 | AU50: =ROUNDUP(IF(E50<=21000,AG50*1.75%,0),0) -> 0 | AV50: =AU50 -> 0 | AW50: =SUM(V50:Z50)+SUM(AH50:AI50) -> 45000 | AX50: =AW50-AP50-SUM(AK50:AM50) -> 45000 | AY50: =SUM(AK50:AP50)+SUM(AR50:AT50)+AV50 -> 9733 | AZ50: =AW50-AY50-BB50 -> 35267 | BA50: Income tax Added
A51: =A50+1 -> 48 | B51: B1 | C51: 40183 | E51: 125000 | F51: =E51*50% -> 62500 | G51: =F51*40% -> 25000 | H51: =IF(E51<11750,0,3500) -> 3500 | I51: 2400 | J51: =E51-SUM(F51:I51) -> 31600 | K51: 44835 | L51: =VLOOKUP(K51,SalaryMonth!$B$5:$E$16,2,FALSE) -> 44830 | M51: =VLOOKUP(K51,SalaryMonth!$B$5:$E$16,3,FALSE) -> 44859 | N51: =VLOOKUP(K51,SalaryMonth!$B$5:$E$16,4,FALSE) -> 30 | O51: =IF(L51<C51,"Y","N") -> N | P51: =IF(OR(D51<>"",M51<D51),"Y","N") -> N | Q51: 30 | R51: 30 | S51: 0 | T51: 0 | U51: 0 | V51: =ROUND((F51/N51)*Q51,0) -> 62500 | W51: =ROUND((G51/N51)*Q51,0) -> 25000 | X51: =ROUND((H51/N51)*Q51,0) -> 3500 | Y51: =(I51/N51)*Q51 -> 2400 | Z51: =ROUND((J51/N51)*Q51,0) -> 31600 | AB51: =ROUND((V51/Q51)*Q51-(V51/Q51)*S51,0) -> 62500 | AC51: =ROUND((W51/Q51)*Q51-(W51/Q51)*S51,0) -> 25000 | AD51: =ROUND((X51/Q51)*Q51-(X51/Q51)*S51,0) -> 3500 | AE51: =I51 -> 2400 | AF51: =ROUND((Z51/Q51)*Q51-(Z51/Q51)*S51,0) -> 31600 | AG51: =SUM(AB51:AF51) -> 125000 | AH51: 0 | AI51: 0 | AJ51: =SUM(AB51:AI51) -> 250000 | AK51: =SUM(V51:Z51)-AG51 -> 0 | AL51: =ROUND(E51*(U51/Q51),0) -> 0 | AM51: =ROUND(E51*(T51/Q51),0) -> 0 | AN51: 0 | AO51: =AE51 -> 2400 | AP51: 0 | AQ51: =SUM(F51:J51)-SUM(AK51:AP51) -> 122600 | AR51: =IF( AX51<15001,0,IF(AX51<20001,150,200)) -> 200 | AS51: 0 | AT51: =MIN( ROUND(AB51*12%,0),1800) -> 1800 | AU51: =ROUNDUP(IF(E51<=21000,AG51*1.75%,0),0) -> 0 | AV51: =AU51 -> 0 | AW51: =SUM(V51:Z51)+SUM(AH51:AI51) -> 125000 | AX51: =AW51-AP51-SUM(AK51:AM51) -> 125000 | AY51: =SUM(AK51:AP51)+SUM(AR51:AT51)+AV51 -> 4400 | AZ51: =AW51-AY51-BB51 -> 108100 | BA51: Income tax Added | BB51: 12500
A52: =A51+1 -> 49 | AK52: =SUM(V52:Z52)-AG52 -> 0 | AZ52: =AW52-AY52-BB52 -> 0
A53: =A52+1 -> 50 | B53: A1 | C53: 40180 | E53: 62000 | F53: =E53*50% -> 31000 | G53: =F53*40% -> 12400 | H53: =IF(E53<11750,0,3500) -> 3500 | I53: 0 | J53: =E53-SUM(F53:I53) -> 15100 | K53: 44866 | L53: =VLOOKUP(K53,SalaryMonth!$B$5:$E$16,2,FALSE) -> 44860 | M53: =VLOOKUP(K53,SalaryMonth!$B$5:$E$16,3,FALSE) -> 44890 | N53: =VLOOKUP(K53,SalaryMonth!$B$5:$E$16,4,FALSE) -> 31 | O53: =IF(L53<=C53,"Y","N") -> N | P53: =IF(OR(D53<>"",M53<D53),"Y","N") -> N | Q53: 31 | R53: 28 | S53: 1 | T53: 1 | U53: 1 | V53: =ROUND((F53/N53)*Q53,0) -> 31000 | W53: =ROUND((G53/N53)*Q53,0) -> 12400 | X53: =ROUND((H53/N53)*Q53,0) -> 3500 | Y53: =(I53/N53)*Q53 -> 0 | Z53: =ROUND((J53/N53)*Q53,0) -> 15100 | AB53: =ROUND((V53/Q53)*Q53-(V53/Q53)*S53,0) -> 30000 | AC53: =ROUND((W53/Q53)*Q53-(W53/Q53)*S53,0) -> 12000 | AD53: =ROUND((X53/Q53)*Q53-(X53/Q53)*S53,0) -> 3387 | AE53: =Y53 -> 0 | AF53: =ROUND((Z53/Q53)*Q53-(Z53/Q53)*S53,0) -> 14613 | AG53: =SUM(AB53:AF53) -> 60000 | AH53: 0 | AI53: 0 | AJ53: =SUM(AB53:AI53) -> 120000 | AK53: =SUM(V53:Z53)-AG53 -> 2000 | AL53: =ROUND(E53*(U53/Q53),0) -> 2000 | AM53: =ROUND(E53*(T53/Q53),0) -> 2000 | AN53: 0 | AO53: =AE53 -> 0 | AP53: 2000 | AQ53: =SUM(F53:J53)-SUM(AK53:AP53) -> 54000 | AR53: =IF( AX53<15001,0,IF(AX53<20001,150,200)) -> 200 | AS53: 0 | AT53: =MIN( ROUND(AB53*12%,0),1800) -> 1800 | AU53: =ROUNDUP(IF(E53<=21000,AG53*1.75%,0),0) -> 0 | AV53: =AU53 -> 0 | AW53: =SUM(V53:Z53)+SUM(AH53:AI53) -> 62000 | AX53: =AW53-AP53-SUM(AK53:AM53) -> 54000 | AY53: =SUM(AK53:AP53)+SUM(AR53:AT53)+AV53 -> 10000 | AZ53: =AW53-AY53-BB53 -> 52000 | BA53: Late Coming And UnAuthorized /LOP | BB53: 0
A54: =A53+1 -> 51 | B54: A2 | C54: 40180 | E54: 17000 | F54: =E54*50% -> 8500 | G54: =F54*40% -> 3400 | H54: =IF(E54<11750,0,3500) -> 3500 | I54: 0 | J54: =E54-SUM(F54:I54) -> 1600 | K54: 44866 | L54: =VLOOKUP(K54,SalaryMonth!$B$5:$E$16,2,FALSE) -> 44860 | M54: =VLOOKUP(K54,SalaryMonth!$B$5:$E$16,3,FALSE) -> 44890 | N54: =VLOOKUP(K54,SalaryMonth!$B$5:$E$16,4,FALSE) -> 31 | O54: =IF(L54<C54,"Y","N") -> N | P54: =IF(OR(D54<>"",M54<D54),"Y","N") -> N | Q54: 31 | R54: 29 | S54: 0 | T54: 0 | U54: 0 | V54: =ROUND((F54/N54)*Q54,0) -> 8500 | W54: =ROUND((G54/N54)*Q54,0) -> 3400 | X54: =ROUND((H54/N54)*Q54,0) -> 3500 | Y54: =(I54/N54)*Q54 -> 0 | Z54: =ROUND((J54/N54)*Q54,0) -> 1600 | AB54: =ROUND((V54/Q54)*Q54-(V54/Q54)*S54,0) -> 8500 | AC54: =ROUND((W54/Q54)*Q54-(W54/Q54)*S54,0) -> 3400 | AD54: =ROUND((X54/Q54)*Q54-(X54/Q54)*S54,0) -> 3500 | AE54: =Y54 -> 0 | AF54: =ROUND((Z54/Q54)*Q54-(Z54/Q54)*S54,0) -> 1600 | AG54: =SUM(AB54:AF54) -> 17000 | AH54: 1000 | AI54: 1500 | AJ54: =SUM(AB54:AI54) -> 36500 | AK54: =SUM(V54:Z54)-AG54 -> 0 | AL54: =ROUND(E54*(U54/Q54),0) -> 0 | AM54: =ROUND(E54*(T54/Q54),0) -> 0 | AN54: 0 | AO54: =AE54 -> 0 | AP54: 0 | AQ54: =SUM(F54:J54)-SUM(AK54:AP54) -> 17000 | AR54: =IF( AX54<15001,0,IF(AX54<20001,150,200)) -> 150 | AS54: 0 | AT54: =MIN( ROUND(AB54*12%,0),1800) -> 1020 | AU54: =ROUNDUP(IF(E54<=21000,AG54*1.75%,0),0) -> 298 | AV54: =AU54 -> 298 | AW54: =SUM(V54:Z54)+SUM(AH54:AI54) -> 19500 | AX54: =AW54-AP54-SUM(AK54:AM54) -> 19500 | AY54: =SUM(AK54:AP54)+SUM(AR54:AT54)+AV54 -> 1468 | AZ54: =AW54-AY54-BB54 -> 18032 | BA54: ESI should be deducted because ESI is deducted because Employee is under ESI Slab
A55: =A54+1 -> 52 | B55: A3 | C55: 40181 | E55: 11000 | F55: =E55*50% -> 5500 | G55: =F55*40% -> 2200 | H55: =IF(E55<11750,0,3500) -> 0 | I55: 0 | J55: =E55-SUM(F55:I55) -> 3300 | K55: 44866 | L55: =VLOOKUP(K55,SalaryMonth!$B$5:$E$16,2,FALSE) -> 44860 | M55: =VLOOKUP(K55,SalaryMonth!$B$5:$E$16,3,FALSE) -> 44890 | N55: =VLOOKUP(K55,SalaryMonth!$B$5:$E$16,4,FALSE) -> 31 | O55: =IF(L55<C55,"Y","N") -> N | P55: =IF(OR(D55<>"",M55<D55),"Y","N") -> N | Q55: 31 | R55: 29 | S55: 0 | T55: 0 | U55: 0 | V55: =ROUND((F55/N55)*Q55,0) -> 5500 | W55: =ROUND((G55/N55)*Q55,0) -> 2200 | X55: =ROUND((H55/N55)*Q55,0) -> 0 | Y55: =(I55/N55)*Q55 -> 0 | Z55: =ROUND((J55/N55)*Q55,0) -> 3300 | AB55: =ROUND((V55/Q55)*Q55-(V55/Q55)*S55,0) -> 5500 | AC55: =ROUND((W55/Q55)*Q55-(W55/Q55)*S55,0) -> 2200 | AD55: =ROUND((X55/Q55)*Q55-(X55/Q55)*S55,0) -> 0 | AE55: =Y55 -> 0 | AF55: =ROUND((Z55/Q55)*Q55-(Z55/Q55)*S55,0) -> 3300 | AG55: =SUM(AB55:AF55) -> 11000 | AH55: 0 | AI55: 0 | AJ55: =SUM(AB55:AI55) -> 22000 | AK55: =SUM(V55:Z55)-AG55 -> 0 | AL55: =ROUND(E55*(U55/Q55),0) -> 0 | AM55: =ROUND(E55*(T55/Q55),0) -> 0 | AN55: 0 | AO55: =AE55 -> 0 | AP55: 0 | AQ55: =SUM(F55:J55)-SUM(AK55:AP55) -> 11000 | AR55: =IF( AX55<15001,0,IF(AX55<20001,150,200)) -> 0 | AS55: 0 | AT55: =MIN( ROUND(AB55*12%,0),1800) -> 660 | AU55: =ROUNDUP(IF(E55<=21000,AG55*1.75%,0),0) -> 193 | AV55: =AU55 -> 193 | AW55: =SUM(V55:Z55)+SUM(AH55:AI55) -> 11000 | AX55: =AW55-AP55-SUM(AK55:AM55) -> 11000 | AY55: =SUM(AK55:AP55)+SUM(AR55:AT55)+AV55 -> 853 | AZ55: =AW55-AY55-BB55 -> 10147 | BA55: ESI is deducted because employee salary is under ESI slab
A56: =A55+1 -> 53 | B56: A4 | C56: 40182 | E56: 25000 | F56: =E56*50% -> 12500 | G56: =F56*40% -> 5000 | H56: =IF(E56<11750,0,3500) -> 3500 | I56: 0 | J56: =E56-SUM(F56:I56) -> 4000 | K56: 44866 | L56: =VLOOKUP(K56,SalaryMonth!$B$5:$E$16,2,FALSE) -> 44860 | M56: =VLOOKUP(K56,SalaryMonth!$B$5:$E$16,3,FALSE) -> 44890 | N56: =VLOOKUP(K56,SalaryMonth!$B$5:$E$16,4,FALSE) -> 31 | O56: =IF(L56<C56,"Y","N") -> N | P56: =IF(OR(D56<>"",M56<D56),"Y","N") -> N | Q56: 31 | R56: 29 | S56: 0 | T56: 0 | U56: 0 | V56: =ROUND((F56/N56)*Q56,0) -> 12500 | W56: =ROUND((G56/N56)*Q56,0) -> 5000 | X56: =ROUND((H56/N56)*Q56,0) -> 3500 | Y56: =(I56/N56)*Q56 -> 0 | Z56: =ROUND((J56/N56)*Q56,0) -> 4000 | AB56: =ROUND((V56/Q56)*Q56-(V56/Q56)*S56,0) -> 12500 | AC56: =ROUND((W56/Q56)*Q56-(W56/Q56)*S56,0) -> 5000 | AD56: =ROUND((X56/Q56)*Q56-(X56/Q56)*S56,0) -> 3500 | AE56: =Y56 -> 0 | AF56: =ROUND((Z56/Q56)*Q56-(Z56/Q56)*S56,0) -> 4000 | AG56: =SUM(AB56:AF56) -> 25000 | AH56: 0 | AI56: 2000 | AJ56: =SUM(AB56:AI56) -> 52000 | AK56: =SUM(V56:Z56)-AG56 -> 0 | AL56: =ROUND(E56*(U56/Q56),0) -> 0 | AM56: =ROUND(E56*(T56/Q56),0) -> 0 | AN56: 0 | AO56: =AE56 -> 0 | AP56: 0 | AQ56: =SUM(F56:J56)-SUM(AK56:AP56) -> 25000 | AR56: =IF( AX56<15001,0,IF(AX56<20001,150,200)) -> 200 | AS56: 0 | AT56: =MIN( ROUND(AB56*12%,0),1800) -> 1500 | AU56: =ROUNDUP(IF(E56<=21000,AG56*1.75%,0),0) -> 0 | AV56: =AU56 -> 0 | AW56: =SUM(V56:Z56)+SUM(AH56:AI56) -> 27000 | AX56: =AW56-AP56-SUM(AK56:AM56) -> 27000 | AY56: =SUM(AK56:AP56)+SUM(AR56:AT56)+AV56 -> 1700 | AZ56: =AW56-AY56-BB56 -> 25300
A57: =A56+1 -> 54 | B57: A5 | C57: 44860 | E57: 32000 | F57: =E57*50% -> 16000 | G57: =F57*40% -> 6400 | H57: =IF(E57<11750,0,3500) -> 3500 | I57: 0 | J57: =E57-SUM(F57:I57) -> 6100 | K57: 44866 | L57: =VLOOKUP(K57,SalaryMonth!$B$5:$E$16,2,FALSE) -> 44860 | M57: =VLOOKUP(K57,SalaryMonth!$B$5:$E$16,3,FALSE) -> 44890 | N57: =VLOOKUP(K57,SalaryMonth!$B$5:$E$16,4,FALSE) -> 31 | O57: =IF(L57<C57,"Y","N") -> N | P57: =IF(OR(D57<>"",M57<D57),"Y","N") -> N | Q57: 31 | R57: 25 | S57: 4 | T57: 0 | U57: 0 | V57: =ROUND((F57/N57)*Q57,0) -> 16000 | W57: =ROUND((G57/N57)*Q57,0) -> 6400 | X57: =ROUND((H57/N57)*Q57,0) -> 3500 | Y57: =(I57/N57)*Q57 -> 0 | Z57: =ROUND((J57/N57)*Q57,0) -> 6100 | AB57: =ROUND((V57/Q57)*Q57-(V57/Q57)*S57,0) -> 13935 | AC57: =ROUND((W57/Q57)*Q57-(W57/Q57)*S57,0) -> 5574 | AD57: =ROUND((X57/Q57)*Q57-(X57/Q57)*S57,0) -> 3048 | AE57: =Y57 -> 0 | AF57: =ROUND((Z57/Q57)*Q57-(Z57/Q57)*S57,0) -> 5313 | AG57: =SUM(AB57:AF57) -> 27870 | AH57: 0 | AI57: 0 | AJ57: =SUM(AB57:AI57) -> 55740 | AK57: =SUM(V57:Z57)-AG57 -> 4130 | AL57: =ROUND(E57*(U57/Q57),0) -> 0 | AM57: =ROUND(E57*(T57/Q57),0) -> 0 | AN57: 3333 | AO57: =AE57 -> 0 | AP57: 0 | AQ57: =SUM(F57:J57)-SUM(AK57:AP57) -> 24537 | AR57: =IF( AX57<15001,0,IF(AX57<20001,150,200)) -> 200 | AS57: 0 | AT57: =MIN( ROUND(AB57*12%,0),1800) -> 1672 | AU57: =ROUNDUP(IF(E57<=21000,AG57*1.75%,0),0) -> 0 | AV57: =AU57 -> 0 | AW57: =SUM(V57:Z57)+SUM(AH57:AI57) -> 32000 | AX57: =AW57-AP57-SUM(AK57:AM57) -> 27870 | AY57: =SUM(AK57:AP57)+SUM(AR57:AT57)+AV57 -> 9335 | AZ57: =AW57-AY57-BB57 -> 22665
A58: =A57+1 -> 55 | B58: B1 | C58: 40183 | E58: 125000 | F58: =E58*50% -> 62500 | G58: =F58*40% -> 25000 | H58: =IF(E58<11750,0,3500) -> 3500 | I58: 2400 | J58: =E58-SUM(F58:I58) -> 31600 | K58: 44866 | L58: =VLOOKUP(K58,SalaryMonth!$B$5:$E$16,2,FALSE) -> 44860 | M58: =VLOOKUP(K58,SalaryMonth!$B$5:$E$16,3,FALSE) -> 44890 | N58: =VLOOKUP(K58,SalaryMonth!$B$5:$E$16,4,FALSE) -> 31 | O58: =IF(L58<C58,"Y","N") -> N | P58: =IF(OR(D58<>"",M58<D58),"Y","N") -> N | Q58: 31 | R58: 31 | S58: 0 | T58: 0 | U58: 0 | V58: =ROUND((F58/N58)*Q58,0) -> 62500 | W58: =ROUND((G58/N58)*Q58,0) -> 25000 | X58: =ROUND((H58/N58)*Q58,0) -> 3500 | Y58: =(I58/N58)*Q58 -> 2400 | Z58: =ROUND((J58/N58)*Q58,0) -> 31600 | AB58: =ROUND((V58/Q58)*Q58-(V58/Q58)*S58,0) -> 62500 | AC58: =ROUND((W58/Q58)*Q58-(W58/Q58)*S58,0) -> 25000 | AD58: =ROUND((X58/Q58)*Q58-(X58/Q58)*S58,0) -> 3500 | AE58: =I58 -> 2400 | AF58: =ROUND((Z58/Q58)*Q58-(Z58/Q58)*S58,0) -> 31600 | AG58: =SUM(AB58:AF58) -> 125000 | AH58: 0 | AI58: 0 | AJ58: =SUM(AB58:AI58) -> 250000 | AK58: =SUM(V58:Z58)-AG58 -> 0 | AL58: =ROUND(E58*(U58/Q58),0) -> 0 | AM58: =ROUND(E58*(T58/Q58),0) -> 0 | AN58: 0 | AO58: =AE58 -> 2400 | AP58: 0 | AQ58: =SUM(F58:J58)-SUM(AK58:AP58) -> 122600 | AR58: =IF( AX58<15001,0,IF(AX58<20001,150,200)) -> 200 | AS58: 0 | AT58: =MIN( ROUND(AB58*12%,0),1800) -> 1800 | AU58: =ROUNDUP(IF(E58<=21000,AG58*1.75%,0),0) -> 0 | AV58: =AU58 -> 0 | AW58: =SUM(V58:Z58)+SUM(AH58:AI58) -> 125000 | AX58: =AW58-AP58-SUM(AK58:AM58) -> 125000 | AY58: =SUM(AK58:AP58)+SUM(AR58:AT58)+AV58 -> 4400 | AZ58: =AW58-AY58-BB58 -> 108100 | BA58: Income tax Added | BB58: 12500
A59: =A58+1 -> 56 | AK59: =SUM(V59:Z59)-AG59 -> 0 | AZ59: =AW59-AY59-BB59 -> 0
A60: =A59+1 -> 57 | B60: A1 | C60: 40180 | E60: 62000 | F60: =E60*50% -> 31000 | G60: =F60*40% -> 12400 | H60: =IF(E60<11750,0,3500) -> 3500 | I60: 0 | J60: =E60-SUM(F60:I60) -> 15100 | K60: 44896 | L60: =VLOOKUP(K60,SalaryMonth!$B$5:$E$16,2,FALSE) -> 44891 | M60: =VLOOKUP(K60,SalaryMonth!$B$5:$E$16,3,FALSE) -> 44920 | N60: =VLOOKUP(K60,SalaryMonth!$B$5:$E$16,4,FALSE) -> 30 | O60: =IF(L60<=C60,"Y","N") -> N | P60: =IF(OR(D60<>"",M60<D60),"Y","N") -> N | Q60: 30 | R60: 1 | S60: 29 | T60: 0 | U60: 0 | V60: =ROUND((F60/N60)*Q60,0) -> 31000 | W60: =ROUND((G60/N60)*Q60,0) -> 12400 | X60: =ROUND((H60/N60)*Q60,0) -> 3500 | Y60: =(I60/N60)*Q60 -> 0 | Z60: =ROUND((J60/N60)*Q60,0) -> 15100 | AB60: =ROUND((V60/Q60)*Q60-(V60/Q60)*S60,0) -> 1033 | AC60: =ROUND((W60/Q60)*Q60-(W60/Q60)*S60,0) -> 413 | AD60: =ROUND((X60/Q60)*Q60-(X60/Q60)*S60,0) -> 117 | AE60: =Y60 -> 0 | AF60: =ROUND((Z60/Q60)*Q60-(Z60/Q60)*S60,0) -> 503 | AG60: =SUM(AB60:AF60) -> 2066 | AH60: 0 | AI60: 0 | AJ60: =SUM(AB60:AI60) -> 4132 | AK60: =SUM(V60:Z60)-AG60 -> 59934 | AL60: =ROUND(E60*(U60/Q60),0) -> 0 | AM60: =ROUND(E60*(T60/Q60),0) -> 0 | AN60: 0 | AO60: =AE60 -> 0 | AP60: 0 | AQ60: =SUM(F60:J60)-SUM(AK60:AP60) -> 2066 | AR60: =IF( AX60<15001,0,IF(AX60<20001,150,200)) -> 0 | AS60: 0 | AT60: =MIN( ROUND(AB60*12%,0),1800) -> 124 | AU60: =ROUNDUP(IF(E60<=21000,AG60*1.75%,0),0) -> 0 | AV60: =AU60 -> 0 | AW60: =SUM(V60:Z60)+SUM(AH60:AI60) -> 62000 | AX60: =AW60-AP60-SUM(AK60:AM60) -> 2066 | AY60: =SUM(AK60:AP60)+SUM(AR60:AT60)+AV60 -> 60058 | AZ60: =AW60-AY60-BB60 -> 1942 | BA60: Lop Added 29days as Employee Present days are 29
A61: =A60+1 -> 58 | B61: A2 | C61: 40181 | E61: 50000 | F61: =E61*50% -> 25000 | G61: =F61*40% -> 10000 | H61: =IF(E61<11750,0,3500) -> 3500 | I61: 0 | J61: =E61-SUM(F61:I61) -> 11500 | K61: 44896 | L61: =VLOOKUP(K61,SalaryMonth!$B$5:$E$16,2,FALSE) -> 44891 | M61: =VLOOKUP(K61,SalaryMonth!$B$5:$E$16,3,FALSE) -> 44920 | N61: =VLOOKUP(K61,SalaryMonth!$B$5:$E$16,4,FALSE) -> 30 | O61: =IF(L61<C61,"Y","N") -> N | P61: =IF(OR(D61<>"",M61<D61),"Y","N") -> N | Q61: 30 | R61: 25 | S61: 5 | T61: 0 | U61: 0 | V61: =ROUND((F61/N61)*Q61,0) -> 25000 | W61: =ROUND((G61/N61)*Q61,0) -> 10000 | X61: =ROUND((H61/N61)*Q61,0) -> 3500 | Y61: =(I61/N61)*Q61 -> 0 | Z61: =ROUND((J61/N61)*Q61,0) -> 11500 | AB61: =ROUND((V61/Q61)*Q61-(V61/Q61)*S61,0) -> 20833 | AC61: =ROUND((W61/Q61)*Q61-(W61/Q61)*S61,0) -> 8333 | AD61: =ROUND((X61/Q61)*Q61-(X61/Q61)*S61,0) -> 2917 | AE61: =Y61 -> 0 | AF61: =ROUND((Z61/Q61)*Q61-(Z61/Q61)*S61,0) -> 9583 | AG61: =SUM(AB61:AF61) -> 41666 | AH61: 1000 | AI61: 0 | AJ61: =SUM(AB61:AI61) -> 84332 | AK61: =SUM(V61:Z61)-AG61 -> 8334 | AL61: =ROUND(E61*(U61/Q61),0) -> 0 | AM61: =ROUND(E61*(T61/Q61),0) -> 0 | AN61: 0 | AO61: =AE61 -> 0 | AP61: 1000 | AQ61: =SUM(F61:J61)-SUM(AK61:AP61) -> 40666 | AR61: =IF( AX61<15001,0,IF(AX61<20001,150,200)) -> 200 | AS61: 0 | AT61: =MIN( ROUND(AB61*12%,0),1800) -> 1800 | AU61: =ROUNDUP(IF(E61<=21000,AG61*1.75%,0),0) -> 0 | AV61: =ROUNDUP(AG61 *1.75%,0) -> 730 | AW61: =SUM(V61:Z61)+SUM(AH61:AI61) -> 51000 | AX61: =AW61-AP61-SUM(AK61:AM61) -> 41666 | AY61: =SUM(AK61:AP61)+SUM(AR61:AT61)+AV61 -> 12064 | AZ61: =AW61-AY61-BB61 -> 38936 | BA61: ESI IS Deducted Because Employe Have An ESI Deduction in last Month
A62: =A61+1 -> 59 | B62: A3 | C62: 40181 | E62: 11000 | F62: =E62*50% -> 5500 | G62: =F62*40% -> 2200 | H62: =IF(E62<11750,0,3500) -> 0 | I62: 0 | J62: =E62-SUM(F62:I62) -> 3300 | K62: 44896 | L62: =VLOOKUP(K62,SalaryMonth!$B$5:$E$16,2,FALSE) -> 44891 | M62: =VLOOKUP(K62,SalaryMonth!$B$5:$E$16,3,FALSE) -> 44920 | N62: =VLOOKUP(K62,SalaryMonth!$B$5:$E$16,4,FALSE) -> 30 | O62: =IF(L62<C62,"Y","N") -> N | P62: =IF(OR(D62<>"",M62<D62),"Y","N") -> N | Q62: 30 | R62: 29 | S62: 0 | T62: 0 | U62: 0 | V62: =ROUND((F62/N62)*Q62,0) -> 5500 | W62: =ROUND((G62/N62)*Q62,0) -> 2200 | X62: =ROUND((H62/N62)*Q62,0) -> 0 | Y62: =(I62/N62)*Q62 -> 0 | Z62: =ROUND((J62/N62)*Q62,0) -> 3300 | AB62: =ROUND((V62/Q62)*Q62-(V62/Q62)*S62,0) -> 5500 | AC62: =ROUND((W62/Q62)*Q62-(W62/Q62)*S62,0) -> 2200 | AD62: =ROUND((X62/Q62)*Q62-(X62/Q62)*S62,0) -> 0 | AE62: =Y62 -> 0 | AF62: =ROUND((Z62/Q62)*Q62-(Z62/Q62)*S62,0) -> 3300 | AG62: =SUM(AB62:AF62) -> 11000 | AH62: 0 | AI62: 2000 | AJ62: =SUM(AB62:AI62) -> 24000 | AK62: =SUM(V62:Z62)-AG62 -> 0 | AL62: =ROUND(E62*(U62/Q62),0) -> 0 | AM62: =ROUND(E62*(T62/Q62),0) -> 0 | AN62: 0 | AO62: =AE62 -> 0 | AP62: 0 | AQ62: =SUM(F62:J62)-SUM(AK62:AP62) -> 11000 | AR62: =IF( AX62<15001,0,IF(AX62<20001,150,200)) -> 0 | AS62: 0 | AT62: =MIN( ROUND(AB62*12%,0),1800) -> 660 | AU62: =ROUNDUP(IF(E62<=21000,AG62*1.75%,0),0) -> 193 | AV62: =AU62 -> 193 | AW62: =SUM(V62:Z62)+SUM(AH62:AI62) -> 13000 | AX62: =AW62-AP62-SUM(AK62:AM62) -> 13000 | AY62: =SUM(AK62:AP62)+SUM(AR62:AT62)+AV62 -> 853 | AZ62: =AW62-AY62-BB62 -> 12147 | BA62: ESI is deducted because employee salary is under ESI slab
A63: =A62+1 -> 60 | B63: A4 | C63: 40182 | E63: 25000 | F63: =E63*50% -> 12500 | G63: =F63*40% -> 5000 | H63: =IF(E63<11750,0,3500) -> 3500 | I63: 0 | J63: =E63-SUM(F63:I63) -> 4000 | K63: 44896 | L63: =VLOOKUP(K63,SalaryMonth!$B$5:$E$16,2,FALSE) -> 44891 | M63: =VLOOKUP(K63,SalaryMonth!$B$5:$E$16,3,FALSE) -> 44920 | N63: =VLOOKUP(K63,SalaryMonth!$B$5:$E$16,4,FALSE) -> 30 | O63: =IF(L63<C63,"Y","N") -> N | P63: =IF(OR(D63<>"",M63<D63),"Y","N") -> N | Q63: 30 | R63: 29 | S63: 0 | T63: 0 | U63: 0 | V63: =ROUND((F63/N63)*Q63,0) -> 12500 | W63: =ROUND((G63/N63)*Q63,0) -> 5000 | X63: =ROUND((H63/N63)*Q63,0) -> 3500 | Y63: =(I63/N63)*Q63 -> 0 | Z63: =ROUND((J63/N63)*Q63,0) -> 4000 | AB63: =ROUND((V63/Q63)*Q63-(V63/Q63)*S63,0) -> 12500 | AC63: =ROUND((W63/Q63)*Q63-(W63/Q63)*S63,0) -> 5000 | AD63: =ROUND((X63/Q63)*Q63-(X63/Q63)*S63,0) -> 3500 | AE63: =Y63 -> 0 | AF63: =ROUND((Z63/Q63)*Q63-(Z63/Q63)*S63,0) -> 4000 | AG63: =SUM(AB63:AF63) -> 25000 | AH63: 0 | AI63: 0 | AJ63: =SUM(AB63:AI63) -> 50000 | AK63: =SUM(V63:Z63)-AG63 -> 0 | AL63: =ROUND(E63*(U63/Q63),0) -> 0 | AM63: =ROUND(E63*(T63/Q63),0) -> 0 | AN63: 0 | AO63: =AE63 -> 0 | AP63: 0 | AQ63: =SUM(F63:J63)-SUM(AK63:AP63) -> 25000 | AR63: =IF( AX63<15001,0,IF(AX63<20001,150,200)) -> 200 | AS63: 0 | AT63: =MIN( ROUND(AB63*12%,0),1800) -> 1500 | AU63: =ROUNDUP(IF(E63<=21000,AG63*1.75%,0),0) -> 0 | AV63: =AU63 -> 0 | AW63: =SUM(V63:Z63)+SUM(AH63:AI63) -> 25000 | AX63: =AW63-AP63-SUM(AK63:AM63) -> 25000 | AY63: =SUM(AK63:AP63)+SUM(AR63:AT63)+AV63 -> 1700 | AZ63: =AW63-AY63-BB63 -> 23300
A64: =A63+1 -> 61 | B64: A5 | C64: 40183 | E64: 45000 | F64: =E64*50% -> 22500 | G64: =F64*40% -> 9000 | H64: =IF(E64<11750,0,3500) -> 3500 | I64: 2400 | J64: =E64-SUM(F64:I64) -> 7600 | K64: 44896 | L64: =VLOOKUP(K64,SalaryMonth!$B$5:$E$16,2,FALSE) -> 44891 | M64: =VLOOKUP(K64,SalaryMonth!$B$5:$E$16,3,FALSE) -> 44920 | N64: =VLOOKUP(K64,SalaryMonth!$B$5:$E$16,4,FALSE) -> 30 | O64: =IF(L64<C64,"Y","N") -> N | P64: =IF(OR(D64<>"",M64<D64),"Y","N") -> N | Q64: 30 | R64: 29 | S64: 0 | T64: 0 | U64: 0 | V64: =ROUND((F64/N64)*Q64,0) -> 22500 | W64: =ROUND((G64/N64)*Q64,0) -> 9000 | X64: =ROUND((H64/N64)*Q64,0) -> 3500 | Y64: =(I64/N64)*Q64 -> 2400 | Z64: =ROUND((J64/N64)*Q64,0) -> 7600 | AB64: =ROUND((V64/Q64)*Q64-(V64/Q64)*S64,0) -> 22500 | AC64: =ROUND((W64/Q64)*Q64-(W64/Q64)*S64,0) -> 9000 | AD64: =ROUND((X64/Q64)*Q64-(X64/Q64)*S64,0) -> 3500 | AE64: =Y64 -> 2400 | AF64: =ROUND((Z64/Q64)*Q64-(Z64/Q64)*S64,0) -> 7600 | AG64: =SUM(AB64:AF64) -> 45000 | AH64: 0 | AI64: 0 | AJ64: =SUM(AB64:AI64) -> 90000 | AK64: =SUM(V64:Z64)-AG64 -> 0 | AL64: =ROUND(E64*(U64/Q64),0) -> 0 | AM64: =ROUND(E64*(T64/Q64),0) -> 0 | AN64: 3333 | AO64: =AE64 -> 2400 | AP64: 0 | AQ64: =SUM(F64:J64)-SUM(AK64:AP64) -> 39267 | AR64: =IF( AX64<15001,0,IF(AX64<20001,150,200)) -> 200 | AS64: 2000 | AT64: =MIN( ROUND(AB64*12%,0),1800) -> 1800 | AU64: =ROUNDUP(IF(E64<=21000,AG64*1.75%,0),0) -> 0 | AV64: =AU64 -> 0 | AW64: =SUM(V64:Z64)+SUM(AH64:AI64) -> 45000 | AX64: =AW64-AP64-SUM(AK64:AM64) -> 45000 | AY64: =SUM(AK64:AP64)+SUM(AR64:AT64)+AV64 -> 9733 | AZ64: =AW64-AY64-BB64 -> 35267 | BA64: Income tax Added
A65: =A64+1 -> 62 | B65: B1 | C65: 40183 | E65: 125000 | F65: =E65*50% -> 62500 | G65: =F65*40% -> 25000 | H65: =IF(E65<11750,0,3500) -> 3500 | I65: 2400 | J65: =E65-SUM(F65:I65) -> 31600 | K65: 44896 | L65: =VLOOKUP(K65,SalaryMonth!$B$5:$E$16,2,FALSE) -> 44891 | M65: =VLOOKUP(K65,SalaryMonth!$B$5:$E$16,3,FALSE) -> 44920 | N65: =VLOOKUP(K65,SalaryMonth!$B$5:$E$16,4,FALSE) -> 30 | O65: =IF(L65<C65,"Y","N") -> N | P65: =IF(OR(D65<>"",M65<D65),"Y","N") -> N | Q65: 30 | R65: 30 | S65: 0 | T65: 0 | U65: 0 | V65: =ROUND((F65/N65)*Q65,0) -> 62500 | W65: =ROUND((G65/N65)*Q65,0) -> 25000 | X65: =ROUND((H65/N65)*Q65,0) -> 3500 | Y65: =(I65/N65)*Q65 -> 2400 | Z65: =ROUND((J65/N65)*Q65,0) -> 31600 | AB65: =ROUND((V65/Q65)*Q65-(V65/Q65)*S65,0) -> 62500 | AC65: =ROUND((W65/Q65)*Q65-(W65/Q65)*S65,0) -> 25000 | AD65: =ROUND((X65/Q65)*Q65-(X65/Q65)*S65,0) -> 3500 | AE65: =I65 -> 2400 | AF65: =ROUND((Z65/Q65)*Q65-(Z65/Q65)*S65,0) -> 31600 | AG65: =SUM(AB65:AF65) -> 125000 | AH65: 0 | AI65: 0 | AJ65: =SUM(AB65:AI65) -> 250000 | AK65: =SUM(V65:Z65)-AG65 -> 0 | AL65: =ROUND(E65*(U65/Q65),0) -> 0 | AM65: =ROUND(E65*(T65/Q65),0) -> 0 | AN65: 0 | AO65: =AE65 -> 2400 | AP65: 0 | AQ65: =SUM(F65:J65)-SUM(AK65:AP65) -> 122600 | AR65: =IF( AX65<15001,0,IF(AX65<20001,150,200)) -> 200 | AS65: 0 | AT65: =MIN( ROUND(AB65*12%,0),1800) -> 1800 | AU65: =ROUNDUP(IF(E65<=21000,AG65*1.75%,0),0) -> 0 | AV65: =AU65 -> 0 | AW65: =SUM(V65:Z65)+SUM(AH65:AI65) -> 125000 | AX65: =AW65-AP65-SUM(AK65:AM65) -> 125000 | AY65: =SUM(AK65:AP65)+SUM(AR65:AT65)+AV65 -> 4400 | AZ65: =AW65-AY65-BB65 -> 108118 | BA65: Income tax Added | BB65: 12482
A66: =A65+1 -> 63 | AK66: =SUM(V66:Z66)-AG66 -> 0 | AZ66: =AW66-AY66-BB66 -> 0
A67: =A66+1 -> 64 | B67: A1 | C67: 40180 | E67: 62000 | F67: =E67*50% -> 31000 | G67: =F67*40% -> 12400 | H67: =IF(E67<11750,0,3500) -> 3500 | I67: 0 | J67: =E67-SUM(F67:I67) -> 15100 | K67: 44927 | L67: =VLOOKUP(K67,SalaryMonth!$B$5:$E$16,2,FALSE) -> 44921 | M67: =VLOOKUP(K67,SalaryMonth!$B$5:$E$16,3,FALSE) -> 44951 | N67: =VLOOKUP(K67,SalaryMonth!$B$5:$E$16,4,FALSE) -> 31 | O67: =IF(L67<=C67,"Y","N") -> N | P67: =IF(OR(D67<>"",M67<D67),"Y","N") -> N | Q67: 31 | R67: 29 | S67: 1 | T67: 1 | U67: 0 | V67: =ROUND((F67/N67)*Q67,0) -> 31000 | W67: =ROUND((G67/N67)*Q67,0) -> 12400 | X67: =ROUND((H67/N67)*Q67,0) -> 3500 | Y67: =(I67/N67)*Q67 -> 0 | Z67: =ROUND((J67/N67)*Q67,0) -> 15100 | AB67: =ROUND((V67/Q67)*Q67-(V67/Q67)*S67,0) -> 30000 | AC67: =ROUND((W67/Q67)*Q67-(W67/Q67)*S67,0) -> 12000 | AD67: =ROUND((X67/Q67)*Q67-(X67/Q67)*S67,0) -> 3387 | AE67: =Y67 -> 0 | AF67: =ROUND((Z67/Q67)*Q67-(Z67/Q67)*S67,0) -> 14613 | AG67: =SUM(AB67:AF67) -> 60000 | AH67: 0 | AI67: 0 | AJ67: =SUM(AB67:AI67) -> 120000 | AK67: =SUM(V67:Z67)-AG67 -> 2000 | AL67: =ROUND(E67*(U67/Q67),0) -> 0 | AM67: =ROUND(E67*(T67/Q67),0) -> 2000 | AN67: 0 | AO67: =AE67 -> 0 | AP67: 2000 | AQ67: =SUM(F67:J67)-SUM(AK67:AP67) -> 56000 | AR67: =IF( AX67<15001,0,IF(AX67<20001,150,200)) -> 200 | AS67: 0 | AT67: =MIN( ROUND(AB67*12%,0),1800) -> 1800 | AU67: =ROUNDUP(IF(E67<=21000,AG67*1.75%,0),0) -> 0 | AV67: =AU67 -> 0 | AW67: =SUM(V67:Z67)+SUM(AH67:AI67) -> 62000 | AX67: =AW67-AP67-SUM(AK67:AM67) -> 56000 | AY67: =SUM(AK67:AP67)+SUM(AR67:AT67)+AV67 -> 8000 | AZ67: =AW67-AY67-BB67 -> 54000 | BA67: Paycut added 2000/LC Amount 2000
A68: =A67+1 -> 65 | B68: A2 | C68: 40180 | E68: 44000 | F68: =E68*50% -> 22000 | G68: =F68*40% -> 8800 | H68: =IF(E68<11750,0,3500) -> 3500 | I68: 0 | J68: =E68-SUM(F68:I68) -> 9700 | K68: 44927 | L68: =VLOOKUP(K68,SalaryMonth!$B$5:$E$16,2,FALSE) -> 44921 | M68: =VLOOKUP(K68,SalaryMonth!$B$5:$E$16,3,FALSE) -> 44951 | N68: =VLOOKUP(K68,SalaryMonth!$B$5:$E$16,4,FALSE) -> 31 | O68: =IF(L68<C68,"Y","N") -> N | P68: =IF(OR(D68<>"",M68<D68),"Y","N") -> N | Q68: 31 | R68: 29 | S68: 0 | T68: 0 | U68: 0 | V68: =ROUND((F68/N68)*Q68,0) -> 22000 | W68: =ROUND((G68/N68)*Q68,0) -> 8800 | X68: =ROUND((H68/N68)*Q68,0) -> 3500 | Y68: =(I68/N68)*Q68 -> 0 | Z68: =ROUND((J68/N68)*Q68,0) -> 9700 | AB68: =ROUND((V68/Q68)*Q68-(V68/Q68)*S68,0) -> 22000 | AC68: =ROUND((W68/Q68)*Q68-(W68/Q68)*S68,0) -> 8800 | AD68: =ROUND((X68/Q68)*Q68-(X68/Q68)*S68,0) -> 3500 | AE68: =Y68 -> 0 | AF68: =ROUND((Z68/Q68)*Q68-(Z68/Q68)*S68,0) -> 9700 | AG68: =SUM(AB68:AF68) -> 44000 | AH68: 0 | AI68: 0 | AJ68: =SUM(AB68:AI68) -> 88000 | AK68: =SUM(V68:Z68)-AG68 -> 0 | AL68: =ROUND(E68*(U68/Q68),0) -> 0 | AM68: =ROUND(E68*(T68/Q68),0) -> 0 | AN68: 0 | AO68: =AE68 -> 0 | AP68: 0 | AQ68: =SUM(F68:J68)-SUM(AK68:AP68) -> 44000 | AR68: =IF( AX68<15001,0,IF(AX68<20001,150,200)) -> 200 | AS68: 0 | AT68: =MIN( ROUND(AB68*12%,0),1800) -> 1800 | AU68: =ROUNDUP(IF(E68<=21000,AG68*1.75%,0),0) -> 0 | AV68: =ROUNDUP(AG68 *1.75%,0) -> 770 | AW68: =SUM(V68:Z68)+SUM(AH68:AI68) -> 44000 | AX68: =AW68-AP68-SUM(AK68:AM68) -> 44000 | AY68: =SUM(AK68:AP68)+SUM(AR68:AT68)+AV68 -> 2770 | AZ68: =AW68-AY68-BB68 -> 41230 | BA68: ESI IS Deducted Because Employe Have An ESI Deduction in last Month
A69: =A68+1 -> 66 | B69: A3 | C69: 40181 | E69: 11000 | F69: =E69*50% -> 5500 | G69: =F69*40% -> 2200 | H69: =IF(E69<11750,0,3500) -> 0 | I69: 0 | J69: =E69-SUM(F69:I69) -> 3300 | K69: 44927 | L69: =VLOOKUP(K69,SalaryMonth!$B$5:$E$16,2,FALSE) -> 44921 | M69: =VLOOKUP(K69,SalaryMonth!$B$5:$E$16,3,FALSE) -> 44951 | N69: =VLOOKUP(K69,SalaryMonth!$B$5:$E$16,4,FALSE) -> 31 | O69: =IF(L69<C69,"Y","N") -> N | P69: =IF(OR(D69<>"",M69<D69),"Y","N") -> N | Q69: 31 | R69: 29 | S69: 0 | T69: 0 | U69: 0 | V69: =ROUND((F69/N69)*Q69,0) -> 5500 | W69: =ROUND((G69/N69)*Q69,0) -> 2200 | X69: =ROUND((H69/N69)*Q69,0) -> 0 | Y69: =(I69/N69)*Q69 -> 0 | Z69: =ROUND((J69/N69)*Q69,0) -> 3300 | AB69: =ROUND((V69/Q69)*Q69-(V69/Q69)*S69,0) -> 5500 | AC69: =ROUND((W69/Q69)*Q69-(W69/Q69)*S69,0) -> 2200 | AD69: =ROUND((X69/Q69)*Q69-(X69/Q69)*S69,0) -> 0 | AE69: =Y69 -> 0 | AF69: =ROUND((Z69/Q69)*Q69-(Z69/Q69)*S69,0) -> 3300 | AG69: =SUM(AB69:AF69) -> 11000 | AH69: 0 | AI69: 0 | AJ69: =SUM(AB69:AI69) -> 22000 | AK69: =SUM(V69:Z69)-AG69 -> 0 | AL69: =ROUND(E69*(U69/Q69),0) -> 0 | AM69: =ROUND(E69*(T69/Q69),0) -> 0 | AN69: 0 | AO69: =AE69 -> 0 | AP69: 0 | AQ69: =SUM(F69:J69)-SUM(AK69:AP69) -> 11000 | AR69: =IF( AX69<15001,0,IF(AX69<20001,150,200)) -> 0 | AS69: 0 | AT69: =MIN( ROUND(AB69*12%,0),1800) -> 660 | AU69: =ROUNDUP(IF(E69<=21000,AG69*1.75%,0),0) -> 193 | AV69: =AU69 -> 193 | AW69: =SUM(V69:Z69)+SUM(AH69:AI69) -> 11000 | AX69: =AW69-AP69-SUM(AK69:AM69) -> 11000 | AY69: =SUM(AK69:AP69)+SUM(AR69:AT69)+AV69 -> 853 | AZ69: =AW69-AY69-BB69 -> 10147 | BA69: ESI is deducted because employee salary is under ESI slab
A70: =A69+1 -> 67 | B70: A4 | C70: 40182 | E70: 25000 | F70: =E70*50% -> 12500 | G70: =F70*40% -> 5000 | H70: =IF(E70<11750,0,3500) -> 3500 | I70: 0 | J70: =E70-SUM(F70:I70) -> 4000 | K70: 44927 | L70: =VLOOKUP(K70,SalaryMonth!$B$5:$E$16,2,FALSE) -> 44921 | M70: =VLOOKUP(K70,SalaryMonth!$B$5:$E$16,3,FALSE) -> 44951 | N70: =VLOOKUP(K70,SalaryMonth!$B$5:$E$16,4,FALSE) -> 31 | O70: =IF(L70<C70,"Y","N") -> N | P70: =IF(OR(D70<>"",M70<D70),"Y","N") -> N | Q70: 31 | R70: 29 | S70: 0 | T70: 0 | U70: 0 | V70: =ROUND((F70/N70)*Q70,0) -> 12500 | W70: =ROUND((G70/N70)*Q70,0) -> 5000 | X70: =ROUND((H70/N70)*Q70,0) -> 3500 | Y70: =(I70/N70)*Q70 -> 0 | Z70: =ROUND((J70/N70)*Q70,0) -> 4000 | AB70: =ROUND((V70/Q70)*Q70-(V70/Q70)*S70,0) -> 12500 | AC70: =ROUND((W70/Q70)*Q70-(W70/Q70)*S70,0) -> 5000 | AD70: =ROUND((X70/Q70)*Q70-(X70/Q70)*S70,0) -> 3500 | AE70: =Y70 -> 0 | AF70: =ROUND((Z70/Q70)*Q70-(Z70/Q70)*S70,0) -> 4000 | AG70: =SUM(AB70:AF70) -> 25000 | AH70: 0 | AI70: 0 | AJ70: =SUM(AB70:AI70) -> 50000 | AK70: =SUM(V70:Z70)-AG70 -> 0 | AL70: =ROUND(E70*(U70/Q70),0) -> 0 | AM70: =ROUND(E70*(T70/Q70),0) -> 0 | AN70: 0 | AO70: =AE70 -> 0 | AP70: 0 | AQ70: =SUM(F70:J70)-SUM(AK70:AP70) -> 25000 | AR70: =IF( AX70<15001,0,IF(AX70<20001,150,200)) -> 200 | AS70: 0 | AT70: =MIN( ROUND(AB70*12%,0),1800) -> 1500 | AU70: =ROUNDUP(IF(E70<=21000,AG70*1.75%,0),0) -> 0 | AV70: =AU70 -> 0 | AW70: =SUM(V70:Z70)+SUM(AH70:AI70) -> 25000 | AX70: =AW70-AP70-SUM(AK70:AM70) -> 25000 | AY70: =SUM(AK70:AP70)+SUM(AR70:AT70)+AV70 -> 1700 | AZ70: =AW70-AY70-BB70 -> 23300
A71: =A70+1 -> 68 | B71: A5 | C71: 40183 | E71: 32000 | F71: =E71*50% -> 16000 | G71: =F71*40% -> 6400 | H71: =IF(E71<11750,0,3500) -> 3500 | I71: 0 | J71: =E71-SUM(F71:I71) -> 6100 | K71: 44927 | L71: =VLOOKUP(K71,SalaryMonth!$B$5:$E$16,2,FALSE) -> 44921 | M71: =VLOOKUP(K71,SalaryMonth!$B$5:$E$16,3,FALSE) -> 44951 | N71: =VLOOKUP(K71,SalaryMonth!$B$5:$E$16,4,FALSE) -> 31 | O71: =IF(L71<C71,"Y","N") -> N | P71: =IF(OR(D71<>"",M71<D71),"Y","N") -> N | Q71: 31 | R71: 29 | S71: 0 | T71: 0 | U71: 0 | V71: =ROUND((F71/N71)*Q71,0) -> 16000 | W71: =ROUND((G71/N71)*Q71,0) -> 6400 | X71: =ROUND((H71/N71)*Q71,0) -> 3500 | Y71: =(I71/N71)*Q71 -> 0 | Z71: =ROUND((J71/N71)*Q71,0) -> 6100 | AB71: =ROUND((V71/Q71)*Q71-(V71/Q71)*S71,0) -> 16000 | AC71: =ROUND((W71/Q71)*Q71-(W71/Q71)*S71,0) -> 6400 | AD71: =ROUND((X71/Q71)*Q71-(X71/Q71)*S71,0) -> 3500 | AE71: =Y71 -> 0 | AF71: =ROUND((Z71/Q71)*Q71-(Z71/Q71)*S71,0) -> 6100 | AG71: =SUM(AB71:AF71) -> 32000 | AH71: 0 | AI71: 0 | AJ71: =SUM(AB71:AI71) -> 64000 | AK71: =SUM(V71:Z71)-AG71 -> 0 | AL71: =ROUND(E71*(U71/Q71),0) -> 0 | AM71: =ROUND(E71*(T71/Q71),0) -> 0 | AN71: 3333 | AO71: =AE71 -> 0 | AP71: 0 | AQ71: =SUM(F71:J71)-SUM(AK71:AP71) -> 28667 | AR71: =IF( AX71<15001,0,IF(AX71<20001,150,200)) -> 200 | AS71: 0 | AT71: =MIN( ROUND(AB71*12%,0),1800) -> 1800 | AU71: =ROUNDUP(IF(E71<=21000,AG71*1.75%,0),0) -> 0 | AV71: =AU71 -> 0 | AW71: =SUM(V71:Z71)+SUM(AH71:AI71) -> 32000 | AX71: =AW71-AP71-SUM(AK71:AM71) -> 32000 | AY71: =SUM(AK71:AP71)+SUM(AR71:AT71)+AV71 -> 5333 | AZ71: =AW71-AY71-BB71 -> 26667
A72: =A71+1 -> 69 | B72: B1 | C72: 40183 | E72: 125000 | F72: =E72*50% -> 62500 | G72: =F72*40% -> 25000 | H72: =IF(E72<11750,0,3500) -> 3500 | I72: 2400 | J72: =E72-SUM(F72:I72) -> 31600 | K72: 44927 | L72: =VLOOKUP(K72,SalaryMonth!$B$5:$E$16,2,FALSE) -> 44921 | M72: =VLOOKUP(K72,SalaryMonth!$B$5:$E$16,3,FALSE) -> 44951 | N72: =VLOOKUP(K72,SalaryMonth!$B$5:$E$16,4,FALSE) -> 31 | O72: =IF(L72<C72,"Y","N") -> N | P72: =IF(OR(D72<>"",M72<D72),"Y","N") -> N | Q72: 31 | R72: 31 | S72: 0 | T72: 0 | U72: 0 | V72: =ROUND((F72/N72)*Q72,0) -> 62500 | W72: =ROUND((G72/N72)*Q72,0) -> 25000 | X72: =ROUND((H72/N72)*Q72,0) -> 3500 | Y72: =(I72/N72)*Q72 -> 2400 | Z72: =ROUND((J72/N72)*Q72,0) -> 31600 | AB72: =ROUND((V72/Q72)*Q72-(V72/Q72)*S72,0) -> 62500 | AC72: =ROUND((W72/Q72)*Q72-(W72/Q72)*S72,0) -> 25000 | AD72: =ROUND((X72/Q72)*Q72-(X72/Q72)*S72,0) -> 3500 | AE72: =I72 -> 2400 | AF72: =ROUND((Z72/Q72)*Q72-(Z72/Q72)*S72,0) -> 31600 | AG72: =SUM(AB72:AF72) -> 125000 | AH72: 0 | AI72: 0 | AJ72: =SUM(AB72:AI72) -> 250000 | AK72: =SUM(V72:Z72)-AG72 -> 0 | AL72: =ROUND(E72*(U72/Q72),0) -> 0 | AM72: =ROUND(E72*(T72/Q72),0) -> 0 | AN72: 0 | AO72: =AE72 -> 2400 | AP72: 0 | AQ72: =SUM(F72:J72)-SUM(AK72:AP72) -> 122600 | AR72: =IF( AX72<15001,0,IF(AX72<20001,150,200)) -> 200 | AS72: 0 | AT72: =MIN( ROUND(AB72*12%,0),1800) -> 1800 | AU72: =ROUNDUP(IF(E72<=21000,AG72*1.75%,0),0) -> 0 | AV72: =AU72 -> 0 | AW72: =SUM(V72:Z72)+SUM(AH72:AI72) -> 125000 | AX72: =AW72-AP72-SUM(AK72:AM72) -> 125000 | AY72: =SUM(AK72:AP72)+SUM(AR72:AT72)+AV72 -> 4400 | AZ72: =AW72-AY72-BB72 -> 120600 | BA72: Income tax Added
A73: =A72+1 -> 70 | AK73: =SUM(V73:Z73)-AG73 -> 0 | AZ73: =AW73-AY73-BB73 -> 0
A74: =A73+1 -> 71 | B74: A1 | C74: 40180 | E74: 62000 | F74: =E74*50% -> 31000 | G74: =F74*40% -> 12400 | H74: =IF(E74<11750,0,3500) -> 3500 | I74: 0 | J74: =E74-SUM(F74:I74) -> 15100 | K74: 44958 | L74: =VLOOKUP(K74,SalaryMonth!$B$5:$E$16,2,FALSE) -> 44952 | M74: =VLOOKUP(K74,SalaryMonth!$B$5:$E$16,3,FALSE) -> 44982 | N74: =VLOOKUP(K74,SalaryMonth!$B$5:$E$16,4,FALSE) -> 31 | O74: =IF(L74<=C74,"Y","N") -> N | P74: =IF(OR(D74<>"",M74<D74),"Y","N") -> N | Q74: 31 | R74: 29 | S74: 1 | T74: 0 | U74: 0 | V74: =ROUND((F74/N74)*Q74,0) -> 31000 | W74: =ROUND((G74/N74)*Q74,0) -> 12400 | X74: =ROUND((H74/N74)*Q74,0) -> 3500 | Y74: =(I74/N74)*Q74 -> 0 | Z74: =ROUND((J74/N74)*Q74,0) -> 15100 | AB74: =ROUND((V74/Q74)*Q74-(V74/Q74)*S74,0) -> 30000 | AC74: =ROUND((W74/Q74)*Q74-(W74/Q74)*S74,0) -> 12000 | AD74: =ROUND((X74/Q74)*Q74-(X74/Q74)*S74,0) -> 3387 | AE74: =Y74 -> 0 | AF74: =ROUND((Z74/Q74)*Q74-(Z74/Q74)*S74,0) -> 14613 | AG74: =SUM(AB74:AF74) -> 60000 | AH74: 0 | AI74: 0 | AJ74: =SUM(AB74:AI74) -> 120000 | AK74: =SUM(V74:Z74)-AG74 -> 2000 | AL74: =ROUND(E74*(U74/Q74),0) -> 0 | AM74: =ROUND(E74*(T74/Q74),0) -> 0 | AN74: 0 | AO74: =AE74 -> 0 | AP74: 2000 | AQ74: =SUM(F74:J74)-SUM(AK74:AP74) -> 58000 | AR74: =IF( AX74<15001,0,IF(AX74<20001,150,200)) -> 200 | AS74: 0 | AT74: =MIN( ROUND(AB74*12%,0),1800) -> 1800 | AU74: =ROUNDUP(IF(E74<=21000,AG74*1.75%,0),0) -> 0 | AV74: =AU74 -> 0 | AW74: =SUM(V74:Z74)+SUM(AH74:AI74) -> 62000 | AX74: =AW74-AP74-SUM(AK74:AM74) -> 58000 | AY74: =SUM(AK74:AP74)+SUM(AR74:AT74)+AV74 -> 6000 | AZ74: =AW74-AY74-BB74 -> 56000 | BA74: Paycut added 2000/Advance Deducted 8333
A75: =A74+1 -> 72 | B75: A2 | C75: 40180 | E75: 34000 | F75: =E75*50% -> 17000 | G75: =F75*40% -> 6800 | H75: =IF(E75<11750,0,3500) -> 3500 | I75: 0 | J75: =E75-SUM(F75:I75) -> 6700 | K75: 44958 | L75: =VLOOKUP(K75,SalaryMonth!$B$5:$E$16,2,FALSE) -> 44952 | M75: =VLOOKUP(K75,SalaryMonth!$B$5:$E$16,3,FALSE) -> 44982 | N75: =VLOOKUP(K75,SalaryMonth!$B$5:$E$16,4,FALSE) -> 31 | O75: =IF(L75<C75,"Y","N") -> N | P75: =IF(OR(D75<>"",M75<D75),"Y","N") -> N | Q75: 31 | R75: 29 | S75: 0 | T75: 0 | U75: 0 | V75: =ROUND((F75/N75)*Q75,0) -> 17000 | W75: =ROUND((G75/N75)*Q75,0) -> 6800 | X75: =ROUND((H75/N75)*Q75,0) -> 3500 | Y75: =(I75/N75)*Q75 -> 0 | Z75: =ROUND((J75/N75)*Q75,0) -> 6700 | AB75: =ROUND((V75/Q75)*Q75-(V75/Q75)*S75,0) -> 17000 | AC75: =ROUND((W75/Q75)*Q75-(W75/Q75)*S75,0) -> 6800 | AD75: =ROUND((X75/Q75)*Q75-(X75/Q75)*S75,0) -> 3500 | AE75: =Y75 -> 0 | AF75: =ROUND((Z75/Q75)*Q75-(Z75/Q75)*S75,0) -> 6700 | AG75: =SUM(AB75:AF75) -> 34000 | AH75: 0 | AI75: 0 | AJ75: =SUM(AB75:AI75) -> 68000 | AK75: =SUM(V75:Z75)-AG75 -> 0 | AL75: =ROUND(E75*(U75/Q75),0) -> 0 | AM75: =ROUND(E75*(T75/Q75),0) -> 0 | AN75: 0 | AO75: =AE75 -> 0 | AP75: 0 | AQ75: =SUM(F75:J75)-SUM(AK75:AP75) -> 34000 | AR75: =IF( AX75<15001,0,IF(AX75<20001,150,200)) -> 200 | AS75: 0 | AT75: =MIN( ROUND(AB75*12%,0),1800) -> 1800 | AU75: =ROUNDUP(IF(E75<=21000,AG75*1.75%,0),0) -> 0 | AV75: =ROUNDUP(AG75 *1.75%,0) -> 595 | AW75: =SUM(V75:Z75)+SUM(AH75:AI75) -> 34000 | AX75: =AW75-AP75-SUM(AK75:AM75) -> 34000 | AY75: =SUM(AK75:AP75)+SUM(AR75:AT75)+AV75 -> 2595 | AZ75: =AW75-AY75-BB75 -> 31405 | BA75: ESI IS Deducted Because Employe Have An ESI Deduction in last Month
A76: =A75+1 -> 73 | B76: A3 | C76: 40181 | E76: 11000 | F76: =E76*50% -> 5500 | G76: =F76*40% -> 2200 | H76: =IF(E76<11750,0,3500) -> 0 | I76: 0 | J76: =E76-SUM(F76:I76) -> 3300 | K76: 44958 | L76: =VLOOKUP(K76,SalaryMonth!$B$5:$E$16,2,FALSE) -> 44952 | M76: =VLOOKUP(K76,SalaryMonth!$B$5:$E$16,3,FALSE) -> 44982 | N76: =VLOOKUP(K76,SalaryMonth!$B$5:$E$16,4,FALSE) -> 31 | O76: =IF(L76<C76,"Y","N") -> N | P76: =IF(OR(D76<>"",M76<D76),"Y","N") -> N | Q76: 31 | R76: 29 | S76: 0 | T76: 0 | U76: 0 | V76: =ROUND((F76/N76)*Q76,0) -> 5500 | W76: =ROUND((G76/N76)*Q76,0) -> 2200 | X76: =ROUND((H76/N76)*Q76,0) -> 0 | Y76: =(I76/N76)*Q76 -> 0 | Z76: =ROUND((J76/N76)*Q76,0) -> 3300 | AB76: =ROUND((V76/Q76)*Q76-(V76/Q76)*S76,0) -> 5500 | AC76: =ROUND((W76/Q76)*Q76-(W76/Q76)*S76,0) -> 2200 | AD76: =ROUND((X76/Q76)*Q76-(X76/Q76)*S76,0) -> 0 | AE76: =Y76 -> 0 | AF76: =ROUND((Z76/Q76)*Q76-(Z76/Q76)*S76,0) -> 3300 | AG76: =SUM(AB76:AF76) -> 11000 | AH76: 0 | AI76: 0 | AJ76: =SUM(AB76:AI76) -> 22000 | AK76: =SUM(V76:Z76)-AG76 -> 0 | AL76: =ROUND(E76*(U76/Q76),0) -> 0 | AM76: =ROUND(E76*(T76/Q76),0) -> 0 | AN76: 0 | AO76: =AE76 -> 0 | AP76: 0 | AQ76: =SUM(F76:J76)-SUM(AK76:AP76) -> 11000 | AR76: =IF( AX76<15001,0,IF(AX76<20001,150,200)) -> 0 | AS76: 0 | AT76: =MIN( ROUND(AB76*12%,0),1800) -> 660 | AU76: =ROUNDUP(IF(E76<=21000,AG76*1.75%,0),0) -> 193 | AV76: =AU76 -> 193 | AW76: =SUM(V76:Z76)+SUM(AH76:AI76) -> 11000 | AX76: =AW76-AP76-SUM(AK76:AM76) -> 11000 | AY76: =SUM(AK76:AP76)+SUM(AR76:AT76)+AV76 -> 853 | AZ76: =AW76-AY76-BB76 -> 10147 | BA76: ESI is deducted because employee salary is under ESI slab
A77: =A76+1 -> 74 | B77: A4 | C77: 40182 | E77: 25000 | F77: =E77*50% -> 12500 | G77: =F77*40% -> 5000 | H77: =IF(E77<11750,0,3500) -> 3500 | I77: 0 | J77: =E77-SUM(F77:I77) -> 4000 | K77: 44958 | L77: =VLOOKUP(K77,SalaryMonth!$B$5:$E$16,2,FALSE) -> 44952 | M77: =VLOOKUP(K77,SalaryMonth!$B$5:$E$16,3,FALSE) -> 44982 | N77: =VLOOKUP(K77,SalaryMonth!$B$5:$E$16,4,FALSE) -> 31 | O77: =IF(L77<C77,"Y","N") -> N | P77: =IF(OR(D77<>"",M77<D77),"Y","N") -> N | Q77: 31 | R77: 29 | S77: 0 | T77: 0 | U77: 0 | V77: =ROUND((F77/N77)*Q77,0) -> 12500 | W77: =ROUND((G77/N77)*Q77,0) -> 5000 | X77: =ROUND((H77/N77)*Q77,0) -> 3500 | Y77: =(I77/N77)*Q77 -> 0 | Z77: =ROUND((J77/N77)*Q77,0) -> 4000 | AB77: =ROUND((V77/Q77)*Q77-(V77/Q77)*S77,0) -> 12500 | AC77: =ROUND((W77/Q77)*Q77-(W77/Q77)*S77,0) -> 5000 | AD77: =ROUND((X77/Q77)*Q77-(X77/Q77)*S77,0) -> 3500 | AE77: =Y77 -> 0 | AF77: =ROUND((Z77/Q77)*Q77-(Z77/Q77)*S77,0) -> 4000 | AG77: =SUM(AB77:AF77) -> 25000 | AH77: 0 | AI77: 0 | AJ77: =SUM(AB77:AI77) -> 50000 | AK77: =SUM(V77:Z77)-AG77 -> 0 | AL77: =ROUND(E77*(U77/Q77),0) -> 0 | AM77: =ROUND(E77*(T77/Q77),0) -> 0 | AN77: 0 | AO77: =AE77 -> 0 | AP77: 0 | AQ77: =SUM(F77:J77)-SUM(AK77:AP77) -> 25000 | AR77: =IF( AX77<15001,0,IF(AX77<20001,150,200)) -> 200 | AS77: 0 | AT77: =MIN( ROUND(AB77*12%,0),1800) -> 1500 | AU77: =ROUNDUP(IF(E77<=21000,AG77*1.75%,0),0) -> 0 | AV77: =AU77 -> 0 | AW77: =SUM(V77:Z77)+SUM(AH77:AI77) -> 25000 | AX77: =AW77-AP77-SUM(AK77:AM77) -> 25000 | AY77: =SUM(AK77:AP77)+SUM(AR77:AT77)+AV77 -> 1700 | AZ77: =AW77-AY77-BB77 -> 23300
A78: =A77+1 -> 75 | B78: A5 | C78: 40183 | D78: 44962 | E78: 32000 | F78: =E78*50% -> 16000 | G78: =F78*40% -> 6400 | H78: =IF(E78<11750,0,3500) -> 3500 | I78: 0 | J78: =E78-SUM(F78:I78) -> 6100 | K78: 44958 | L78: =VLOOKUP(K78,SalaryMonth!$B$5:$E$16,2,FALSE) -> 44952 | M78: =VLOOKUP(K78,SalaryMonth!$B$5:$E$16,3,FALSE) -> 44982 | N78: =VLOOKUP(K78,SalaryMonth!$B$5:$E$16,4,FALSE) -> 31 | O78: =IF(L78<C78,"Y","N") -> N | P78: =IF(OR(D78<>"",M78<D78),"Y","N") -> Y | Q78: 11 | R78: 11 | S78: 0 | T78: 0 | U78: 0 | V78: =ROUND((F78/N78)*Q78,0) -> 5677 | W78: =ROUND((G78/N78)*Q78,0) -> 2271 | X78: =ROUND((H78/N78)*Q78,0) -> 1242 | Y78: =(I78/N78)*Q78 -> 0 | Z78: =ROUND((J78/N78)*Q78,0) -> 2165 | AB78: =ROUND((V78/Q78)*Q78-(V78/Q78)*S78,0) -> 5677 | AC78: =ROUND((W78/Q78)*Q78-(W78/Q78)*S78,0) -> 2271 | AD78: =ROUND((X78/Q78)*Q78-(X78/Q78)*S78,0) -> 1242 | AE78: =Y78 -> 0 | AF78: =ROUND((Z78/Q78)*Q78-(Z78/Q78)*S78,0) -> 2165 | AG78: =SUM(AB78:AF78) -> 11355 | AH78: 0 | AI78: 0 | AJ78: =SUM(AB78:AI78) -> 22710 | AK78: =SUM(V78:Z78)-AG78 -> 0 | AL78: =ROUND(E78*(U78/Q78),0) -> 0 | AM78: =ROUND(E78*(T78/Q78),0) -> 0 | AN78: 3333 | AO78: =AE78 -> 0 | AP78: 0 | AQ78: =SUM(F78:J78)-SUM(AK78:AP78) -> 28667 | AR78: =IF( AX78<15001,0,IF(AX78<20001,150,200)) -> 0 | AS78: 0 | AT78: =MIN( ROUND(AB78*12%,0),1800) -> 681 | AU78: =ROUNDUP(IF(E78<=21000,AG78*1.75%,0),0) -> 0 | AV78: =AU78 -> 0 | AW78: =SUM(V78:Z78)+SUM(AH78:AI78) -> 11355 | AX78: =AW78-AP78-SUM(AK78:AM78) -> 11355 | AY78: =SUM(AK78:AP78)+SUM(AR78:AT78)+AV78 -> 4014 | AZ78: =AW78-AY78-BB78 -> 7341
A79: =A78+1 -> 76 | B79: A6 | C79: 44973 | E79: 31000 | F79: =E79*50% -> 15500 | G79: =F79*40% -> 6200 | H79: =IF(E79<11750,0,3500) -> 3500 | I79: 0 | J79: =E79-SUM(F79:I79) -> 5800 | K79: 44958 | L79: =VLOOKUP(K79,SalaryMonth!$B$5:$E$16,2,FALSE) -> 44952 | M79: =VLOOKUP(K79,SalaryMonth!$B$5:$E$16,3,FALSE) -> 44982 | N79: =VLOOKUP(K79,SalaryMonth!$B$5:$E$16,4,FALSE) -> 31 | O79: =IF(L79<C79,"Y","N") -> Y | P79: =IF(OR(D79<>"",M79<D79),"Y","N") -> N | Q79: 10 | R79: 10 | S79: 0 | T79: 0 | U79: 0 | V79: =ROUND((F79/N79)*Q79,0) -> 5000 | W79: =ROUND((G79/N79)*Q79,0) -> 2000 | X79: =ROUND((H79/N79)*Q79,0) -> 1129 | Y79: =(I79/N79)*Q79 -> 0 | Z79: =ROUND((J79/N79)*Q79,0) -> 1871 | AB79: =ROUND((V79/Q79)*Q79-(V79/Q79)*S79,0) -> 5000 | AC79: =ROUND((W79/Q79)*Q79-(W79/Q79)*S79,0) -> 2000 | AD79: =ROUND((X79/Q79)*Q79-(X79/Q79)*S79,0) -> 1129 | AE79: =Y79 -> 0 | AF79: =ROUND((Z79/Q79)*Q79-(Z79/Q79)*S79,0) -> 1871 | AG79: =SUM(AB79:AF79) -> 10000 | AH79: 0 | AI79: 0 | AJ79: =SUM(AB79:AI79) -> 20000 | AK79: =SUM(V79:Z79)-AG79 -> 0 | AL79: =ROUND(E79*(U79/Q79),0) -> 0 | AM79: =ROUND(E79*(T79/Q79),0) -> 0 | AN79: 0 | AO79: =AE79 -> 0 | AP79: 0 | AQ79: =SUM(F79:J79)-SUM(AK79:AP79) -> 31000 | AR79: =IF( AX79<15001,0,IF(AX79<20001,150,200)) -> 0 | AS79: 0 | AT79: =MIN( ROUND(AB79*12%,0),1800) -> 600 | AU79: =ROUNDUP(IF(E79<=21000,AG79*1.75%,0),0) -> 0 | AV79: =AU79 -> 0 | AW79: =SUM(V79:Z79)+SUM(AH79:AI79) -> 10000 | AX79: =AW79-AP79-SUM(AK79:AM79) -> 10000 | AY79: =SUM(AK79:AP79)+SUM(AR79:AT79)+AV79 -> 600 | AZ79: =AW79-AY79-BB79 -> 9400 | BA79: New employee
A80: =A79+1 -> 77 | B80: A7 | C80: 44967 | D80: 44976 | E80: 31000 | F80: =E80*50% -> 15500 | G80: =F80*40% -> 6200 | H80: =IF(E80<11750,0,3500) -> 3500 | I80: 0 | J80: =E80-SUM(F80:I80) -> 5800 | K80: 44958 | L80: =VLOOKUP(K80,SalaryMonth!$B$5:$E$16,2,FALSE) -> 44952 | M80: =VLOOKUP(K80,SalaryMonth!$B$5:$E$16,3,FALSE) -> 44982 | N80: =VLOOKUP(K80,SalaryMonth!$B$5:$E$16,4,FALSE) -> 31 | O80: =IF(L80<C80,"Y","N") -> Y | P80: =IF(OR(D80<>"",M80<D80),"Y","N") -> Y | Q80: 10 | R80: 10 | S80: 0 | T80: 0 | U80: 0 | V80: =ROUND((F80/N80)*Q80,0) -> 5000 | W80: =ROUND((G80/N80)*Q80,0) -> 2000 | X80: =ROUND((H80/N80)*Q80,0) -> 1129 | Y80: =(I80/N80)*Q80 -> 0 | Z80: =ROUND((J80/N80)*Q80,0) -> 1871 | AB80: =ROUND((V80/Q80)*Q80-(V80/Q80)*S80,0) -> 5000 | AC80: =ROUND((W80/Q80)*Q80-(W80/Q80)*S80,0) -> 2000 | AD80: =ROUND((X80/Q80)*Q80-(X80/Q80)*S80,0) -> 1129 | AE80: =Y80 -> 0 | AF80: =ROUND((Z80/Q80)*Q80-(Z80/Q80)*S80,0) -> 1871 | AG80: =SUM(AB80:AF80) -> 10000 | AH80: 0 | AI80: 0 | AJ80: =SUM(AB80:AI80) -> 20000 | AK80: =SUM(V80:Z80)-AG80 -> 0 | AL80: =ROUND(E80*(U80/Q80),0) -> 0 | AM80: =ROUND(E80*(T80/Q80),0) -> 0 | AN80: 0 | AO80: =AE80 -> 0 | AP80: 0 | AQ80: =SUM(F80:J80)-SUM(AK80:AP80) -> 31000 | AR80: =IF( AX80<15001,0,IF(AX80<20001,150,200)) -> 0 | AS80: 0 | AT80: =MIN( ROUND(AB80*12%,0),1800) -> 600 | AU80: =ROUNDUP(IF(E80<=21000,AG80*1.75%,0),0) -> 0 | AV80: =AU80 -> 0 | AW80: =SUM(V80:Z80)+SUM(AH80:AI80) -> 10000 | AX80: =AW80-AP80-SUM(AK80:AM80) -> 10000 | AY80: =SUM(AK80:AP80)+SUM(AR80:AT80)+AV80 -> 600 | AZ80: =AW80-AY80-BB80 -> 9400 | BA80: New employee
A81: =A80+1 -> 78 | B81: B1 | C81: 40183 | E81: 125000 | F81: =E81*50% -> 62500 | G81: =F81*40% -> 25000 | H81: =IF(E81<11750,0,3500) -> 3500 | I81: 2400 | J81: =E81-SUM(F81:I81) -> 31600 | K81: 44958 | L81: =VLOOKUP(K81,SalaryMonth!$B$5:$E$16,2,FALSE) -> 44952 | M81: =VLOOKUP(K81,SalaryMonth!$B$5:$E$16,3,FALSE) -> 44982 | N81: =VLOOKUP(K81,SalaryMonth!$B$5:$E$16,4,FALSE) -> 31 | O81: =IF(L81<C81,"Y","N") -> N | P81: =IF(OR(D81<>"",M81<D81),"Y","N") -> N | Q81: 31 | R81: 31 | S81: 0 | T81: 0 | U81: 0 | V81: =ROUND((F81/N81)*Q81,0) -> 62500 | W81: =ROUND((G81/N81)*Q81,0) -> 25000 | X81: =ROUND((H81/N81)*Q81,0) -> 3500 | Y81: =(I81/N81)*Q81 -> 2400 | Z81: =ROUND((J81/N81)*Q81,0) -> 31600 | AB81: =ROUND((V81/Q81)*Q81-(V81/Q81)*S81,0) -> 62500 | AC81: =ROUND((W81/Q81)*Q81-(W81/Q81)*S81,0) -> 25000 | AD81: =ROUND((X81/Q81)*Q81-(X81/Q81)*S81,0) -> 3500 | AE81: =I81 -> 2400 | AF81: =ROUND((Z81/Q81)*Q81-(Z81/Q81)*S81,0) -> 31600 | AG81: =SUM(AB81:AF81) -> 125000 | AH81: 0 | AI81: 0 | AJ81: =SUM(AB81:AI81) -> 250000 | AK81: =SUM(V81:Z81)-AG81 -> 0 | AL81: =ROUND(E81*(U81/Q81),0) -> 0 | AM81: =ROUND(E81*(T81/Q81),0) -> 0 | AN81: 0 | AO81: =AE81 -> 2400 | AP81: 0 | AQ81: =SUM(F81:J81)-SUM(AK81:AP81) -> 122600 | AR81: =IF( AX81<15001,0,IF(AX81<20001,150,200)) -> 200 | AS81: 0 | AT81: =MIN( ROUND(AB81*12%,0),1800) -> 1800 | AU81: =ROUNDUP(IF(E81<=21000,AG81*1.75%,0),0) -> 0 | AV81: =AU81 -> 0 | AW81: =SUM(V81:Z81)+SUM(AH81:AI81) -> 125000 | AX81: =AW81-AP81-SUM(AK81:AM81) -> 125000 | AY81: =SUM(AK81:AP81)+SUM(AR81:AT81)+AV81 -> 4400 | AZ81: =AW81-AY81-BB81 -> 120600 | BA81: Income tax Added
A82: =A81+1 -> 79 | B82: C1 | C82: 40183 | E82: 1000000 | F82: =E82*50% -> 500000 | G82: =F82*40% -> 200000 | H82: =IF(E82<11750,0,3500) -> 3500 | I82: 2400 | J82: =E82-SUM(F82:I82) -> 294100 | K82: 44958 | L82: =VLOOKUP(K82,SalaryMonth!$B$5:$E$16,2,FALSE) -> 44952 | M82: =VLOOKUP(K82,SalaryMonth!$B$5:$E$16,3,FALSE) -> 44982 | N82: =VLOOKUP(K82,SalaryMonth!$B$5:$E$16,4,FALSE) -> 31 | O82: =IF(L82<C82,"Y","N") -> N | P82: =IF(OR(D82<>"",M82<D82),"Y","N") -> N | Q82: 31 | R82: 31 | S82: 0 | T82: 0 | U82: 0 | V82: =ROUND((F82/N82)*Q82,0) -> 500000 | W82: =ROUND((G82/N82)*Q82,0) -> 200000 | X82: =ROUND((H82/N82)*Q82,0) -> 3500 | Y82: =(I82/N82)*Q82 -> 2400 | Z82: =ROUND((J82/N82)*Q82,0) -> 294100 | AB82: =ROUND((V82/Q82)*Q82-(V82/Q82)*S82,0) -> 500000 | AC82: =ROUND((W82/Q82)*Q82-(W82/Q82)*S82,0) -> 200000 | AD82: =ROUND((X82/Q82)*Q82-(X82/Q82)*S82,0) -> 3500 | AE82: =I82 -> 2400 | AF82: =ROUND((Z82/Q82)*Q82-(Z82/Q82)*S82,0) -> 294100 | AG82: =SUM(AB82:AF82) -> 1000000 | AH82: 0 | AI82: 0 | AJ82: =SUM(AB82:AI82) -> 2000000 | AK82: =SUM(V82:Z82)-AG82 -> 0 | AL82: =ROUND(E82*(U82/Q82),0) -> 0 | AM82: =ROUND(E82*(T82/Q82),0) -> 0 | AN82: 0 | AO82: =AE82 -> 2400 | AP82: 0 | AQ82: =SUM(F82:J82)-SUM(AK82:AP82) -> 997600 | AR82: =IF( AX82<15001,0,IF(AX82<20001,150,200)) -> 200 | AS82: 0 | AT82: =MIN( ROUND(AB82*12%,0),1800) -> 1800 | AU82: =ROUNDUP(IF(E82<=21000,AG82*1.75%,0),0) -> 0 | AV82: =AU82 -> 0 | AW82: =SUM(V82:Z82)+SUM(AH82:AI82) -> 1000000 | AX82: =AW82-AP82-SUM(AK82:AM82) -> 1000000 | AY82: =SUM(AK82:AP82)+SUM(AR82:AT82)+AV82 -> 4400 | AZ82: =AW82-AY82-BB82 -> 584946 | BA82: Income tax Added | BB82: 410654
A83: =A82+1 -> 80 | AK83: =SUM(V83:Z83)-AG83 -> 0 | AZ83: =AW83-AY83-BB83 -> 0
A84: =A83+1 -> 81 | B84: A1 | C84: 40180 | E84: 62000 | F84: =E84*50% -> 31000 | G84: =F84*40% -> 12400 | H84: =IF(E84<11750,0,3500) -> 3500 | I84: 0 | J84: =E84-SUM(F84:I84) -> 15100 | K84: 44986 | L84: =VLOOKUP(K84,SalaryMonth!$B$5:$E$16,2,FALSE) -> 44983 | M84: =VLOOKUP(K84,SalaryMonth!$B$5:$E$16,3,FALSE) -> 45010 | N84: =VLOOKUP(K84,SalaryMonth!$B$5:$E$16,4,FALSE) -> 28 | O84: =IF(L84<=C84,"Y","N") -> N | P84: =IF(OR(D84<>"",M84<D84),"Y","N") -> N | Q84: 28 | R84: 24 | S84: 1 | T84: 1 | U84: 2 | V84: =ROUND((F84/N84)*Q84,0) -> 31000 | W84: =ROUND((G84/N84)*Q84,0) -> 12400 | X84: =ROUND((H84/N84)*Q84,0) -> 3500 | Y84: =(I84/N84)*Q84 -> 0 | Z84: =ROUND((J84/N84)*Q84,0) -> 15100 | AB84: =ROUND((V84/Q84)*Q84-(V84/Q84)*S84,0) -> 29893 | AC84: =ROUND((W84/Q84)*Q84-(W84/Q84)*S84,0) -> 11957 | AD84: =ROUND((X84/Q84)*Q84-(X84/Q84)*S84,0) -> 3375 | AE84: =Y84 -> 0 | AF84: =ROUND((Z84/Q84)*Q84-(Z84/Q84)*S84,0) -> 14561 | AG84: =SUM(AB84:AF84) -> 59786 | AH84: 1000 | AI84: 2000 | AJ84: =SUM(AB84:AI84) -> 122572 | AK84: =SUM(V84:Z84)-AG84 -> 2214 | AL84: =ROUND(E84*(U84/Q84),0) -> 4429 | AM84: =ROUND(E84*(T84/Q84),0) -> 2214 | AN84: 0 | AO84: =AE84 -> 0 | AP84: 2000 | AQ84: =SUM(F84:J84)-SUM(AK84:AP84) -> 51143 | AR84: =IF( AX84<15001,0,IF(AX84<20001,150,200)) -> 200 | AS84: 2000 | AT84: =MIN( ROUND(AB84*12%,0),1800) -> 1800 | AU84: =ROUNDUP(IF(E84<=21000,AG84*1.75%,0),0) -> 0 | AV84: =AU84 -> 0 | AW84: =SUM(V84:Z84)+SUM(AH84:AI84) -> 65000 | AX84: =AW84-AP84-SUM(AK84:AM84) -> 54143 | AY84: =SUM(AK84:AP84)+SUM(AR84:AT84)+AV84 -> 14857 | AZ84: =AW84-AY84-BB84 -> 50143 | BA84: Paycut added 2000/Arears And Incentives Added /Lop/UA/LC/income tax added
A85: =A84+1 -> 82 | B85: A2 | C85: 40180 | E85: 48000 | F85: =E85*50% -> 24000 | G85: =F85*40% -> 9600 | H85: =IF(E85<11750,0,3500) -> 3500 | I85: 0 | J85: =E85-SUM(F85:I85) -> 10900 | K85: 44986 | L85: =VLOOKUP(K85,SalaryMonth!$B$5:$E$16,2,FALSE) -> 44983 | M85: =VLOOKUP(K85,SalaryMonth!$B$5:$E$16,3,FALSE) -> 45010 | N85: =VLOOKUP(K85,SalaryMonth!$B$5:$E$16,4,FALSE) -> 28 | O85: =IF(L85<C85,"Y","N") -> N | P85: =IF(OR(D85<>"",M85<D85),"Y","N") -> N | Q85: 28 | R85: 23 | S85: 1 | T85: 1 | U85: 3 | V85: =ROUND((F85/N85)*Q85,0) -> 24000 | W85: =ROUND((G85/N85)*Q85,0) -> 9600 | X85: =ROUND((H85/N85)*Q85,0) -> 3500 | Y85: =(I85/N85)*Q85 -> 0 | Z85: =ROUND((J85/N85)*Q85,0) -> 10900 | AB85: =ROUND((V85/Q85)*Q85-(V85/Q85)*S85,0) -> 23143 | AC85: =ROUND((W85/Q85)*Q85-(W85/Q85)*S85,0) -> 9257 | AD85: =ROUND((X85/Q85)*Q85-(X85/Q85)*S85,0) -> 3375 | AE85: =Y85 -> 0 | AF85: =ROUND((Z85/Q85)*Q85-(Z85/Q85)*S85,0) -> 10511 | AG85: =SUM(AB85:AF85) -> 46286 | AH85: 0 | AI85: 0 | AJ85: =SUM(AB85:AI85) -> 92572 | AK85: =SUM(V85:Z85)-AG85 -> 1714 | AL85: =ROUND(E85*(U85/Q85),0) -> 5143 | AM85: =ROUND(E85*(T85/Q85),0) -> 1714 | AN85: 0 | AO85: =AE85 -> 0 | AP85: 0 | AQ85: =SUM(F85:J85)-SUM(AK85:AP85) -> 39429 | AR85: =IF( AX85<15001,0,IF(AX85<20001,150,200)) -> 200 | AS85: 0 | AT85: =MIN( ROUND(AB85*12%,0),1800) -> 1800 | AU85: =ROUNDUP(IF(E85<=21000,AG85*1.75%,0),0) -> 0 | AV85: =ROUNDUP(AG85 *1.75%,0) -> 811 | AW85: =SUM(V85:Z85)+SUM(AH85:AI85) -> 48000 | AX85: =AW85-AP85-SUM(AK85:AM85) -> 39429 | AY85: =SUM(AK85:AP85)+SUM(AR85:AT85)+AV85 -> 11382 | AZ85: =AW85-AY85-BB85 -> 36618 | BA85: ESI IS Deducted Because Employe Have An ESI Deduction in last Month/Lop/UA/LC
A86: =A85+1 -> 83 | B86: A3 | C86: 40181 | E86: 11000 | F86: =E86*50% -> 5500 | G86: =F86*40% -> 2200 | H86: =IF(E86<11750,0,3500) -> 0 | I86: 0 | J86: =E86-SUM(F86:I86) -> 3300 | K86: 44986 | L86: =VLOOKUP(K86,SalaryMonth!$B$5:$E$16,2,FALSE) -> 44983 | M86: =VLOOKUP(K86,SalaryMonth!$B$5:$E$16,3,FALSE) -> 45010 | N86: =VLOOKUP(K86,SalaryMonth!$B$5:$E$16,4,FALSE) -> 28 | O86: =IF(L86<C86,"Y","N") -> N | P86: =IF(OR(D86<>"",M86<D86),"Y","N") -> N | Q86: 28 | R86: 22 | S86: 1 | T86: 1 | U86: 4 | V86: =ROUND((F86/N86)*Q86,0) -> 5500 | W86: =ROUND((G86/N86)*Q86,0) -> 2200 | X86: =ROUND((H86/N86)*Q86,0) -> 0 | Y86: =(I86/N86)*Q86 -> 0 | Z86: =ROUND((J86/N86)*Q86,0) -> 3300 | AB86: =ROUND((V86/Q86)*Q86-(V86/Q86)*S86,0) -> 5304 | AC86: =ROUND((W86/Q86)*Q86-(W86/Q86)*S86,0) -> 2121 | AD86: =ROUND((X86/Q86)*Q86-(X86/Q86)*S86,0) -> 0 | AE86: =Y86 -> 0 | AF86: =ROUND((Z86/Q86)*Q86-(Z86/Q86)*S86,0) -> 3182 | AG86: =SUM(AB86:AF86) -> 10607 | AH86: 0 | AI86: 0 | AJ86: =SUM(AB86:AI86) -> 21214 | AK86: =SUM(V86:Z86)-AG86 -> 393 | AL86: =ROUND(E86*(U86/Q86),0) -> 1571 | AM86: =ROUND(E86*(T86/Q86),0) -> 393 | AN86: 0 | AO86: =AE86 -> 0 | AP86: 0 | AQ86: =SUM(F86:J86)-SUM(AK86:AP86) -> 8643 | AR86: =IF( AX86<15001,0,IF(AX86<20001,150,200)) -> 0 | AS86: 0 | AT86: =MIN( ROUND(AB86*12%,0),1800) -> 636 | AU86: =ROUNDUP(IF(E86<=21000,AG86*1.75%,0),0) -> 186 | AV86: =AU86 -> 186 | AW86: =SUM(V86:Z86)+SUM(AH86:AI86) -> 11000 | AX86: =AW86-AP86-SUM(AK86:AM86) -> 8643 | AY86: =SUM(AK86:AP86)+SUM(AR86:AT86)+AV86 -> 3179 | AZ86: =AW86-AY86-BB86 -> 7821 | BA86: ESI is deducted because employee salary is under ESI slab/Lop/UA/LC
A87: =A86+1 -> 84 | B87: A4 | C87: 40182 | E87: 25000 | F87: =E87*50% -> 12500 | G87: =F87*40% -> 5000 | H87: =IF(E87<11750,0,3500) -> 3500 | I87: 0 | J87: =E87-SUM(F87:I87) -> 4000 | K87: 44986 | L87: =VLOOKUP(K87,SalaryMonth!$B$5:$E$16,2,FALSE) -> 44983 | M87: =VLOOKUP(K87,SalaryMonth!$B$5:$E$16,3,FALSE) -> 45010 | N87: =VLOOKUP(K87,SalaryMonth!$B$5:$E$16,4,FALSE) -> 28 | O87: =IF(L87<C87,"Y","N") -> N | P87: =IF(OR(D87<>"",M87<D87),"Y","N") -> N | Q87: 28 | R87: 21 | S87: 1 | T87: 1 | U87: 5 | V87: =ROUND((F87/N87)*Q87,0) -> 12500 | W87: =ROUND((G87/N87)*Q87,0) -> 5000 | X87: =ROUND((H87/N87)*Q87,0) -> 3500 | Y87: =(I87/N87)*Q87 -> 0 | Z87: =ROUND((J87/N87)*Q87,0) -> 4000 | AB87: =ROUND((V87/Q87)*Q87-(V87/Q87)*S87,0) -> 12054 | AC87: =ROUND((W87/Q87)*Q87-(W87/Q87)*S87,0) -> 4821 | AD87: =ROUND((X87/Q87)*Q87-(X87/Q87)*S87,0) -> 3375 | AE87: =Y87 -> 0 | AF87: =ROUND((Z87/Q87)*Q87-(Z87/Q87)*S87,0) -> 3857 | AG87: =SUM(AB87:AF87) -> 24107 | AH87: 0 | AI87: 0 | AJ87: =SUM(AB87:AI87) -> 48214 | AK87: =SUM(V87:Z87)-AG87 -> 893 | AL87: =ROUND(E87*(U87/Q87),0) -> 4464 | AM87: =ROUND(E87*(T87/Q87),0) -> 893 | AN87: 0 | AO87: =AE87 -> 0 | AP87: 1500 | AQ87: =SUM(F87:J87)-SUM(AK87:AP87) -> 17250 | AR87: =IF( AX87<15001,0,IF(AX87<20001,150,200)) -> 150 | AS87: 0 | AT87: =MIN( ROUND(AB87*12%,0),1800) -> 1446 | AU87: =ROUNDUP(IF(E87<=21000,AG87*1.75%,0),0) -> 0 | AV87: =AU87 -> 0 | AW87: =SUM(V87:Z87)+SUM(AH87:AI87) -> 25000 | AX87: =AW87-AP87-SUM(AK87:AM87) -> 17250 | AY87: =SUM(AK87:AP87)+SUM(AR87:AT87)+AV87 -> 9346 | AZ87: =AW87-AY87-BB87 -> 15654 | BA87: Paycut Added.Lop/UA/LC
A88: =A87+1 -> 85 | B88: A6 | C88: 44973 | E88: 32000 | F88: =E88*50% -> 16000 | G88: =F88*40% -> 6400 | H88: =IF(E88<11750,0,3500) -> 3500 | I88: 0 | J88: =E88-SUM(F88:I88) -> 6100 | K88: 44986 | L88: =VLOOKUP(K88,SalaryMonth!$B$5:$E$16,2,FALSE) -> 44983 | M88: =VLOOKUP(K88,SalaryMonth!$B$5:$E$16,3,FALSE) -> 45010 | N88: =VLOOKUP(K88,SalaryMonth!$B$5:$E$16,4,FALSE) -> 28 | O88: =IF(L88<C88,"Y","N") -> N | P88: =IF(OR(D88<>"",M88<D88),"Y","N") -> N | Q88: 28 | R88: 20 | S88: 1 | T88: 1 | U88: 6 | V88: =ROUND((F88/N88)*Q88,0) -> 16000 | W88: =ROUND((G88/N88)*Q88,0) -> 6400 | X88: =ROUND((H88/N88)*Q88,0) -> 3500 | Y88: =(I88/N88)*Q88 -> 0 | Z88: =ROUND((J88/N88)*Q88,0) -> 6100 | AB88: =ROUND((V88/Q88)*Q88-(V88/Q88)*S88,0) -> 15429 | AC88: =ROUND((W88/Q88)*Q88-(W88/Q88)*S88,0) -> 6171 | AD88: =ROUND((X88/Q88)*Q88-(X88/Q88)*S88,0) -> 3375 | AE88: =Y88 -> 0 | AF88: =ROUND((Z88/Q88)*Q88-(Z88/Q88)*S88,0) -> 5882 | AG88: =SUM(AB88:AF88) -> 30857 | AH88: 0 | AI88: 2000 | AJ88: =SUM(AB88:AI88) -> 63714 | AK88: =SUM(V88:Z88)-AG88 -> 1143 | AL88: =ROUND(E88*(U88/Q88),0) -> 6857 | AM88: =ROUND(E88*(T88/Q88),0) -> 1143 | AN88: 0 | AO88: =AE88 -> 0 | AP88: 0 | AQ88: =SUM(F88:J88)-SUM(AK88:AP88) -> 22857 | AR88: =IF( AX88<15001,0,IF(AX88<20001,150,200)) -> 200 | AS88: 0 | AT88: =MIN( ROUND(AB88*12%,0),1800) -> 1800 | AU88: =ROUNDUP(IF(E88<=21000,AG88*1.75%,0),0) -> 0 | AV88: =AU88 -> 0 | AW88: =SUM(V88:Z88)+SUM(AH88:AI88) -> 34000 | AX88: =AW88-AP88-SUM(AK88:AM88) -> 24857 | AY88: =SUM(AK88:AP88)+SUM(AR88:AT88)+AV88 -> 11143 | AZ88: =AW88-AY88-BB88 -> 22857 | BA88: Incentives Added./Lop/UA/LC
A89: =A88+1 -> 86 | B89: B1 | C89: 40183 | E89: 125000 | F89: =E89*50% -> 62500 | G89: =F89*40% -> 25000 | H89: =IF(E89<11750,0,3500) -> 3500 | I89: 2400 | J89: =E89-SUM(F89:I89) -> 31600 | K89: 44986 | L89: =VLOOKUP(K89,SalaryMonth!$B$5:$E$16,2,FALSE) -> 44983 | M89: =VLOOKUP(K89,SalaryMonth!$B$5:$E$16,3,FALSE) -> 45010 | N89: =VLOOKUP(K89,SalaryMonth!$B$5:$E$16,4,FALSE) -> 28 | O89: =IF(L89<C89,"Y","N") -> N | P89: =IF(OR(D89<>"",M89<D89),"Y","N") -> N | Q89: 28 | R89: 28 | S89: 0 | T89: 0 | U89: 0 | V89: =ROUND((F89/N89)*Q89,0) -> 62500 | W89: =ROUND((G89/N89)*Q89,0) -> 25000 | X89: =ROUND((H89/N89)*Q89,0) -> 3500 | Y89: =(I89/N89)*Q89 -> 2400 | Z89: =ROUND((J89/N89)*Q89,0) -> 31600 | AB89: =ROUND((V89/Q89)*Q89-(V89/Q89)*S89,0) -> 62500 | AC89: =ROUND((W89/Q89)*Q89-(W89/Q89)*S89,0) -> 25000 | AD89: =ROUND((X89/Q89)*Q89-(X89/Q89)*S89,0) -> 3500 | AE89: =I89 -> 2400 | AF89: =ROUND((Z89/Q89)*Q89-(Z89/Q89)*S89,0) -> 31600 | AG89: =SUM(AB89:AF89) -> 125000 | AH89: 0 | AI89: 0 | AJ89: =SUM(AB89:AI89) -> 250000 | AK89: =SUM(V89:Z89)-AG89 -> 0 | AL89: =ROUND(E89*(U89/Q89),0) -> 0 | AM89: =ROUND(E89*(T89/Q89),0) -> 0 | AN89: 0 | AO89: =AE89 -> 2400 | AP89: 0 | AQ89: =SUM(F89:J89)-SUM(AK89:AP89) -> 122600 | AR89: =IF( AX89<15001,0,IF(AX89<20001,150,200)) -> 200 | AS89: 0 | AT89: =MIN( ROUND(AB89*12%,0),1800) -> 1800 | AU89: =ROUNDUP(IF(E89<=21000,AG89*1.75%,0),0) -> 0 | AV89: =AU89 -> 0 | AW89: =SUM(V89:Z89)+SUM(AH89:AI89) -> 125000 | AX89: =AW89-AP89-SUM(AK89:AM89) -> 125000 | AY89: =SUM(AK89:AP89)+SUM(AR89:AT89)+AV89 -> 4400 | AZ89: =AW89-AY89-BB89 -> 120600 | BA89: Income tax Added
A90: =A89+1 -> 87 | B90: C1 | C90: 40183 | E90: 1000000 | F90: =E90*50% -> 500000 | G90: =F90*40% -> 200000 | H90: =IF(E90<11750,0,3500) -> 3500 | I90: 2400 | J90: =E90-SUM(F90:I90) -> 294100 | K90: 44986 | L90: =VLOOKUP(K90,SalaryMonth!$B$5:$E$16,2,FALSE) -> 44983 | M90: =VLOOKUP(K90,SalaryMonth!$B$5:$E$16,3,FALSE) -> 45010 | N90: =VLOOKUP(K90,SalaryMonth!$B$5:$E$16,4,FALSE) -> 28 | O90: =IF(L90<C90,"Y","N") -> N | P90: =IF(OR(D90<>"",M90<D90),"Y","N") -> N | Q90: 28 | R90: 28 | S90: 0 | T90: 0 | U90: 0 | V90: =ROUND((F90/N90)*Q90,0) -> 500000 | W90: =ROUND((G90/N90)*Q90,0) -> 200000 | X90: =ROUND((H90/N90)*Q90,0) -> 3500 | Y90: =(I90/N90)*Q90 -> 2400 | Z90: =ROUND((J90/N90)*Q90,0) -> 294100 | AB90: =ROUND((V90/Q90)*Q90-(V90/Q90)*S90,0) -> 500000 | AC90: =ROUND((W90/Q90)*Q90-(W90/Q90)*S90,0) -> 200000 | AD90: =ROUND((X90/Q90)*Q90-(X90/Q90)*S90,0) -> 3500 | AE90: =I90 -> 2400 | AF90: =ROUND((Z90/Q90)*Q90-(Z90/Q90)*S90,0) -> 294100 | AG90: =SUM(AB90:AF90) -> 1000000 | AH90: 0 | AI90: 0 | AJ90: =SUM(AB90:AI90) -> 2000000 | AK90: =SUM(V90:Z90)-AG90 -> 0 | AL90: =ROUND(E90*(U90/Q90),0) -> 0 | AM90: =ROUND(E90*(T90/Q90),0) -> 0 | AN90: 0 | AO90: =AE90 -> 2400 | AP90: 0 | AQ90: =SUM(F90:J90)-SUM(AK90:AP90) -> 997600 | AR90: =IF( AX90<15001,0,IF(AX90<20001,150,200)) -> 200 | AS90: 0 | AT90: =MIN( ROUND(AB90*12%,0),1800) -> 1800 | AU90: =ROUNDUP(IF(E90<=21000,AG90*1.75%,0),0) -> 0 | AV90: =AU90 -> 0 | AW90: =SUM(V90:Z90)+SUM(AH90:AI90) -> 1000000 | AX90: =AW90-AP90-SUM(AK90:AM90) -> 1000000 | AY90: =SUM(AK90:AP90)+SUM(AR90:AT90)+AV90 -> 4400 | AZ90: =AW90-AY90-BB90 -> 995600 | BA90: Employee Joined in last month with tax bracket
A91: =A90+1 -> 88 | B91: C2 | C91: 40183 | E91: 2000000 | F91: =E91*50% -> 1000000 | G91: =F91*40% -> 400000 | H91: =IF(E91<11750,0,3500) -> 3500 | I91: 2400 | J91: =E91-SUM(F91:I91) -> 594100 | K91: 44986 | L91: =VLOOKUP(K91,SalaryMonth!$B$5:$E$16,2,FALSE) -> 44983 | M91: =VLOOKUP(K91,SalaryMonth!$B$5:$E$16,3,FALSE) -> 45010 | N91: =VLOOKUP(K91,SalaryMonth!$B$5:$E$16,4,FALSE) -> 28 | O91: =IF(L91<C91,"Y","N") -> N | P91: =IF(OR(D91<>"",M91<D91),"Y","N") -> N | Q91: 28 | R91: 28 | S91: 0 | T91: 0 | U91: 0 | V91: =ROUND((F91/N91)*Q91,0) -> 1000000 | W91: =ROUND((G91/N91)*Q91,0) -> 400000 | X91: =ROUND((H91/N91)*Q91,0) -> 3500 | Y91: =(I91/N91)*Q91 -> 2400 | Z91: =ROUND((J91/N91)*Q91,0) -> 594100 | AB91: =ROUND((V91/Q91)*Q91-(V91/Q91)*S91,0) -> 1000000 | AC91: =ROUND((W91/Q91)*Q91-(W91/Q91)*S91,0) -> 400000 | AD91: =ROUND((X91/Q91)*Q91-(X91/Q91)*S91,0) -> 3500 | AE91: =I91 -> 2400 | AF91: =ROUND((Z91/Q91)*Q91-(Z91/Q91)*S91,0) -> 594100 | AG91: =SUM(AB91:AF91) -> 2000000 | AH91: 0 | AI91: 0 | AJ91: =SUM(AB91:AI91) -> 4000000 | AK91: =SUM(V91:Z91)-AG91 -> 0 | AL91: =ROUND(E91*(U91/Q91),0) -> 0 | AM91: =ROUND(E91*(T91/Q91),0) -> 0 | AN91: 0 | AO91: =AE91 -> 2400 | AP91: 0 | AQ91: =SUM(F91:J91)-SUM(AK91:AP91) -> 1997600 | AR91: =IF( AX91<15001,0,IF(AX91<20001,150,200)) -> 200 | AS91: 0 | AT91: =MIN( ROUND(AB91*12%,0),1800) -> 1800 | AU91: =ROUNDUP(IF(E91<=21000,AG91*1.75%,0),0) -> 0 | AV91: =AU91 -> 0 | AW91: =SUM(V91:Z91)+SUM(AH91:AI91) -> 2000000 | AX91: =AW91-AP91-SUM(AK91:AM91) -> 2000000 | AY91: =SUM(AK91:AP91)+SUM(AR91:AT91)+AV91 -> 4400 | AZ91: =AW91-AY91-BB91 -> 1583573 | BA91: Employee Joined in last month with tax bracket | BB91: 412027

Sheet SalaryValues
A1: S.No | B1: Employee Code | C1: DOJ | D1: DOR | E1: Salary | F1: Basic | G1: HRA | H1: Medical & Transport Allowance | I1: Food Coupons | J1: Special Allowance | K1: Month | L1: Month Start | M1: Month End | N1: Month Days | O1: Is New Employee | P1: Is Left Employee | Q1: Employee Working days | R1: Days present | S1: LOP Days | T1: Late Coming days | U1: Unauthorized leaves | V1: Basic | W1: HRA | X1: Medical & Transport Allowance | Y1: Food Coupons | Z1: Special Allowance | AB1: Basic | AC1: HRA | AD1: Medical & Transport Allowance | AE1: Food Coupons | AF1: Special Allowance | AG1: Salary Earned (For ESI) | AH1: Arrears | AI1: Incentives | AJ1: Gross Earnings Total | AK1: LOP Amount | AL1: UA Amount | AM1: LC Amount | AN1: Staff Salary Advances | AO1: Food Coupons | AP1: Paycut | AQ1: Net Salary Earned | AR1: PT | AS1: Income Tax | AT1: PF Employee Contribution | AU1: ESI Employee Contribution | AV1: ESI Final | AW1: Gross Earnings | AX1: Gross Earnings For Tax | AY1: Gross Deduction | AZ1: Net Take Home | BA1: Comments
A2: 1 | B2: A1 | C2: 40180 | E2: 62000 | F2: 31000 | G2: 12400 | H2: 3500 | I2: 0 | J2: 15100 | K2: 44652 | L2: 44646 | M2: 44676 | N2: 31 | O2: N | P2: N | Q2: 31 | R2: 28 | S2: 1 | T2: 1 | U2: 1 | V2: 31000 | W2: 12400 | X2: 3500 | Y2: 0 | Z2: 15100 | AB2: 30000 | AC2: 12000 | AD2: 3387 | AE2: 0 | AF2: 14613 | AG2: 60000 | AH2: 1000 | AI2: 1000 | AJ2: 122000 | AK2: 2000 | AL2: 2000 | AM2: 2000 | AN2: 8333 | AO2: 0 | AP2: 200 | AQ2: 47467 | AR2: 200 | AS2: 500 | AT2: 1800 | AU2: 0 | AV2: 0 | AW2: 64000 | AX2: 57800 | AY2: 17033 | AZ2: 46967 | BA2: Arrears Incentives Added /Advance Deducted 8333/LATE Coming /UnAuthorized/incometax
A3: 2 | B3: A2 | C3: 40180 | E3: 22000 | F3: 11000 | G3: 4400 | H3: 3500 | I3: 0 | J3: 3100 | K3: 44652 | L3: 44646 | M3: 44676 | N3: 31 | O3: N | P3: N | Q3: 31 | R3: 29 | S3: 0 | T3: 0 | U3: 0 | V3: 11000 | W3: 4400 | X3: 3500 | Y3: 0 | Z3: 3100 | AB3: 11000 | AC3: 4400 | AD3: 3500 | AE3: 0 | AF3: 3100 | AG3: 22000 | AH3: 0 | AI3: 0 | AJ3: 44000 | AK3: 0 | AL3: 0 | AM3: 0 | AN3: 0 | AO3: 0 | AP3: 0 | AQ3: 22000 | AR3: 200 | AS3: 0 | AT3: 1320 | AU3: 0 | AV3: 0 | AW3: 22000 | AX3: 22000 | AY3: 1520 | AZ3: 20480 | BA3: ESI is not deducted because Employee salary is Not under ESI slab
A4: 3 | B4: A3 | C4: 40181 | E4: 11000 | F4: 5500 | G4: 2200 | H4: 0 | I4: 0 | J4: 3300 | K4: 44652 | L4: 44646 | M4: 44676 | N4: 31 | O4: N | P4: N | Q4: 31 | R4: 29 | S4: 0 | T4: 0 | U4: 0 | V4: 5500 | W4: 2200 | X4: 0 | Y4: 0 | Z4: 3300 | AB4: 5500 | AC4: 2200 | AD4: 0 | AE4: 0 | AF4: 3300 | AG4: 11000 | AH4: 0 | AI4: 0 | AJ4: 22000 | AK4: 0 | AL4: 0 | AM4: 0 | AN4: 0 | AO4: 0 | AP4: 0 | AQ4: 11000 | AR4: 0 | AS4: 0 | AT4: 660 | AU4: 193 | AV4: 193 | AW4: 11000 | AX4: 11000 | AY4: 853 | AZ4: 10147 | BA4: ESI is deducted because employee salary is under ESI slab
A5: 4 | B5: A4 | C5: 40182 | E5: 25000 | F5: 12500 | G5: 5000 | H5: 3500 | I5: 0 | J5: 4000 | K5: 44652 | L5: 44646 | M5: 44676 | N5: 31 | O5: N | P5: N | Q5: 31 | R5: 29 | S5: 0 | T5: 0 | U5: 0 | V5: 12500 | W5: 5000 | X5: 3500 | Y5: 0 | Z5: 4000 | AB5: 12500 | AC5: 5000 | AD5: 3500 | AE5: 0 | AF5: 4000 | AG5: 25000 | AH5: 0 | AI5: 0 | AJ5: 50000 | AK5: 0 | AL5: 0 | AM5: 0 | AN5: 0 | AO5: 0 | AP5: 0 | AQ5: 25000 | AR5: 200 | AS5: 0 | AT5: 1500 | AU5: 0 | AV5: 0 | AW5: 25000 | AX5: 25000 | AY5: 1700 | AZ5: 23300
A6: 5 | B6: A5 | C6: 40183 | E6: 45000 | F6: 22500 | G6: 9000 | H6: 3500 | I6: 2400 | J6: 7600 | K6: 44652 | L6: 44646 | M6: 44676 | N6: 31 | O6: N | P6: N | Q6: 31 | R6: 29 | S6: 0 | T6: 0 | U6: 0 | V6: 22500 | W6: 9000 | X6: 3500 | Y6: 2400 | Z6: 7600 | AB6: 22500 | AC6: 9000 | AD6: 3500 | AE6: 2400 | AF6: 7600 | AG6: 45000 | AH6: 0 | AI6: 0 | AJ6: 90000 | AK6: 0 | AL6: 0 | AM6: 0 | AN6: 0 | AO6: 2400 | AP6: 0 | AQ6: 42600 | AR6: 200 | AS6: 2000 | AT6: 1800 | AU6: 0 | AV6: 0 | AW6: 45000 | AX6: 45000 | AY6: 6400 | AZ6: 38600 | BA6: Income tax Added
A7: 6 | AK7: 0
A8: 7 | B8: A1 | C8: 40180 | E8: 62000 | F8: 31000 | G8: 12400 | H8: 3500 | I8: 0 | J8: 15100 | K8: 44682 | L8: 44677 | M8: 44706 | N8: 30 | O8: N | P8: N | Q8: 30 | R8: 29 | S8: 1 | T8: 0 | U8: 0 | V8: 31000 | W8: 12400 | X8: 3500 | Y8: 0 | Z8: 15100 | AB8: 29967 | AC8: 11987 | AD8: 3383 | AE8: 0 | AF8: 14597 | AG8: 59934 | AH8: 0 | AI8: 1000 | AJ8: 120868 | AK8: 2066 | AL8: 0 | AM8: 0 | AN8: 8333 | AO8: 0 | AP8: 0 | AQ8: 51601 | AR8: 200 | AS8: 0 | AT8: 1800 | AU8: 0 | AV8: 0 | AW8: 63000 | AX8: 60934 | AY8: 12399 | AZ8: 50601 | BA8: incentives Added 1000rs/Advance Deducted 8333
A9: 8 | B9: A2 | C9: 40180 | E9: 21000 | F9: 10500 | G9: 4200 | H9: 3500 | I9: 0 | J9: 2800 | K9: 44682 | L9: 44677 | M9: 44706 | N9: 30 | O9: N | P9: N | Q9: 30 | R9: 29 | S9: 0 | T9: 0 | U9: 0 | V9: 10500 | W9: 4200 | X9: 3500 | Y9: 0 | Z9: 2800 | AB9: 10500 | AC9: 4200 | AD9: 3500 | AE9: 0 | AF9: 2800 | AG9: 21000 | AH9: 0 | AI9: 0 | AJ9: 42000 | AK9: 0 | AL9: 0 | AM9: 0 | AN9: 0 | AO9: 0 | AP9: 0 | AQ9: 21000 | AR9: 200 | AS9: 0 | AT9: 1260 | AU9: 368 | AV9: 368 | AW9: 21000 | AX9: 21000 | AY9: 1828 | AZ9: 19172 | BA9: ESI is deducted because employee salary is under ESI slab
A10: 9 | B10: A3 | C10: 40181 | E10: 11000 | F10: 5500 | G10: 2200 | H10: 0 | I10: 0 | J10: 3300 | K10: 44682 | L10: 44677 | M10: 44706 | N10: 30 | O10: N | P10: N | Q10: 30 | R10: 29 | S10: 0 | T10: 0 | U10: 0 | V10: 5500 | W10: 2200 | X10: 0 | Y10: 0 | Z10: 3300 | AB10: 5500 | AC10: 2200 | AD10: 0 | AE10: 0 | AF10: 3300 | AG10: 11000 | AH10: 0 | AI10: 0 | AJ10: 22000 | AK10: 0 | AL10: 0 | AM10: 0 | AN10: 0 | AO10: 0 | AP10: 0 | AQ10: 11000 | AR10: 0 | AS10: 0 | AT10: 660 | AU10: 193 | AV10: 193 | AW10: 11000 | AX10: 11000 | AY10: 853 | AZ10: 10147 | BA10: ESI is deducted because employee salary is under ESI slab
A11: 10 | B11: A4 | C11: 40182 | E11: 25000 | F11: 12500 | G11: 5000 | H11: 3500 | I11: 0 | J11: 4000 | K11: 44682 | L11: 44677 | M11: 44706 | N11: 30 | O11: N | P11: N | Q11: 30 | R11: 29 | S11: 0 | T11: 0 | U11: 0 | V11: 12500 | W11: 5000 | X11: 3500 | Y11: 0 | Z11: 4000 | AB11: 12500 | AC11: 5000 | AD11: 3500 | AE11: 0 | AF11: 4000 | AG11: 25000 | AH11: 0 | AI11: 0 | AJ11: 50000 | AK11: 0 | AL11: 0 | AM11: 0 | AN11: 0 | AO11: 0 | AP11: 0 | AQ11: 25000 | AR11: 200 | AS11: 0 | AT11: 1500 | AU11: 0 | AV11: 0 | AW11: 25000 | AX11: 25000 | AY11: 1700 | AZ11: 23300
A12: 11 | B12: A5 | C12: 40183 | E12: 50000 | F12: 25000 | G12: 10000 | H12: 3500 | I12: 2400 | J12: 9100 | K12: 44682 | L12: 44677 | M12: 44706 | N12: 30 | O12: N | P12: N | Q12: 30 | R12: 29 | S12: 0 | T12: 0 | U12: 0 | V12: 25000 | W12: 10000 | X12: 3500 | Y12: 2400 | Z12: 9100 | AB12: 25000 | AC12: 10000 | AD12: 3500 | AE12: 2400 | AF12: 9100 | AG12: 50000 | AH12: 2000 | AI12: 0 | AJ12: 102000 | AK12: 0 | AL12: 0 | AM12: 0 | AN12: 0 | AO12: 2400 | AP12: 0 | AQ12: 47600 | AR12: 200 | AS12: 2000 | AT12: 1800 | AU12: 0 | AV12: 0 | AW12: 52000 | AX12: 52000 | AY12: 6400 | AZ12: 45600 | BA12: Income tax Added/Arrears Added
A13: 12 | AK13: 0
A14: 13 | B14: A1 | C14: 40180 | E14: 62000 | F14: 31000 | G14: 12400 | H14: 3500 | I14: 0 | J14: 15100 | K14: 44713 | L14: 44707 | M14: 44737 | N14: 31 | O14: N | P14: N | Q14: 31 | R14: 29 | S14: 1 | T14: 0 | U14: 0 | V14: 31000 | W14: 12400 | X14: 3500 | Y14: 0 | Z14: 15100 | AB14: 30000 | AC14: 12000 | AD14: 3387 | AE14: 0 | AF14: 14613 | AG14: 60000 | AH14: 0 | AI14: 0 | AJ14: 120000 | AK14: 2000 | AL14: 0 | AM14: 0 | AN14: 8333 | AO14: 0 | AP14: 0 | AQ14: 51667 | AR14: 200 | AS14: 0 | AT14: 1800 | AU14: 0 | AV14: 0 | AW14: 62000 | AX14: 60000 | AY14: 12333 | AZ14: 49667 | BA14: /Advance Deducted 8333
A15: 14 | B15: A2 | C15: 40180 | E15: 24000 | F15: 12000 | G15: 4800 | H15: 3500 | I15: 0 | J15: 3700 | K15: 44713 | L15: 44707 | M15: 44737 | N15: 31 | O15: N | P15: N | Q15: 31 | R15: 29 | S15: 0 | T15: 0 | U15: 0 | V15: 12000 | W15: 4800 | X15: 3500 | Y15: 0 | Z15: 3700 | AB15: 12000 | AC15: 4800 | AD15: 3500 | AE15: 0 | AF15: 3700 | AG15: 24000 | AH15: 0 | AI15: 0 | AJ15: 48000 | AK15: 0 | AL15: 0 | AM15: 0 | AN15: 0 | AO15: 0 | AP15: 0 | AQ15: 24000 | AR15: 200 | AS15: 0 | AT15: 1440 | AU15: 0 | AV15: 420 | AW15: 24000 | AX15: 24000 | AY15: 2060 | AZ15: 21940 | BA15: ESI should be deducted because ESI is deducted in May month it will continue up to sep irrespective of salary
A16: 15 | B16: A3 | C16: 40181 | E16: 11000 | F16: 5500 | G16: 2200 | H16: 0 | I16: 0 | J16: 3300 | K16: 44713 | L16: 44707 | M16: 44737 | N16: 31 | O16: N | P16: N | Q16: 31 | R16: 29 | S16: 0 | T16: 0 | U16: 0 | V16: 5500 | W16: 2200 | X16: 0 | Y16: 0 | Z16: 3300 | AB16: 5500 | AC16: 2200 | AD16: 0 | AE16: 0 | AF16: 3300 | AG16: 11000 | AH16: 0 | AI16: 0 | AJ16: 22000 | AK16: 0 | AL16: 0 | AM16: 0 | AN16: 0 | AO16: 0 | AP16: 0 | AQ16: 11000 | AR16: 0 | AS16: 0 | AT16: 660 | AU16: 193 | AV16: 193 | AW16: 11000 | AX16: 11000 | AY16: 853 | AZ16: 10147 | BA16: ESI is deducted because employee salary is under ESI slab
A17: 16 | B17: A4 | C17: 40182 | E17: 25000 | F17: 12500 | G17: 5000 | H17: 3500 | I17: 0 | J17: 4000 | K17: 44713 | L17: 44707 | M17: 44737 | N17: 31 | O17: N | P17: N | Q17: 31 | R17: 29 | S17: 0 | T17: 0 | U17: 0 | V17: 12500 | W17: 5000 | X17: 3500 | Y17: 0 | Z17: 4000 | AB17: 12500 | AC17: 5000 | AD17: 3500 | AE17: 0 | AF17: 4000 | AG17: 25000 | AH17: 0 | AI17: 0 | AJ17: 50000 | AK17: 0 | AL17: 0 | AM17: 0 | AN17: 0 | AO17: 0 | AP17: 0 | AQ17: 25000 | AR17: 200 | AS17: 0 | AT17: 1500 | AU17: 0 | AV17: 0 | AW17: 25000 | AX17: 25000 | AY17: 1700 | AZ17: 23300
A18: 17 | B18: A5 | C18: 40183 | E18: 32000 | F18: 16000 | G18: 6400 | H18: 3500 | I18: 0 | J18: 6100 | K18: 44713 | L18: 44707 | M18: 44737 | N18: 31 | O18: N | P18: N | Q18: 31 | R18: 29 | S18: 0 | T18: 0 | U18: 0 | V18: 16000 | W18: 6400 | X18: 3500 | Y18: 0 | Z18: 6100 | AB18: 16000 | AC18: 6400 | AD18: 3500 | AE18: 0 | AF18: 6100 | AG18: 32000 | AH18: 0 | AI18: 0 | AJ18: 64000 | AK18: 0 | AL18: 0 | AM18: 0 | AN18: 0 | AO18: 0 | AP18: 0 | AQ18: 32000 | AR18: 200 | AS18: 0 | AT18: 1800 | AU18: 0 | AV18: 0 | AW18: 32000 | AX18: 32000 | AY18: 2000 | AZ18: 30000
A19: 18 | AK19: 0
A20: 19 | B20: A1 | C20: 40180 | E20: 62000 | F20: 31000 | G20: 12400 | H20: 3500 | I20: 0 | J20: 15100 | K20: 44743 | L20: 44738 | M20: 44767 | N20: 30 | O20: N | P20: N | Q20: 30 | R20: 29 | S20: 1 | T20: 0 | U20: 0 | V20: 31000 | W20: 12400 | X20: 3500 | Y20: 0 | Z20: 15100 | AB20: 29967 | AC20: 11987 | AD20: 3383 | AE20: 0 | AF20: 14597 | AG20: 59934 | AH20: 0 | AI20: 0 | AJ20: 119868 | AK20: 2066 | AL20: 0 | AM20: 0 | AN20: 8333 | AO20: 0 | AP20: 0 | AQ20: 51601 | AR20: 200 | AS20: 2000 | AT20: 1800 | AU20: 0 | AV20: 0 | AW20: 62000 | AX20: 59934 | AY20: 14399 | AZ20: 47601 | BA20: Advance Deducted 8333/income Tax
A21: 20 | B21: A2 | C21: 40180 | E21: 25000 | F21: 12500 | G21: 5000 | H21: 3500 | I21: 0 | J21: 4000 | K21: 44743 | L21: 44738 | M21: 44767 | N21: 30 | O21: N | P21: N | Q21: 30 | R21: 29 | S21: 0 | T21: 0 | U21: 0 | V21: 12500 | W21: 5000 | X21: 3500 | Y21: 0 | Z21: 4000 | AB21: 12500 | AC21: 5000 | AD21: 3500 | AE21: 0 | AF21: 4000 | AG21: 25000 | AH21: 0 | AI21: 0 | AJ21: 50000 | AK21: 0 | AL21: 0 | AM21: 0 | AN21: 0 | AO21: 0 | AP21: 0 | AQ21: 25000 | AR21: 200 | AS21: 0 | AT21: 1500 | AU21: 0 | AV21: 438 | AW21: 25000 | AX21: 25000 | AY21: 2138 | AZ21: 22862 | BA21: ESI should be deducted because ESI is deducted in May month it will continue up to sep irrespective of salary
A22: 21 | B22: A3 | C22: 40181 | E22: 11000 | F22: 5500 | G22: 2200 | H22: 0 | I22: 0 | J22: 3300 | K22: 44743 | L22: 44738 | M22: 44767 | N22: 30 | O22: N | P22: N | Q22: 30 | R22: 29 | S22: 0 | T22: 0 | U22: 0 | V22: 5500 | W22: 2200 | X22: 0 | Y22: 0 | Z22: 3300 | AB22: 5500 | AC22: 2200 | AD22: 0 | AE22: 0 | AF22: 3300 | AG22: 11000 | AH22: 0 | AI22: 0 | AJ22: 22000 | AK22: 0 | AL22: 0 | AM22: 0 | AN22: 0 | AO22: 0 | AP22: 0 | AQ22: 11000 | AR22: 0 | AS22: 0 | AT22: 660 | AU22: 193 | AV22: 193 | AW22: 11000 | AX22: 11000 | AY22: 853 | AZ22: 10147 | BA22: ESI is deducted because employee salary is under ESI slab
A23: 22 | B23: A4 | C23: 40182 | E23: 25000 | F23: 12500 | G23: 5000 | H23: 3500 | I23: 0 | J23: 4000 | K23: 44743 | L23: 44738 | M23: 44767 | N23: 30 | O23: N | P23: N | Q23: 30 | R23: 29 | S23: 0 | T23: 0 | U23: 0 | V23: 12500 | W23: 5000 | X23: 3500 | Y23: 0 | Z23: 4000 | AB23: 12500 | AC23: 5000 | AD23: 3500 | AE23: 0 | AF23: 4000 | AG23: 25000 | AH23: 0 | AI23: 0 | AJ23: 50000 | AK23: 0 | AL23: 0 | AM23: 0 | AN23: 0 | AO23: 0 | AP23: 2000 | AQ23: 23000 | AR23: 200 | AS23: 0 | AT23: 1500 | AU23: 0 | AV23: 0 | AW23: 25000 | AX23: 23000 | AY23: 3700 | AZ23: 21300 | BA23: Paycut added 2000
A24: 23 | B24: A5 | C24: 40183 | E24: 32000 | F24: 16000 | G24: 6400 | H24: 3500 | I24: 0 | J24: 6100 | K24: 44743 | L24: 44738 | M24: 44767 | N24: 30 | O24: N | P24: N | Q24: 30 | R24: 29 | S24: 0 | T24: 0 | U24: 0 | V24: 16000 | W24: 6400 | X24: 3500 | Y24: 0 | Z24: 6100 | AB24: 16000 | AC24: 6400 | AD24: 3500 | AE24: 0 | AF24: 6100 | AG24: 32000 | AH24: 0 | AI24: 0 | AJ24: 64000 | AK24: 0 | AL24: 0 | AM24: 0 | AN24: 0 | AO24: 0 | AP24: 0 | AQ24: 32000 | AR24: 200 | AS24: 0 | AT24: 1800 | AU24: 0 | AV24: 0 | AW24: 32000 | AX24: 32000 | AY24: 2000 | AZ24: 30000
A25: 24 | AK25: 0
A26: 25 | B26: A1 | C26: 40180 | E26: 62000 | F26: 31000 | G26: 12400 | H26: 3500 | I26: 0 | J26: 15100 | K26: 44774 | L26: 44768 | M26: 44798 | N26: 31 | O26: N | P26: N | Q26: 31 | R26: 29 | S26: 1 | T26: 0 | U26: 0 | V26: 31000 | W26: 12400 | X26: 3500 | Y26: 0 | Z26: 15100 | AB26: 30000 | AC26: 12000 | AD26: 3387 | AE26: 0 | AF26: 14613 | AG26: 60000 | AH26: 0 | AI26: 0 | AJ26: 120000 | AK26: 2000 | AL26: 0 | AM26: 0 | AN26: 8333 | AO26: 0 | AP26: 0 | AQ26: 51667 | AR26: 200 | AS26: 200 | AT26: 1800 | AU26: 0 | AV26: 0 | AW26: 62000 | AX26: 60000 | AY26: 12533 | AZ26: 49467 | BA26: Advance Deducted 8333/income tax
A27: 26 | B27: A2 | C27: 40180 | E27: 17000 | F27: 8500 | G27: 3400 | H27: 3500 | I27: 0 | J27: 1600 | K27: 44774 | L27: 44768 | M27: 44798 | N27: 31 | O27: N | P27: N | Q27: 31 | R27: 29 | S27: 0 | T27: 0 | U27: 0 | V27: 8500 | W27: 3400 | X27: 3500 | Y27: 0 | Z27: 1600 | AB27: 8500 | AC27: 3400 | AD27: 3500 | AE27: 0 | AF27: 1600 | AG27: 17000 | AH27: 0 | AI27: 0 | AJ27: 34000 | AK27: 0 | AL27: 0 | AM27: 0 | AN27: 0 | AO27: 0 | AP27: 0 | AQ27: 17000 | AR27: 150 | AS27: 0 | AT27: 1020 | AU27: 298 | AV27: 298 | AW27: 17000 | AX27: 17000 | AY27: 1468 | AZ27: 15532 | BA27: ESI should be deducted because ESI is deducted in May month it will continue up to sep irrespective of salary
A28: 27 | B28: A3 | C28: 40181 | E28: 11000 | F28: 5500 | G28: 2200 | H28: 0 | I28: 0 | J28: 3300 | K28: 44774 | L28: 44768 | M28: 44798 | N28: 31 | O28: N | P28: N | Q28: 31 | R28: 29 | S28: 0 | T28: 0 | U28: 0 | V28: 5500 | W28: 2200 | X28: 0 | Y28: 0 | Z28: 3300 | AB28: 5500 | AC28: 2200 | AD28: 0 | AE28: 0 | AF28: 3300 | AG28: 11000 | AH28: 0 | AI28: 0 | AJ28: 22000 | AK28: 0 | AL28: 0 | AM28: 0 | AN28: 0 | AO28: 0 | AP28: 0 | AQ28: 11000 | AR28: 0 | AS28: 0 | AT28: 660 | AU28: 193 | AV28: 193 | AW28: 11000 | AX28: 11000 | AY28: 853 | AZ28: 10147 | BA28: ESI is deducted because employee salary is under ESI slab
A29: 28 | B29: A4 | C29: 40182 | E29: 25000 | F29: 12500 | G29: 5000 | H29: 3500 | I29: 0 | J29: 4000 | K29: 44774 | L29: 44768 | M29: 44798 | N29: 31 | O29: N | P29: N | Q29: 31 | R29: 29 | S29: 0 | T29: 0 | U29: 0 | V29: 12500 | W29: 5000 | X29: 3500 | Y29: 0 | Z29: 4000 | AB29: 12500 | AC29: 5000 | AD29: 3500 | AE29: 0 | AF29: 4000 | AG29: 25000 | AH29: 0 | AI29: 0 | AJ29: 50000 | AK29: 0 | AL29: 0 | AM29: 0 | AN29: 0 | AO29: 0 | AP29: 2000 | AQ29: 23000 | AR29: 200 | AS29: 0 | AT29: 1500 | AU29: 0 | AV29: 0 | AW29: 25000 | AX29: 23000 | AY29: 3700 | AZ29: 21300 | BA29: paycut added 2000
A30: 29 | B30: A5 | C30: 40183 | E30: 32000 | F30: 16000 | G30: 6400 | H30: 3500 | I30: 0 | J30: 6100 | K30: 44774 | L30: 44768 | M30: 44798 | N30: 31 | O30: N | P30: N | Q30: 31 | R30: 29 | S30: 0 | T30: 0 | U30: 0 | V30: 16000 | W30: 6400 | X30: 3500 | Y30: 0 | Z30: 6100 | AB30: 16000 | AC30: 6400 | AD30: 3500 | AE30: 0 | AF30: 6100 | AG30: 32000 | AH30: 0 | AI30: 0 | AJ30: 64000 | AK30: 0 | AL30: 0 | AM30: 0 | AN30: 0 | AO30: 0 | AP30: 0 | AQ30: 32000 | AR30: 200 | AS30: 0 | AT30: 1800 | AU30: 0 | AV30: 0 | AW30: 32000 | AX30: 32000 | AY30: 2000 | AZ30: 30000
A31: 30 | AK31: 0
A32: 31 | B32: A1 | C32: 40180 | E32: 62000 | F32: 31000 | G32: 12400 | H32: 3500 | I32: 0 | J32: 15100 | K32: 44805 | L32: 44799 | M32: 44829 | N32: 31 | O32: N | P32: N | Q32: 31 | R32: 29 | S32: 1 | T32: 0 | U32: 0 | V32: 31000 | W32: 12400 | X32: 3500 | Y32: 0 | Z32: 15100 | AB32: 30000 | AC32: 12000 | AD32: 3387 | AE32: 0 | AF32: 14613 | AG32: 60000 | AH32: 0 | AI32: 0 | AJ32: 120000 | AK32: 2000 | AL32: 0 | AM32: 0 | AN32: 8333 | AO32: 0 | AP32: 2000 | AQ32: 49667 | AR32: 200 | AS32: 0 | AT32: 1800 | AU32: 0 | AV32: 0 | AW32: 62000 | AX32: 58000 | AY32: 14333 | AZ32: 47667 | BA32: Paycut added 2000/Advance Deducted 8333
A33: 32 | B33: A2 | C33: 40180 | E33: 24000 | F33: 12000 | G33: 4800 | H33: 3500 | I33: 0 | J33: 3700 | K33: 44805 | L33: 44799 | M33: 44829 | N33: 31 | O33: N | P33: N | Q33: 31 | R33: 29 | S33: 0 | T33: 0 | U33: 0 | V33: 12000 | W33: 4800 | X33: 3500 | Y33: 0 | Z33: 3700 | AB33: 12000 | AC33: 4800 | AD33: 3500 | AE33: 0 | AF33: 3700 | AG33: 24000 | AH33: 0 | AI33: 0 | AJ33: 48000 | AK33: 0 | AL33: 0 | AM33: 0 | AN33: 0 | AO33: 0 | AP33: 0 | AQ33: 24000 | AR33: 200 | AS33: 0 | AT33: 1440 | AU33: 0 | AV33: 420 | AW33: 24000 | AX33: 24000 | AY33: 2060 | AZ33: 21940 | BA33: ESI should be deducted because ESI is deducted in May month it will continue up to sep irrespective of salary
A34: 33 | B34: A3 | C34: 40181 | E34: 11000 | F34: 5500 | G34: 2200 | H34: 0 | I34: 0 | J34: 3300 | K34: 44805 | L34: 44799 | M34: 44829 | N34: 31 | O34: N | P34: N | Q34: 31 | R34: 29 | S34: 0 | T34: 0 | U34: 0 | V34: 5500 | W34: 2200 | X34: 0 | Y34: 0 | Z34: 3300 | AB34: 5500 | AC34: 2200 | AD34: 0 | AE34: 0 | AF34: 3300 | AG34: 11000 | AH34: 0 | AI34: 0 | AJ34: 22000 | AK34: 0 | AL34: 0 | AM34: 0 | AN34: 0 | AO34: 0 | AP34: 0 | AQ34: 11000 | AR34: 0 | AS34: 0 | AT34: 660 | AU34: 193 | AV34: 193 | AW34: 11000 | AX34: 11000 | AY34: 853 | AZ34: 10147 | BA34: ESI is deducted because employee salary is under ESI slab
A35: 34 | B35: A4 | C35: 40182 | E35: 25000 | F35: 12500 | G35: 5000 | H35: 3500 | I35: 0 | J35: 4000 | K35: 44805 | L35: 44799 | M35: 44829 | N35: 31 | O35: N | P35: N | Q35: 31 | R35: 29 | S35: 0 | T35: 0 | U35: 0 | V35: 12500 | W35: 5000 | X35: 3500 | Y35: 0 | Z35: 4000 | AB35: 12500 | AC35: 5000 | AD35: 3500 | AE35: 0 | AF35: 4000 | AG35: 25000 | AH35: 0 | AI35: 0 | AJ35: 50000 | AK35: 0 | AL35: 0 | AM35: 0 | AN35: 0 | AO35: 0 | AP35: 0 | AQ35: 25000 | AR35: 200 | AS35: 0 | AT35: 1500 | AU35: 0 | AV35: 0 | AW35: 25000 | AX35: 25000 | AY35: 1700 | AZ35: 23300
A36: 35 | B36: A5 | C36: 40183 | E36: 32000 | F36: 16000 | G36: 6400 | H36: 3500 | I36: 0 | J36: 6100 | K36: 44805 | L36: 44799 | M36: 44829 | N36: 31 | O36: N | P36: N | Q36: 31 | R36: 29 | S36: 0 | T36: 0 | U36: 0 | V36: 16000 | W36: 6400 | X36: 3500 | Y36: 0 | Z36: 6100 | AB36: 16000 | AC36: 6400 | AD36: 3500 | AE36: 0 | AF36: 6100 | AG36: 32000 | AH36: 0 | AI36: 0 | AJ36: 64000 | AK36: 0 | AL36: 0 | AM36: 0 | AN36: 0 | AO36: 0 | AP36: 0 | AQ36: 32000 | AR36: 200 | AS36: 0 | AT36: 1800 | AU36: 0 | AV36: 0 | AW36: 32000 | AX36: 32000 | AY36: 2000 | AZ36: 30000
A37: 36 | AK37: 0
A38: 37 | B38: A1 | C38: 40180 | E38: 62000 | F38: 31000 | G38: 12400 | H38: 3500 | I38: 0 | J38: 15100 | K38: 44835 | L38: 44830 | M38: 44859 | N38: 30 | O38: N | P38: N | Q38: 30 | R38: 1 | S38: 29 | T38: 0 | U38: 0 | V38: 31000 | W38: 12400 | X38: 3500 | Y38: 0 | Z38: 15100 | AB38: 1033 | AC38: 413 | AD38: 117 | AE38: 0 | AF38: 503 | AG38: 2066 | AH38: 0 | AI38: 0 | AJ38: 4132 | AK38: 59934 | AL38: 0 | AM38: 0 | AN38: 2 | AO38: 0 | AP38: 0 | AQ38: 2064 | AR38: 0 | AS38: 0 | AT38: 124 | AU38: 0 | AV38: 0 | AW38: 62000 | AX38: 2066 | AY38: 60060 | AZ38: 1940 | BA38: Lop Added 29days as Employee Present days are 29
A39: 38 | B39: A2 | C39: 44690 | E39: 24000 | F39: 12000 | G39: 4800 | H39: 3500 | I39: 0 | J39: 3700 | K39: 44835 | L39: 44830 | M39: 44859 | N39: 30 | O39: N | P39: N | Q39: 30 | R39: 25 | S39: 5 | T39: 0 | U39: 0 | V39: 12000 | W39: 4800 | X39: 3500 | Y39: 0 | Z39: 3700 | AB39: 10000 | AC39: 4000 | AD39: 2917 | AE39: 0 | AF39: 3083 | AG39: 20000 | AH39: 0 | AI39: 0 | AJ39: 40000 | AK39: 4000 | AL39: 0 | AM39: 0 | AN39: 0 | AO39: 0 | AP39: 1000 | AQ39: 19000 | AR39: 150 | AS39: 0 | AT39: 1200 | AU39: 0 | AV39: 0 | AW39: 24000 | AX39: 19000 | AY39: 6350 | AZ39: 17650 | BA39: ESI is not deducted because Employee salary is Not under ESI slab
A40: 39 | B40: A3 | C40: 40181 | E40: 11000 | F40: 5500 | G40: 2200 | H40: 0 | I40: 0 | J40: 3300 | K40: 44835 | L40: 44830 | M40: 44859 | N40: 30 | O40: N | P40: N | Q40: 30 | R40: 29 | S40: 0 | T40: 0 | U40: 0 | V40: 5500 | W40: 2200 | X40: 0 | Y40: 0 | Z40: 3300 | AB40: 5500 | AC40: 2200 | AD40: 0 | AE40: 0 | AF40: 3300 | AG40: 11000 | AH40: 0 | AI40: 0 | AJ40: 22000 | AK40: 0 | AL40: 0 | AM40: 0 | AN40: 0 | AO40: 0 | AP40: 0 | AQ40: 11000 | AR40: 0 | AS40: 0 | AT40: 660 | AU40: 193 | AV40: 193 | AW40: 11000 | AX40: 11000 | AY40: 853 | AZ40: 10147 | BA40: ESI is deducted because employee salary is under ESI slab
A41: 40 | B41: A4 | C41: 40182 | E41: 25000 | F41: 12500 | G41: 5000 | H41: 3500 | I41: 0 | J41: 4000 | K41: 44835 | L41: 44830 | M41: 44859 | N41: 30 | O41: N | P41: N | Q41: 30 | R41: 29 | S41: 0 | T41: 0 | U41: 0 | V41: 12500 | W41: 5000 | X41: 3500 | Y41: 0 | Z41: 4000 | AB41: 12500 | AC41: 5000 | AD41: 3500 | AE41: 0 | AF41: 4000 | AG41: 25000 | AH41: 0 | AI41: 0 | AJ41: 50000 | AK41: 0 | AL41: 0 | AM41: 0 | AN41: 0 | AO41: 0 | AP41: 0 | AQ41: 25000 | AR41: 200 | AS41: 0 | AT41: 1500 | AU41: 0 | AV41: 0 | AW41: 25000 | AX41: 25000 | AY41: 1700 | AZ41: 23300
A42: 41 | B42: A5 | C42: 40183 | E42: 45000 | F42: 22500 | G42: 9000 | H42: 3500 | I42: 2400 | J42: 7600 | K42: 44835 | L42: 44830 | M42: 44859 | N42: 30 | O42: N | P42: N | Q42: 30 | R42: 29 | S42: 0 | T42: 0 | U42: 0 | V42: 22500 | W42: 9000 | X42: 3500 | Y42: 2400 | Z42: 7600 | AB42: 22500 | AC42: 9000 | AD42: 3500 | AE42: 2400 | AF42: 7600 | AG42: 45000 | AH42: 0 | AI42: 0 | AJ42: 90000 | AK42: 0 | AL42: 0 | AM42: 0 | AN42: 3333 | AO42: 2400 | AP42: 0 | AQ42: 39267 | AR42: 200 | AS42: 2000 | AT42: 1800 | AU42: 0 | AV42: 0 | AW42: 45000 | AX42: 45000 | AY42: 9733 | AZ42: 35267 | BA42: Income tax Added
A43: 42 | AK43: 0
A44: 43 | B44: A1 | C44: 40180 | E44: 62000 | F44: 31000 | G44: 12400 | H44: 3500 | I44: 0 | J44: 15100 | K44: 44866 | L44: 44860 | M44: 44890 | N44: 31 | O44: N | P44: N | Q44: 31 | R44: 28 | S44: 1 | T44: 1 | U44: 1 | V44: 31000 | W44: 12400 | X44: 3500 | Y44: 0 | Z44: 15100 | AB44: 30000 | AC44: 12000 | AD44: 3387 | AE44: 0 | AF44: 14613 | AG44: 60000 | AH44: 0 | AI44: 0 | AJ44: 120000 | AK44: 2000 | AL44: 2000 | AM44: 2000 | AN44: 0 | AO44: 0 | AP44: 2000 | AQ44: 54000 | AR44: 200 | AS44: 0 | AT44: 1800 | AU44: 0 | AV44: 0 | AW44: 62000 | AX44: 54000 | AY44: 10000 | AZ44: 52000 | BA44: Late Coming And UnAuthorized /LOP
A45: 44 | B45: A2 | C45: 40180 | E45: 17000 | F45: 8500 | G45: 3400 | H45: 3500 | I45: 0 | J45: 1600 | K45: 44866 | L45: 44860 | M45: 44890 | N45: 31 | O45: N | P45: N | Q45: 31 | R45: 29 | S45: 0 | T45: 0 | U45: 0 | V45: 8500 | W45: 3400 | X45: 3500 | Y45: 0 | Z45: 1600 | AB45: 8500 | AC45: 3400 | AD45: 3500 | AE45: 0 | AF45: 1600 | AG45: 17000 | AH45: 1000 | AI45: 1500 | AJ45: 36500 | AK45: 0 | AL45: 0 | AM45: 0 | AN45: 0 | AO45: 0 | AP45: 0 | AQ45: 17000 | AR45: 150 | AS45: 0 | AT45: 1020 | AU45: 298 | AV45: 298 | AW45: 19500 | AX45: 19500 | AY45: 1468 | AZ45: 18032 | BA45: ESI should be deducted because ESI is deducted because Employee is under ESI Slab
A46: 45 | B46: A3 | C46: 40181 | E46: 11000 | F46: 5500 | G46: 2200 | H46: 0 | I46: 0 | J46: 3300 | K46: 44866 | L46: 44860 | M46: 44890 | N46: 31 | O46: N | P46: N | Q46: 31 | R46: 29 | S46: 0 | T46: 0 | U46: 0 | V46: 5500 | W46: 2200 | X46: 0 | Y46: 0 | Z46: 3300 | AB46: 5500 | AC46: 2200 | AD46: 0 | AE46: 0 | AF46: 3300 | AG46: 11000 | AH46: 0 | AI46: 0 | AJ46: 22000 | AK46: 0 | AL46: 0 | AM46: 0 | AN46: 0 | AO46: 0 | AP46: 0 | AQ46: 11000 | AR46: 0 | AS46: 0 | AT46: 660 | AU46: 193 | AV46: 193 | AW46: 11000 | AX46: 11000 | AY46: 853 | AZ46: 10147 | BA46: ESI is deducted because employee salary is under ESI slab
A47: 46 | B47: A4 | C47: 40182 | E47: 25000 | F47: 12500 | G47: 5000 | H47: 3500 | I47: 0 | J47: 4000 | K47: 44866 | L47: 44860 | M47: 44890 | N47: 31 | O47: N | P47: N | Q47: 31 | R47: 29 | S47: 0 | T47: 0 | U47: 0 | V47: 12500 | W47: 5000 | X47: 3500 | Y47: 0 | Z47: 4000 | AB47: 12500 | AC47: 5000 | AD47: 3500 | AE47: 0 | AF47: 4000 | AG47: 25000 | AH47: 0 | AI47: 2000 | AJ47: 52000 | AK47: 0 | AL47: 0 | AM47: 0 | AN47: 0 | AO47: 0 | AP47: 0 | AQ47: 25000 | AR47: 200 | AS47: 0 | AT47: 1500 | AU47: 0 | AV47: 0 | AW47: 27000 | AX47: 27000 | AY47: 1700 | AZ47: 25300
A48: 47 | B48: A5 | C48: 44860 | E48: 32000 | F48: 16000 | G48: 6400 | H48: 3500 | I48: 0 | J48: 6100 | K48: 44866 | L48: 44860 | M48: 44890 | N48: 31 | O48: N | P48: N | Q48: 31 | R48: 25 | S48: 4 | T48: 0 | U48: 0 | V48: 16000 | W48: 6400 | X48: 3500 | Y48: 0 | Z48: 6100 | AB48: 13935 | AC48: 5574 | AD48: 3048 | AE48: 0 | AF48: 5313 | AG48: 27870 | AH48: 0 | AI48: 0 | AJ48: 55740 | AK48: 4130 | AL48: 0 | AM48: 0 | AN48: 3333 | AO48: 0 | AP48: 0 | AQ48: 24537 | AR48: 200 | AS48: 0 | AT48: 1672 | AU48: 0 | AV48: 0 | AW48: 32000 | AX48: 27870 | AY48: 9335 | AZ48: 22665
A49: 48 | AK49: 0
A50: 49 | B50: A1 | C50: 40180 | E50: 62000 | F50: 31000 | G50: 12400 | H50: 3500 | I50: 0 | J50: 15100 | K50: 44896 | L50: 44891 | M50: 44920 | N50: 30 | O50: N | P50: N | Q50: 30 | R50: 1 | S50: 29 | T50: 0 | U50: 0 | V50: 31000 | W50: 12400 | X50: 3500 | Y50: 0 | Z50: 15100 | AB50: 1033 | AC50: 413 | AD50: 117 | AE50: 0 | AF50: 503 | AG50: 2066 | AH50: 0 | AI50: 0 | AJ50: 4132 | AK50: 59934 | AL50: 0 | AM50: 0 | AN50: 0 | AO50: 0 | AP50: 0 | AQ50: 2066 | AR50: 0 | AS50: 0 | AT50: 124 | AU50: 0 | AV50: 0 | AW50: 62000 | AX50: 2066 | AY50: 60058 | AZ50: 1942 | BA50: Lop Added 29days as Employee Present days are 29
A51: 50 | B51: A2 | C51: 40181 | E51: 50000 | F51: 25000 | G51: 10000 | H51: 3500 | I51: 0 | J51: 11500 | K51: 44896 | L51: 44891 | M51: 44920 | N51: 30 | O51: N | P51: N | Q51: 30 | R51: 25 | S51: 5 | T51: 0 | U51: 0 | V51: 25000 | W51: 10000 | X51: 3500 | Y51: 0 | Z51: 11500 | AB51: 20833 | AC51: 8333 | AD51: 2917 | AE51: 0 | AF51: 9583 | AG51: 41666 | AH51: 1000 | AI51: 0 | AJ51: 84332 | AK51: 8334 | AL51: 0 | AM51: 0 | AN51: 0 | AO51: 0 | AP51: 1000 | AQ51: 40666 | AR51: 200 | AS51: 0 | AT51: 1800 | AU51: 0 | AV51: 730 | AW51: 51000 | AX51: 41666 | AY51: 12064 | AZ51: 38936 | BA51: ESI IS Deducted Because Employe Have An ESI Deduction in last Month
A52: 51 | B52: A3 | C52: 40181 | E52: 11000 | F52: 5500 | G52: 2200 | H52: 0 | I52: 0 | J52: 3300 | K52: 44896 | L52: 44891 | M52: 44920 | N52: 30 | O52: N | P52: N | Q52: 30 | R52: 29 | S52: 0 | T52: 0 | U52: 0 | V52: 5500 | W52: 2200 | X52: 0 | Y52: 0 | Z52: 3300 | AB52: 5500 | AC52: 2200 | AD52: 0 | AE52: 0 | AF52: 3300 | AG52: 11000 | AH52: 0 | AI52: 2000 | AJ52: 24000 | AK52: 0 | AL52: 0 | AM52: 0 | AN52: 0 | AO52: 0 | AP52: 0 | AQ52: 11000 | AR52: 0 | AS52: 0 | AT52: 660 | AU52: 193 | AV52: 193 | AW52: 13000 | AX52: 13000 | AY52: 853 | AZ52: 12147 | BA52: ESI is deducted because employee salary is under ESI slab
A53: 52 | B53: A4 | C53: 40182 | E53: 25000 | F53: 12500 | G53: 5000 | H53: 3500 | I53: 0 | J53: 4000 | K53: 44896 | L53: 44891 | M53: 44920 | N53: 30 | O53: N | P53: N | Q53: 30 | R53: 29 | S53: 0 | T53: 0 | U53: 0 | V53: 12500 | W53: 5000 | X53: 3500 | Y53: 0 | Z53: 4000 | AB53: 12500 | AC53: 5000 | AD53: 3500 | AE53: 0 | AF53: 4000 | AG53: 25000 | AH53: 0 | AI53: 0 | AJ53: 50000 | AK53: 0 | AL53: 0 | AM53: 0 | AN53: 0 | AO53: 0 | AP53: 0 | AQ53: 25000 | AR53: 200 | AS53: 0 | AT53: 1500 | AU53: 0 | AV53: 0 | AW53: 25000 | AX53: 25000 | AY53: 1700 | AZ53: 23300
A54: 53 | B54: A5 | C54: 40183 | E54: 45000 | F54: 22500 | G54: 9000 | H54: 3500 | I54: 2400 | J54: 7600 | K54: 44896 | L54: 44891 | M54: 44920 | N54: 30 | O54: N | P54: N | Q54: 30 | R54: 29 | S54: 0 | T54: 0 | U54: 0 | V54: 22500 | W54: 9000 | X54: 3500 | Y54: 2400 | Z54: 7600 | AB54: 22500 | AC54: 9000 | AD54: 3500 | AE54: 2400 | AF54: 7600 | AG54: 45000 | AH54: 0 | AI54: 0 | AJ54: 90000 | AK54: 0 | AL54: 0 | AM54: 0 | AN54: 3333 | AO54: 2400 | AP54: 0 | AQ54: 39267 | AR54: 200 | AS54: 2000 | AT54: 1800 | AU54: 0 | AV54: 0 | AW54: 45000 | AX54: 45000 | AY54: 9733 | AZ54: 35267 | BA54: Income tax Added
A55: 54 | AK55: 0
A56: 55 | B56: A1 | C56: 40180 | E56: 62000 | F56: 31000 | G56: 12400 | H56: 3500 | I56: 0 | J56: 15100 | K56: 44927 | L56: 44921 | M56: 44951 | N56: 31 | O56: N | P56: N | Q56: 31 | R56: 29 | S56: 1 | T56: 1 | U56: 0 | V56: 31000 | W56: 12400 | X56: 3500 | Y56: 0 | Z56: 15100 | AB56: 30000 | AC56: 12000 | AD56: 3387 | AE56: 0 | AF56: 14613 | AG56: 60000 | AH56: 0 | AI56: 0 | AJ56: 120000 | AK56: 2000 | AL56: 0 | AM56: 2000 | AN56: 0 | AO56: 0 | AP56: 2000 | AQ56: 56000 | AR56: 200 | AS56: 0 | AT56: 1800 | AU56: 0 | AV56: 0 | AW56: 62000 | AX56: 56000 | AY56: 8000 | AZ56: 54000 | BA56: Paycut added 2000/LC Amount 2000
A57: 56 | B57: A2 | C57: 40180 | E57: 44000 | F57: 22000 | G57: 8800 | H57: 3500 | I57: 0 | J57: 9700 | K57: 44927 | L57: 44921 | M57: 44951 | N57: 31 | O57: N | P57: N | Q57: 31 | R57: 29 | S57: 0 | T57: 0 | U57: 0 | V57: 22000 | W57: 8800 | X57: 3500 | Y57: 0 | Z57: 9700 | AB57: 22000 | AC57: 8800 | AD57: 3500 | AE57: 0 | AF57: 9700 | AG57: 44000 | AH57: 0 | AI57: 0 | AJ57: 88000 | AK57: 0 | AL57: 0 | AM57: 0 | AN57: 0 | AO57: 0 | AP57: 0 | AQ57: 44000 | AR57: 200 | AS57: 0 | AT57: 1800 | AU57: 0 | AV57: 770 | AW57: 44000 | AX57: 44000 | AY57: 2770 | AZ57: 41230 | BA57: ESI IS Deducted Because Employe Have An ESI Deduction in last Month
A58: 57 | B58: A3 | C58: 40181 | E58: 11000 | F58: 5500 | G58: 2200 | H58: 0 | I58: 0 | J58: 3300 | K58: 44927 | L58: 44921 | M58: 44951 | N58: 31 | O58: N | P58: N | Q58: 31 | R58: 29 | S58: 0 | T58: 0 | U58: 0 | V58: 5500 | W58: 2200 | X58: 0 | Y58: 0 | Z58: 3300 | AB58: 5500 | AC58: 2200 | AD58: 0 | AE58: 0 | AF58: 3300 | AG58: 11000 | AH58: 0 | AI58: 0 | AJ58: 22000 | AK58: 0 | AL58: 0 | AM58: 0 | AN58: 0 | AO58: 0 | AP58: 0 | AQ58: 11000 | AR58: 0 | AS58: 0 | AT58: 660 | AU58: 193 | AV58: 193 | AW58: 11000 | AX58: 11000 | AY58: 853 | AZ58: 10147 | BA58: ESI is deducted because employee salary is under ESI slab
A59: 58 | B59: A4 | C59: 40182 | E59: 25000 | F59: 12500 | G59: 5000 | H59: 3500 | I59: 0 | J59: 4000 | K59: 44927 | L59: 44921 | M59: 44951 | N59: 31 | O59: N | P59: N | Q59: 31 | R59: 29 | S59: 0 | T59: 0 | U59: 0 | V59: 12500 | W59: 5000 | X59: 3500 | Y59: 0 | Z59: 4000 | AB59: 12500 | AC59: 5000 | AD59: 3500 | AE59: 0 | AF59: 4000 | AG59: 25000 | AH59: 0 | AI59: 0 | AJ59: 50000 | AK59: 0 | AL59: 0 | AM59: 0 | AN59: 0 | AO59: 0 | AP59: 0 | AQ59: 25000 | AR59: 200 | AS59: 0 | AT59: 1500 | AU59: 0 | AV59: 0 | AW59: 25000 | AX59: 25000 | AY59: 1700 | AZ59: 23300
A60: 59 | B60: A5 | C60: 40183 | E60: 32000 | F60: 16000 | G60: 6400 | H60: 3500 | I60: 0 | J60: 6100 | K60: 44927 | L60: 44921 | M60: 44951 | N60: 31 | O60: N | P60: N | Q60: 31 | R60: 29 | S60: 0 | T60: 0 | U60: 0 | V60: 16000 | W60: 6400 | X60: 3500 | Y60: 0 | Z60: 6100 | AB60: 16000 | AC60: 6400 | AD60: 3500 | AE60: 0 | AF60: 6100 | AG60: 32000 | AH60: 0 | AI60: 0 | AJ60: 64000 | AK60: 0 | AL60: 0 | AM60: 0 | AN60: 3333 | AO60: 0 | AP60: 0 | AQ60: 28667 | AR60: 200 | AS60: 0 | AT60: 1800 | AU60: 0 | AV60: 0 | AW60: 32000 | AX60: 32000 | AY60: 5333 | AZ60: 26667
A61: 60 | AK61: 0
A62: 61 | B62: A1 | C62: 40180 | E62: 62000 | F62: 31000 | G62: 12400 | H62: 3500 | I62: 0 | J62: 15100 | K62: 44958 | L62: 44952 | M62: 44982 | N62: 31 | O62: N | P62: N | Q62: 31 | R62: 29 | S62: 1 | T62: 0 | U62: 0 | V62: 31000 | W62: 12400 | X62: 3500 | Y62: 0 | Z62: 15100 | AB62: 30000 | AC62: 12000 | AD62: 3387 | AE62: 0 | AF62: 14613 | AG62: 60000 | AH62: 0 | AI62: 0 | AJ62: 120000 | AK62: 2000 | AL62: 0 | AM62: 0 | AN62: 0 | AO62: 0 | AP62: 2000 | AQ62: 58000 | AR62: 200 | AS62: 0 | AT62: 1800 | AU62: 0 | AV62: 0 | AW62: 62000 | AX62: 58000 | AY62: 6000 | AZ62: 56000 | BA62: Paycut added 2000/Advance Deducted 8333
A63: 62 | B63: A2 | C63: 40180 | E63: 34000 | F63: 17000 | G63: 6800 | H63: 3500 | I63: 0 | J63: 6700 | K63: 44958 | L63: 44952 | M63: 44982 | N63: 31 | O63: N | P63: N | Q63: 31 | R63: 29 | S63: 0 | T63: 0 | U63: 0 | V63: 17000 | W63: 6800 | X63: 3500 | Y63: 0 | Z63: 6700 | AB63: 17000 | AC63: 6800 | AD63: 3500 | AE63: 0 | AF63: 6700 | AG63: 34000 | AH63: 0 | AI63: 0 | AJ63: 68000 | AK63: 0 | AL63: 0 | AM63: 0 | AN63: 0 | AO63: 0 | AP63: 0 | AQ63: 34000 | AR63: 200 | AS63: 0 | AT63: 1800 | AU63: 0 | AV63: 595 | AW63: 34000 | AX63: 34000 | AY63: 2595 | AZ63: 31405 | BA63: ESI IS Deducted Because Employe Have An ESI Deduction in last Month
A64: 63 | B64: A3 | C64: 40181 | E64: 11000 | F64: 5500 | G64: 2200 | H64: 0 | I64: 0 | J64: 3300 | K64: 44958 | L64: 44952 | M64: 44982 | N64: 31 | O64: N | P64: N | Q64: 31 | R64: 29 | S64: 0 | T64: 0 | U64: 0 | V64: 5500 | W64: 2200 | X64: 0 | Y64: 0 | Z64: 3300 | AB64: 5500 | AC64: 2200 | AD64: 0 | AE64: 0 | AF64: 3300 | AG64: 11000 | AH64: 0 | AI64: 0 | AJ64: 22000 | AK64: 0 | AL64: 0 | AM64: 0 | AN64: 0 | AO64: 0 | AP64: 0 | AQ64: 11000 | AR64: 0 | AS64: 0 | AT64: 660 | AU64: 193 | AV64: 193 | AW64: 11000 | AX64: 11000 | AY64: 853 | AZ64: 10147 | BA64: ESI is deducted because employee salary is under ESI slab
A65: 64 | B65: A4 | C65: 40182 | E65: 25000 | F65: 12500 | G65: 5000 | H65: 3500 | I65: 0 | J65: 4000 | K65: 44958 | L65: 44952 | M65: 44982 | N65: 31 | O65: N | P65: N | Q65: 31 | R65: 29 | S65: 0 | T65: 0 | U65: 0 | V65: 12500 | W65: 5000 | X65: 3500 | Y65: 0 | Z65: 4000 | AB65: 12500 | AC65: 5000 | AD65: 3500 | AE65: 0 | AF65: 4000 | AG65: 25000 | AH65: 0 | AI65: 0 | AJ65: 50000 | AK65: 0 | AL65: 0 | AM65: 0 | AN65: 0 | AO65: 0 | AP65: 0 | AQ65: 25000 | AR65: 200 | AS65: 0 | AT65: 1500 | AU65: 0 | AV65: 0 | AW65: 25000 | AX65: 25000 | AY65: 1700 | AZ65: 23300
A66: 65 | B66: A5 | C66: 40183 | D66: 44962 | E66: 32000 | F66: 16000 | G66: 6400 | H66: 3500 | I66: 0 | J66: 6100 | K66: 44958 | L66: 44952 | M66: 44982 | N66: 31 | O66: N | P66: Y | Q66: 11 | R66: 11 | S66: 0 | T66: 0 | U66: 0 | V66: 5677 | W66: 2271 | X66: 1242 | Y66: 0 | Z66: 2165 | AB66: 5677 | AC66: 2271 | AD66: 1242 | AE66: 0 | AF66: 2165 | AG66: 11355 | AH66: 0 | AI66: 0 | AJ66: 22710 | AK66: 0 | AL66: 0 | AM66: 0 | AN66: 3333 | AO66: 0 | AP66: 0 | AQ66: 28667 | AR66: 0 | AS66: 0 | AT66: 681 | AU66: 0 | AV66: 0 | AW66: 11355 | AX66: 11355 | AY66: 4014 | AZ66: 7341
A67: 66 | B67: A6 | C67: 44973 | E67: 31000 | F67: 15500 | G67: 6200 | H67: 3500 | I67: 0 | J67: 5800 | K67: 44958 | L67: 44952 | M67: 44982 | N67: 31 | O67: Y | P67: N | Q67: 10 | R67: 10 | S67: 0 | T67: 0 | U67: 0 | V67: 5000 | W67: 2000 | X67: 1129 | Y67: 0 | Z67: 1871 | AB67: 5000 | AC67: 2000 | AD67: 1129 | AE67: 0 | AF67: 1871 | AG67: 10000 | AH67: 0 | AI67: 0 | AJ67: 20000 | AK67: 0 | AL67: 0 | AM67: 0 | AN67: 0 | AO67: 0 | AP67: 0 | AQ67: 31000 | AR67: 0 | AS67: 0 | AT67: 600 | AU67: 0 | AV67: 0 | AW67: 10000 | AX67: 10000 | AY67: 600 | AZ67: 9400 | BA67: New employee
A68: 67 | B68: A7 | C68: 44967 | D68: 44976 | E68: 31000 | F68: 15500 | G68: 6200 | H68: 3500 | I68: 0 | J68: 5800 | K68: 44958 | L68: 44952 | M68: 44982 | N68: 31 | O68: Y | P68: Y | Q68: 10 | R68: 10 | S68: 0 | T68: 0 | U68: 0 | V68: 5000 | W68: 2000 | X68: 1129 | Y68: 0 | Z68: 1871 | AB68: 5000 | AC68: 2000 | AD68: 1129 | AE68: 0 | AF68: 1871 | AG68: 10000 | AH68: 0 | AI68: 0 | AJ68: 20000 | AK68: 0 | AL68: 0 | AM68: 0 | AN68: 0 | AO68: 0 | AP68: 0 | AQ68: 31000 | AR68: 0 | AS68: 0 | AT68: 600 | AU68: 0 | AV68: 0 | AW68: 10000 | AX68: 10000 | AY68: 600 | AZ68: 9400 | BA68: New employee
A69: 67 | AK69: 0
A70: 68 | B70: A1 | C70: 40180 | E70: 62000 | F70: 31000 | G70: 12400 | H70: 3500 | I70: 0 | J70: 15100 | K70: 44986 | L70: 44983 | M70: 45010 | N70: 28 | O70: N | P70: N | Q70: 28 | R70: 24 | S70: 1 | T70: 1 | U70: 2 | V70: 31000 | W70: 12400 | X70: 3500 | Y70: 0 | Z70: 15100 | AB70: 29893 | AC70: 11957 | AD70: 3375 | AE70: 0 | AF70: 14561 | AG70: 59786 | AH70: 1000 | AI70: 2000 | AJ70: 122572 | AK70: 2214 | AL70: 4429 | AM70: 2214 | AN70: 0 | AO70: 0 | AP70: 2000 | AQ70: 51143 | AR70: 200 | AS70: 2000 | AT70: 1800 | AU70: 0 | AV70: 0 | AW70: 65000 | AX70: 54143 | AY70: 14857 | AZ70: 50143 | BA70: Paycut added 2000/Arears And Incentives Added /Lop/UA/LC/income tax added
A71: 69 | B71: A2 | C71: 40180 | E71: 48000 | F71: 24000 | G71: 9600 | H71: 3500 | I71: 0 | J71: 10900 | K71: 44986 | L71: 44983 | M71: 45010 | N71: 28 | O71: N | P71: N | Q71: 28 | R71: 23 | S71: 1 | T71: 1 | U71: 3 | V71: 24000 | W71: 9600 | X71: 3500 | Y71: 0 | Z71: 10900 | AB71: 23143 | AC71: 9257 | AD71: 3375 | AE71: 0 | AF71: 10511 | AG71: 46286 | AH71: 0 | AI71: 0 | AJ71: 92572 | AK71: 1714 | AL71: 5143 | AM71: 1714 | AN71: 0 | AO71: 0 | AP71: 0 | AQ71: 39429 | AR71: 200 | AS71: 0 | AT71: 1800 | AU71: 0 | AV71: 811 | AW71: 48000 | AX71: 39429 | AY71: 11382 | AZ71: 36618 | BA71: ESI IS Deducted Because Employe Have An ESI Deduction in last Month/Lop/UA/LC
A72: 70 | B72: A3 | C72: 40181 | E72: 11000 | F72: 5500 | G72: 2200 | H72: 0 | I72: 0 | J72: 3300 | K72: 44986 | L72: 44983 | M72: 45010 | N72: 28 | O72: N | P72: N | Q72: 28 | R72: 22 | S72: 1 | T72: 1 | U72: 4 | V72: 5500 | W72: 2200 | X72: 0 | Y72: 0 | Z72: 3300 | AB72: 5304 | AC72: 2121 | AD72: 0 | AE72: 0 | AF72: 3182 | AG72: 10607 | AH72: 0 | AI72: 0 | AJ72: 21214 | AK72: 393 | AL72: 1571 | AM72: 393 | AN72: 0 | AO72: 0 | AP72: 0 | AQ72: 8643 | AR72: 0 | AS72: 0 | AT72: 636 | AU72: 186 | AV72: 186 | AW72: 11000 | AX72: 8643 | AY72: 3179 | AZ72: 7821 | BA72: ESI is deducted because employee salary is under ESI slab/Lop/UA/LC
A73: 71 | B73: A4 | C73: 40182 | E73: 25000 | F73: 12500 | G73: 5000 | H73: 3500 | I73: 0 | J73: 4000 | K73: 44986 | L73: 44983 | M73: 45010 | N73: 28 | O73: N | P73: N | Q73: 28 | R73: 21 | S73: 1 | T73: 1 | U73: 5 | V73: 12500 | W73: 5000 | X73: 3500 | Y73: 0 | Z73: 4000 | AB73: 12054 | AC73: 4821 | AD73: 3375 | AE73: 0 | AF73: 3857 | AG73: 24107 | AH73: 0 | AI73: 0 | AJ73: 48214 | AK73: 893 | AL73: 4464 | AM73: 893 | AN73: 0 | AO73: 0 | AP73: 1500 | AQ73: 17250 | AR73: 150 | AS73: 0 | AT73: 1446 | AU73: 0 | AV73: 0 | AW73: 25000 | AX73: 17250 | AY73: 9346 | AZ73: 15654 | BA73: Paycut Added.Lop/UA/LC
A74: 72 | B74: A6 | C74: 44973 | E74: 32000 | F74: 16000 | G74: 6400 | H74: 3500 | I74: 0 | J74: 6100 | K74: 44986 | L74: 44983 | M74: 45010 | N74: 28 | O74: N | P74: N | Q74: 28 | R74: 20 | S74: 1 | T74: 1 | U74: 6 | V74: 16000 | W74: 6400 | X74: 3500 | Y74: 0 | Z74: 6100 | AB74: 15429 | AC74: 6171 | AD74: 3375 | AE74: 0 | AF74: 5882 | AG74: 30857 | AH74: 0 | AI74: 2000 | AJ74: 63714 | AK74: 1143 | AL74: 6857 | AM74: 1143 | AN74: 0 | AO74: 0 | AP74: 0 | AQ74: 22857 | AR74: 200 | AS74: 0 | AT74: 1800 | AU74: 0 | AV74: 0 | AW74: 34000 | AX74: 24857 | AY74: 11143 | AZ74: 22857 | BA74: Incentives Added./Lop/UA/LC

Sheet Sheet1
E4: 44952 | F4: 1
E5: =E4+1 -> 44953 | F5: 1
E6: =E5+1 -> 44954 | F6: 1
E7: =E6+1 -> 44955 | F7: 1
E8: =E7+1 -> 44956 | F8: 1
E9: =E8+1 -> 44957 | F9: 1
E10: =E9+1 -> 44958 | F10: 1
E11: =E10+1 -> 44959 | F11: 1
E12: =E11+1 -> 44960 | F12: 1
E13: =E12+1 -> 44961 | F13: 1
E14: =E13+1 -> 44962 | F14: 1
E15: =E14+1 -> 44963
E16: =E15+1 -> 44964
E17: =E16+1 -> 44965
E18: =E17+1 -> 44966
E19: =E18+1 -> 44967
E20: =E19+1 -> 44968
E21: =E20+1 -> 44969
E22: =E21+1 -> 44970
E23: =E22+1 -> 44971
E24: =E23+1 -> 44972
E25: =E24+1 -> 44973
E26: =E25+1 -> 44974
... E34: =E33+1 -> 44982

Sheet HRADeclaration
A1: Employee Code | B1: LandLord | C1: Pan | D1: City | E1: Address | F1: Amount | G1: RentalFrom | H1: RentalTo
A2: A1 | B2: Srikanth | C2: KLMPV5345K | D2: Hyd | E2: Ameerpet | F2: 8000 | G2: 44652 | H2: 45016
A3: A2 | B3: Chishtheshwar | C3: SMLPS6574K | D3: NZB | E3: AnnaSagar | F3: 4000 | G3: 44652 | H3: 45016
A4: B1 | B4: Test | C4: KLMPV5345K | D4: Hyd | E4: Ameerpet | F4: 15000 | G4: 44652 | H4: 45016

Sheet HomeLoanPay
A1: Employee Code | B1: LenderPAN | C1: NameOfLender | D1: Principle | E1: InterestPaid
A2: A3 | B2: WRDFS3456K | C2: VAMSHI | D2: 2000 | E2: 1200
A3: A2 | B3: DRDFS7456K | C3: RAJ | D3: 2000 | E3: 1500
A4: B1 | B4: DRDFS7456K | C4: RAJ | D4: 80000 | E4: 180000

Sheet LetOutProperty
A1: Employee Code | B1: AnnualRentReceived | C1: MunicipalTaxPaid | D1: NetAnnualValue | E1: StandardDeduction | F1: RepayingHomeLoan | G1: InterestPaid | H1: Principle | I1: NameOfLender | J1: LenderPAN | K1: NetIncome
A2: A1 | B2: 50000 | C2: 2000 | D2: 70000 | E2: 10000 | F2: TRUE | G2: 5000 | H2: 1000 | I2: Vishnu | J2: AYSSP3420K | K2: 100000
A3: A2 | B3: 40000 | C3: 1500 | D3: 50000 | E3: 12000 | F3: TRUE | G3: 5000 | H3: 1000 | I3: srikanth | J3: AYSSP3720K | K3: 120000
A4: B1 | B4: 40000 | C4: 1500 | D4: =B4-C4 -> 38500 | E4: 12000 | F4: TRUE | G4: 50000 | H4: 1000 | I4: srikanth | J4: AYSSP3720K | K4: 120000

Sheet Section6A80C
A1: Employee Code | B1: Name | C1: Amount
A2: A1 | B2: Contribution to ULIP of LIC | C2: 12000
A3: A2 | B3: Contribution to ULIP of LIC | C3: 15000
A4: B1 | B4: Contribution to ULIP of LIC | C4: 60000

Sheet Section6A80D
A1: Employee Code | B1: Name | C1: Amount
A2: A1 | B2: Medical Bills | C2: 20000
A3: A2 | B3: Medical Bills | C3: 25000
A4: B1 | B4: Medical Bills | C4: 35000

Sheet Section6AOther
A1: Employee Code | B1: Name | C1: Amount
A2: A1 | B2: Donation to Chief Minister’s Relief Fund | C2: 25000
A3: A2 | B3: Donation to Chief Minister’s Relief Fund | C3: 12000
A4: B1 | B4: Donation to Chief Minister’s Relief Fund | C4: 12000

Sheet PrevEmployment
A1: Employee Code | B1: EncashmentExceptions | C1: ProvisionalFund | D1: ProfessionalTax | E1: IncomeTax | F1: IncomeAfterException
A2: A1 | B2: 23000 | C2: 1200 | D2: 100 | E2: 2000 | F2: 1800
A3: A2 | B3: 20000 | C3: 1000 | D3: 200 | E3: 2000 | F3: 1200

Sheet OtherIncomeSources
A1: Employee Code | B1: InterestOnFD | C1: InterestOnSaving | D1: OtherSources
A2: A1 | B2: 1200 | C2: 1500 | D2: 2000
A3: A2 | B3: 1000 | C3: 2000 | D3: 1200
A4: B1 | B4: 0 | C4: 0 | D4: 20000

Sheet Bonus
A1: Employee Code | B1: Added Date | C1: Amount
A2: A1 | B2: 44805 | C2: 1500
A3: A2 | B3: 44806 | C3: 2000
A4: B1 | B4: 44807 | C4: 2000
